Workbook
Name ExclList: Inputs!$B$26:$B$30
Name FX_Ccy: Inputs!$B$16:$B$23
Name FX_Rate: Inputs!$C$16:$C$23
Name N_Co: Universe!$G$2
Name PriceDiv: Inputs!$C$13
Name ScreenDate: Inputs!$C$11

Sheet Inputs
A1: Inputs
B3: Metric | C3: Weight | D3: Better when
B4: EV/EBIT | C4: 0.3 | D4: Lower
B5: FCF yield | C5: 0.25 | D5: Higher
B6: Cash Conversion | C6: 0.2 | D6: Higher
B7: Net Debt/EBITDA | C7: 0.15 | D7: Lower
B8: Revenue CAGR | C8: 0.1 | D8: Higher
B9: Total | C9: =SUM(C4:C8) -> 1
B11: Screen Date | C11: 46295
B12: Price quoted in, | C12: Pounds
B13: Price divisor | C13: =IF(C12="Pence",100,1) -> 1
B15: Currency | C15: GBP per 1 unit
B16: GBP | C16: 1
B17: USD | C17: 0.7528
B18: EUR | C18: 0.855
B25: Excluded Sectors
B26: Financials
B27: Real Estate

Sheet Universe
F2: Included: | G2: =COUNTIF(G6:G305,"Include") -> 119
A5: Ticker | B5: Company | C5: ISIN | D5: Sector | E5: Auto status | F5: Override | G5: Final Status | H5: Notes
A6: 3IN | B6: 3i Infrastructure | C6: JE00BF5FX167 | D6: Financials | E6: =IF($A6="","",IF(COUNTIF(ExclList,$D6)>0,"Exclude","Include")) -> Exclude | G6: =IF($A6="","",IF($F6<>"",$F6,$E6)) -> Exclude
A7: FOUR | B7: 4imprint | C7: GB0006640972 | D7: Consumer Discretionary | E7: =IF($A7="","",IF(COUNTIF(ExclList,$D7)>0,"Exclude","Include")) -> Include | G7: =IF($A7="","",IF($F7<>"",$F7,$E7)) -> Include
A8: AAS | B8: Aberdeen Asia Focus | C8: GB00BMF19B58 | D8: Financials | E8: =IF($A8="","",IF(COUNTIF(ExclList,$D8)>0,"Exclude","Include")) -> Exclude | G8: =IF($A8="","",IF($F8<>"",$F8,$E8)) -> Exclude
A9: ASL | B9: Aberforth Smaller Companies Trust | C9: GB0000066554 | D9: Financials | E9: =IF($A9="","",IF(COUNTIF(ExclList,$D9)>0,"Exclude","Include")) -> Exclude | G9: =IF($A9="","",IF($F9<>"",$F9,$E9)) -> Exclude
A10: AEP | B10: AEP Plantations | C10: GB00BWPD4D87 | D10: Consumer Staples | E10: =IF($A10="","",IF(COUNTIF(ExclList,$D10)>0,"Exclude","Include")) -> Include | G10: =IF($A10="","",IF($F10<>"",$F10,$E10)) -> Include
A11: ALFA | B11: Alfa Financial Software | C11: GB00BDHXPG30 | D11: Technology | E11: =IF($A11="","",IF(COUNTIF(ExclList,$D11)>0,"Exclude","Include")) -> Include | G11: =IF($A11="","",IF($F11<>"",$F11,$E11)) -> Include
A12: ATT | B12: Allianz Technology Trust | C12: GB00BNG2M159 | D12: Financials | E12: =IF($A12="","",IF(COUNTIF(ExclList,$D12)>0,"Exclude","Include")) -> Exclude | G12: =IF($A12="","",IF($F12<>"",$F12,$E12)) -> Exclude
A13: AMRQ | B13: Amaroq | D13: Basic Materials | E13: =IF($A13="","",IF(COUNTIF(ExclList,$D13)>0,"Exclude","Include")) -> Include | F13: Exclude | G13: =IF($A13="","",IF($F13<>"",$F13,$E13)) -> Exclude
A14: AO | B14: AO World | C14: GB00BJTNFH41 | D14: Consumer Discretionary | E14: =IF($A14="","",IF(COUNTIF(ExclList,$D14)>0,"Exclude","Include")) -> Include | G14: =IF($A14="","",IF($F14<>"",$F14,$E14)) -> Include
A15: APN | B15: Applied Nutrition | C15: GB00BPVDXX64 | D15: Consumer Staples | E15: =IF($A15="","",IF(COUNTIF(ExclList,$D15)>0,"Exclude","Include")) -> Include | G15: =IF($A15="","",IF($F15<>"",$F15,$E15)) -> Include
A16: ASHM | B16: Ashmore Group | C16: GB00B132NW22 | D16: Financials | E16: =IF($A16="","",IF(COUNTIF(ExclList,$D16)>0,"Exclude","Include")) -> Exclude | G16: =IF($A16="","",IF($F16<>"",$F16,$E16)) -> Exclude
A17: AIE | B17: Ashoka India Equity Investment Trust | C17: GB00BF50VS41 | D17: Financials | E17: =IF($A17="","",IF(COUNTIF(ExclList,$D17)>0,"Exclude","Include")) -> Exclude | G17: =IF($A17="","",IF($F17<>"",$F17,$E17)) -> Exclude
A18: ASC | B18: ASOS | C18: GB0030927254 | D18: Consumer Discretionary | E18: =IF($A18="","",IF(COUNTIF(ExclList,$D18)>0,"Exclude","Include")) -> Include | G18: =IF($A18="","",IF($F18<>"",$F18,$E18)) -> Include
A19: ATYM | B19: Atalaya Mining | C19: CY0106002112 | D19: Basic Materials | E19: =IF($A19="","",IF(COUNTIF(ExclList,$D19)>0,"Exclude","Include")) -> Include | G19: =IF($A19="","",IF($F19<>"",$F19,$E19)) -> Include
A20: ATG | B20: Auction Technology Group | C20: GB00BMVQDZ64 | D20: Technology | E20: =IF($A20="","",IF(COUNTIF(ExclList,$D20)>0,"Exclude","Include")) -> Include | G20: =IF($A20="","",IF($F20<>"",$F20,$E20)) -> Include
A21: AGT | B21: AVI Global Trust | C21: GB00BLH3CY60 | D21: Financials | E21: =IF($A21="","",IF(COUNTIF(ExclList,$D21)>0,"Exclude","Include")) -> Exclude | G21: =IF($A21="","",IF($F21<>"",$F21,$E21)) -> Exclude
A22: AVON | B22: Avon Technologies | C22: GB0000667013 | D22: Industrials | E22: =IF($A22="","",IF(COUNTIF(ExclList,$D22)>0,"Exclude","Include")) -> Include | G22: =IF($A22="","",IF($F22<>"",$F22,$E22)) -> Include
A23: BME | B23: B&M | C23: JE00BVSYJW51 | D23: Consumer Discretionary | E23: =IF($A23="","",IF(COUNTIF(ExclList,$D23)>0,"Exclude","Include")) -> Include | G23: =IF($A23="","",IF($F23<>"",$F23,$E23)) -> Include
A24: BGFD | B24: Baillie Gifford Japan Trust | C24: GB0000485838 | D24: Financials | E24: =IF($A24="","",IF(COUNTIF(ExclList,$D24)>0,"Exclude","Include")) -> Exclude | G24: =IF($A24="","",IF($F24<>"",$F24,$E24)) -> Exclude
A25: USA | B25: Baillie Gifford US Growth Trust | C25: GB00BDFGHW41 | D25: Financials | E25: =IF($A25="","",IF(COUNTIF(ExclList,$D25)>0,"Exclude","Include")) -> Exclude | G25: =IF($A25="","",IF($F25<>"",$F25,$E25)) -> Exclude
... A28: BAG | B28: A.G. Barr | C28: GB00B6XZKY75 | D28: Consumer Staples | E28: =IF($A28="","",IF(COUNTIF(ExclList,$D28)>0,"Exclude","Include")) -> Include | G28: =IF($A28="","",IF($F28<>"",$F28,$E28)) -> Include
A29: AJB | B29: AJ Bell | C29: GB00BFZNLB60 | D29: Financials | E29: =IF($A29="","",IF(COUNTIF(ExclList,$D29)>0,"Exclude","Include")) -> Exclude | F29: Exclude | G29: =IF($A29="","",IF($F29<>"",$F29,$E29)) -> Exclude
A30: BWY | B30: Bellway | C30: GB0000904986 | D30: Consumer Discretionary | E30: =IF($A30="","",IF(COUNTIF(ExclList,$D30)>0,"Exclude","Include")) -> Include | G30: =IF($A30="","",IF($F30<>"",$F30,$E30)) -> Include
A31: BKG | B31: Berkeley Group Holdings | C31: GB00BP0RGD03 | D31: Consumer Discretionary | E31: =IF($A31="","",IF(COUNTIF(ExclList,$D31)>0,"Exclude","Include")) -> Include | G31: =IF($A31="","",IF($F31<>"",$F31,$E31)) -> Include
A32: BHMG | B32: BH Macro | C32: GG00BQBFY362 | D32: Financials | E32: =IF($A32="","",IF(COUNTIF(ExclList,$D32)>0,"Exclude","Include")) -> Exclude | G32: =IF($A32="","",IF($F32<>"",$F32,$E32)) -> Exclude
A33: BYG | B33: Big Yellow Group | C33: GB0002869419 | D33: Real Estate | E33: =IF($A33="","",IF(COUNTIF(ExclList,$D33)>0,"Exclude","Include")) -> Exclude | G33: =IF($A33="","",IF($F33<>"",$F33,$E33)) -> Exclude
A34: BPCR | B34: Biopharma Credit | C34: GB00BDGKMY29 | D34: Financials | E34: =IF($A34="","",IF(COUNTIF(ExclList,$D34)>0,"Exclude","Include")) -> Exclude | G34: =IF($A34="","",IF($F34<>"",$F34,$E34)) -> Exclude
A35: BRGE | B35: BlackRock Greater Europe Investment Trust | C35: GB00B01RDH75 | D35: Financials | E35: =IF($A35="","",IF(COUNTIF(ExclList,$D35)>0,"Exclude","Include")) -> Exclude | G35: =IF($A35="","",IF($F35<>"",$F35,$E35)) -> Exclude
A36: BRSC | B36: BlackRock Smaller Companies Trust | C36: GB00BWQGKH23 | D36: Financials | E36: =IF($A36="","",IF(COUNTIF(ExclList,$D36)>0,"Exclude","Include")) -> Exclude | G36: =IF($A36="","",IF($F36<>"",$F36,$E36)) -> Exclude
A37: BRWM | B37: BlackRock World Mining Trust | C37: GB0005774855 | D37: Financials | E37: =IF($A37="","",IF(COUNTIF(ExclList,$D37)>0,"Exclude","Include")) -> Exclude | G37: =IF($A37="","",IF($F37<>"",$F37,$E37)) -> Exclude
A38: BMY | B38: Bloomsbury Publishing | C38: GB0033147751 | D38: Consumer Discretionary | E38: =IF($A38="","",IF(COUNTIF(ExclList,$D38)>0,"Exclude","Include")) -> Include | G38: =IF($A38="","",IF($F38<>"",$F38,$E38)) -> Include
A39: BOY | B39: Bodycote | C39: GB00B3FLWH99 | D39: Industrials | E39: =IF($A39="","",IF(COUNTIF(ExclList,$D39)>0,"Exclude","Include")) -> Include | G39: =IF($A39="","",IF($F39<>"",$F39,$E39)) -> Include
A40: BREE | B40: Breedon Group | C40: GB00BM8NFJ84 | D40: Industrials | E40: =IF($A40="","",IF(COUNTIF(ExclList,$D40)>0,"Exclude","Include")) -> Include | G40: =IF($A40="","",IF($F40<>"",$F40,$E40)) -> Include
A41: BPT | B41: Bridgepoint Group | C41: GB00BND88V85 | D41: Financials | E41: =IF($A41="","",IF(COUNTIF(ExclList,$D41)>0,"Exclude","Include")) -> Exclude | G41: =IF($A41="","",IF($F41<>"",$F41,$E41)) -> Exclude
A42: BUT | B42: Brunner Investment Trust | C42: GB0001490449 | D42: Financials | E42: =IF($A42="","",IF(COUNTIF(ExclList,$D42)>0,"Exclude","Include")) -> Exclude | G42: =IF($A42="","",IF($F42<>"",$F42,$E42)) -> Exclude
A43: BYIT | B43: Bytes Technology Group | C43: GB00BMH18Q19 | D43: Technology | E43: =IF($A43="","",IF(COUNTIF(ExclList,$D43)>0,"Exclude","Include")) -> Include | F43: Include | G43: =IF($A43="","",IF($F43<>"",$F43,$E43)) -> Include
A44: CLDN | B44: Caledonia Investments | C44: GB00BTNQ8K38 | D44: Financials | E44: =IF($A44="","",IF(COUNTIF(ExclList,$D44)>0,"Exclude","Include")) -> Exclude | G44: =IF($A44="","",IF($F44<>"",$F44,$E44)) -> Exclude
A45: CGT | B45: Capital Gearing Trust | C45: GB00BT66KP92 | D45: Financials | E45: =IF($A45="","",IF(COUNTIF(ExclList,$D45)>0,"Exclude","Include")) -> Exclude | G45: =IF($A45="","",IF($F45<>"",$F45,$E45)) -> Exclude
A46: CWR | B46: Ceres Power | C46: GB00BG5KQW09 | D46: Energy | E46: =IF($A46="","",IF(COUNTIF(ExclList,$D46)>0,"Exclude","Include")) -> Include | G46: =IF($A46="","",IF($F46<>"",$F46,$E46)) -> Include
A47: CHG | B47: Chemring Group | C47: GB00B45C9X44 | D47: Industrials | E47: =IF($A47="","",IF(COUNTIF(ExclList,$D47)>0,"Exclude","Include")) -> Include | G47: =IF($A47="","",IF($F47<>"",$F47,$E47)) -> Include
A48: CSN | B48: Chesnara | C48: GB00B00FPT80 | D48: Financials | E48: =IF($A48="","",IF(COUNTIF(ExclList,$D48)>0,"Exclude","Include")) -> Exclude | G48: =IF($A48="","",IF($F48<>"",$F48,$E48)) -> Exclude
A49: CTY | B49: City of London Investment Trust | C49: GB0001990497 | D49: Financials | E49: =IF($A49="","",IF(COUNTIF(ExclList,$D49)>0,"Exclude","Include")) -> Exclude | G49: =IF($A49="","",IF($F49<>"",$F49,$E49)) -> Exclude
A50: CKN | B50: Clarkson | C50: GB0002018363 | D50: Industrials | E50: =IF($A50="","",IF(COUNTIF(ExclList,$D50)>0,"Exclude","Include")) -> Include | G50: =IF($A50="","",IF($F50<>"",$F50,$E50)) -> Include
A51: CBG | B51: Close Brothers Group | C51: GB0007668071 | D51: Financials | E51: =IF($A51="","",IF(COUNTIF(ExclList,$D51)>0,"Exclude","Include")) -> Exclude | G51: =IF($A51="","",IF($F51<>"",$F51,$E51)) -> Exclude
A52: CMCX | B52: CMC Markets | C52: GB00B14SKR37 | D52: Financials | E52: =IF($A52="","",IF(COUNTIF(ExclList,$D52)>0,"Exclude","Include")) -> Exclude | G52: =IF($A52="","",IF($F52<>"",$F52,$E52)) -> Exclude
A53: COA | B53: Coats Group | C53: GB00B4YZN328 | D53: Industrials | E53: =IF($A53="","",IF(COUNTIF(ExclList,$D53)>0,"Exclude","Include")) -> Include | F53: Include | G53: =IF($A53="","",IF($F53<>"",$F53,$E53)) -> Include
A54: CORD | B54: Cordiant Digital Infrastructure | C54: GG00BMC7TM77 | D54: Financials | E54: =IF($A54="","",IF(COUNTIF(ExclList,$D54)>0,"Exclude","Include")) -> Exclude | G54: =IF($A54="","",IF($F54<>"",$F54,$E54)) -> Exclude
A55: COST | B55: Costain Group | C55: GB00B64NSP76 | D55: Industrials | E55: =IF($A55="","",IF(COUNTIF(ExclList,$D55)>0,"Exclude","Include")) -> Include | G55: =IF($A55="","",IF($F55<>"",$F55,$E55)) -> Include
A56: CWK | B56: Cranswick | C56: GB0002318888 | D56: Consumer Staples | E56: =IF($A56="","",IF(COUNTIF(ExclList,$D56)>0,"Exclude","Include")) -> Include | G56: =IF($A56="","",IF($F56<>"",$F56,$E56)) -> Include
A57: CURY | B57: Currys | C57: GB00B4Y7R145 | D57: Consumer Discretionary | E57: =IF($A57="","",IF(COUNTIF(ExclList,$D57)>0,"Exclude","Include")) -> Include | G57: =IF($A57="","",IF($F57<>"",$F57,$E57)) -> Include
A58: CVSG | B58: CVS Group | C58: GB00B2863827 | D58: Health Care | E58: =IF($A58="","",IF(COUNTIF(ExclList,$D58)>0,"Exclude","Include")) -> Include | G58: =IF($A58="","",IF($F58<>"",$F58,$E58)) -> Include
A59: DLN | B59: Derwent London | C59: GB0002652740 | D59: Real Estate | E59: =IF($A59="","",IF(COUNTIF(ExclList,$D59)>0,"Exclude","Include")) -> Exclude | G59: =IF($A59="","",IF($F59<>"",$F59,$E59)) -> Exclude
A60: DSCV | B60: discoverIE | C60: GB0000055888 | D60: Industrials | E60: =IF($A60="","",IF(COUNTIF(ExclList,$D60)>0,"Exclude","Include")) -> Include | G60: =IF($A60="","",IF($F60<>"",$F60,$E60)) -> Include
A61: DOM | B61: Domino's Pizza | C61: GB00BYN59130 | D61: Consumer Discretionary | E61: =IF($A61="","",IF(COUNTIF(ExclList,$D61)>0,"Exclude","Include")) -> Include | G61: =IF($A61="","",IF($F61<>"",$F61,$E61)) -> Include
A62: DRX | B62: Drax Group | C62: GB00B1VNSX38 | D62: Utilities | E62: =IF($A62="","",IF(COUNTIF(ExclList,$D62)>0,"Exclude","Include")) -> Include | G62: =IF($A62="","",IF($F62<>"",$F62,$E62)) -> Include
A63: DOCS | B63: Dr. Martens | C63: GB00BL6NGV24 | D63: Consumer Discretionary | E63: =IF($A63="","",IF(COUNTIF(ExclList,$D63)>0,"Exclude","Include")) -> Include | G63: =IF($A63="","",IF($F63<>"",$F63,$E63)) -> Include
A64: DNLM | B64: Dunelm Group | C64: GB00B1CKQ739 | D64: Consumer Discretionary | E64: =IF($A64="","",IF(COUNTIF(ExclList,$D64)>0,"Exclude","Include")) -> Include | G64: =IF($A64="","",IF($F64<>"",$F64,$E64)) -> Include
A65: EDIN | B65: Edinburgh Investment Trust | C65: GB0003052338 | D65: Financials | E65: =IF($A65="","",IF(COUNTIF(ExclList,$D65)>0,"Exclude","Include")) -> Exclude | G65: =IF($A65="","",IF($F65<>"",$F65,$E65)) -> Exclude
... A70: ESCT | B70: European Smaller Companies Trust | C70: GB00BMCF8689 | D70: Financials | E70: =IF($A70="","",IF(COUNTIF(ExclList,$D70)>0,"Exclude","Include")) -> Exclude | G70: =IF($A70="","",IF($F70<>"",$F70,$E70)) -> Exclude
A71: EWG | B71: Eurowag | C71: GB00BLGXWY71 | D71: Industrials | E71: =IF($A71="","",IF(COUNTIF(ExclList,$D71)>0,"Exclude","Include")) -> Include | F71: Include | G71: =IF($A71="","",IF($F71<>"",$F71,$E71)) -> Include
A72: FCSS | B72: Fidelity China Special Situations | C72: GB00B62Z3C74 | D72: Financials | E72: =IF($A72="","",IF(COUNTIF(ExclList,$D72)>0,"Exclude","Include")) -> Exclude | G72: =IF($A72="","",IF($F72<>"",$F72,$E72)) -> Exclude
A73: FEML | B73: Fidelity Emerging Markets | C73: GG00B4L0PD47 | D73: Financials | E73: =IF($A73="","",IF(COUNTIF(ExclList,$D73)>0,"Exclude","Include")) -> Exclude | G73: =IF($A73="","",IF($F73<>"",$F73,$E73)) -> Exclude
A74: FEV | B74: Fidelity European Trust | C74: GB00BK1PKQ95 | D74: Financials | E74: =IF($A74="","",IF(COUNTIF(ExclList,$D74)>0,"Exclude","Include")) -> Exclude | G74: =IF($A74="","",IF($F74<>"",$F74,$E74)) -> Exclude
A75: FSV | B75: Fidelity Special Values | D75: Financials | E75: =IF($A75="","",IF(COUNTIF(ExclList,$D75)>0,"Exclude","Include")) -> Exclude | F75: Exclude | G75: =IF($A75="","",IF($F75<>"",$F75,$E75)) -> Exclude
A76: FGT | B76: Finsbury Growth & Income Trust | C76: GB0007816068 | D76: Financials | E76: =IF($A76="","",IF(COUNTIF(ExclList,$D76)>0,"Exclude","Include")) -> Exclude | G76: =IF($A76="","",IF($F76<>"",$F76,$E76)) -> Exclude
A77: FGP | B77: FirstGroup | C77: GB0003452173 | D77: Consumer Discretionary | E77: =IF($A77="","",IF(COUNTIF(ExclList,$D77)>0,"Exclude","Include")) -> Include | G77: =IF($A77="","",IF($F77<>"",$F77,$E77)) -> Include
A78: FGEN | B78: Foresight Environmental Infrastructure | C78: GG00BJL5FH87 | D78: Financials | E78: =IF($A78="","",IF(COUNTIF(ExclList,$D78)>0,"Exclude","Include")) -> Exclude | G78: =IF($A78="","",IF($F78<>"",$F78,$E78)) -> Exclude
A79: FSG | B79: Foresight Group | C79: GG00BMD8MJ76 | D79: Financials | E79: =IF($A79="","",IF(COUNTIF(ExclList,$D79)>0,"Exclude","Include")) -> Exclude | G79: =IF($A79="","",IF($F79<>"",$F79,$E79)) -> Exclude
A80: FRAS | B80: Frasers Group | C80: GB00B1QH8P22 | D80: Consumer Discretionary | E80: =IF($A80="","",IF(COUNTIF(ExclList,$D80)>0,"Exclude","Include")) -> Include | G80: =IF($A80="","",IF($F80<>"",$F80,$E80)) -> Include
A81: FCH | B81: Funding Circle | C81: GB00BG0TPX62 | D81: Financials | E81: =IF($A81="","",IF(COUNTIF(ExclList,$D81)>0,"Exclude","Include")) -> Exclude | G81: =IF($A81="","",IF($F81<>"",$F81,$E81)) -> Exclude
A82: GFRD | B82: Galliford Try | C82: GB00BKY40Q38 | D82: Industrials | E82: =IF($A82="","",IF(COUNTIF(ExclList,$D82)>0,"Exclude","Include")) -> Include | G82: =IF($A82="","",IF($F82<>"",$F82,$E82)) -> Include
A83: GAMA | B83: Gamma Communications | C83: GB00BQS10J50 | D83: Telecommunications | E83: =IF($A83="","",IF(COUNTIF(ExclList,$D83)>0,"Exclude","Include")) -> Include | G83: =IF($A83="","",IF($F83<>"",$F83,$E83)) -> Include
A84: GCP | B84: GCP Infrastructure Investments | C84: JE00B6173J15 | D84: Financials | E84: =IF($A84="","",IF(COUNTIF(ExclList,$D84)>0,"Exclude","Include")) -> Exclude | G84: =IF($A84="","",IF($F84<>"",$F84,$E84)) -> Exclude
A85: GEN | B85: Genuit Group | C85: GB00BKRC5K31 | D85: Industrials | E85: =IF($A85="","",IF(COUNTIF(ExclList,$D85)>0,"Exclude","Include")) -> Include | G85: =IF($A85="","",IF($F85<>"",$F85,$E85)) -> Include
A86: GNS | B86: Genus | C86: GB0002074580 | D86: Health Care | E86: =IF($A86="","",IF(COUNTIF(ExclList,$D86)>0,"Exclude","Include")) -> Include | G86: =IF($A86="","",IF($F86<>"",$F86,$E86)) -> Include
A87: DATA | B87: GlobalData | C87: GB00BR3VDF43 | D87: Industrials | E87: =IF($A87="","",IF(COUNTIF(ExclList,$D87)>0,"Exclude","Include")) -> Include | G87: =IF($A87="","",IF($F87<>"",$F87,$E87)) -> Include
... A92: GPE | B92: Great Portland Estates | C92: GB00BF5H9P87 | D92: Real Estate | E92: =IF($A92="","",IF(COUNTIF(ExclList,$D92)>0,"Exclude","Include")) -> Exclude | G92: =IF($A92="","",IF($F92<>"",$F92,$E92)) -> Exclude
A93: UKW | B93: Greencoat UK Wind | C93: GB00B8SC6K54 | D93: Financials | E93: =IF($A93="","",IF(COUNTIF(ExclList,$D93)>0,"Exclude","Include")) -> Exclude | F93: Exclude | G93: =IF($A93="","",IF($F93<>"",$F93,$E93)) -> Exclude
A94: GNC | B94: Greencore | C94: IE0003864109 | D94: Consumer Staples | E94: =IF($A94="","",IF(COUNTIF(ExclList,$D94)>0,"Exclude","Include")) -> Include | G94: =IF($A94="","",IF($F94<>"",$F94,$E94)) -> Include
A95: GRG | B95: Greggs | C95: GB00B63QSB39 | D95: Consumer Discretionary | E95: =IF($A95="","",IF(COUNTIF(ExclList,$D95)>0,"Exclude","Include")) -> Include | G95: =IF($A95="","",IF($F95<>"",$F95,$E95)) -> Include
A96: HFD | B96: Halfords | C96: GB00B012TP20 | D96: Consumer Discretionary | E96: =IF($A96="","",IF(COUNTIF(ExclList,$D96)>0,"Exclude","Include")) -> Include | G96: =IF($A96="","",IF($F96<>"",$F96,$E96)) -> Include
A97: HMSO | B97: Hammerson | C97: GB00BRJQ8J25 | D97: Real Estate | E97: =IF($A97="","",IF(COUNTIF(ExclList,$D97)>0,"Exclude","Include")) -> Exclude | G97: =IF($A97="","",IF($F97<>"",$F97,$E97)) -> Exclude
A98: HANA | B98: Hansa Investment Company | C98: BMG428941162 | D98: Financials | E98: =IF($A98="","",IF(COUNTIF(ExclList,$D98)>0,"Exclude","Include")) -> Exclude | G98: =IF($A98="","",IF($F98<>"",$F98,$E98)) -> Exclude
A99: HBR | B99: Harbour Energy | C99: GB00BMBVGQ36 | D99: Energy | E99: =IF($A99="","",IF(COUNTIF(ExclList,$D99)>0,"Exclude","Include")) -> Include | G99: =IF($A99="","",IF($F99<>"",$F99,$E99)) -> Include
A100: HVPE | B100: HarbourVest Global Private Equity | C100: GG00BR30MJ80 | D100: Financials | E100: =IF($A100="","",IF(COUNTIF(ExclList,$D100)>0,"Exclude","Include")) -> Exclude | G100: =IF($A100="","",IF($F100<>"",$F100,$E100)) -> Exclude
A101: HWG | B101: Harworth Group | C101: GB00BYZJ7G42 | D101: Real Estate | E101: =IF($A101="","",IF(COUNTIF(ExclList,$D101)>0,"Exclude","Include")) -> Exclude | G101: =IF($A101="","",IF($F101<>"",$F101,$E101)) -> Exclude
A102: HAS | B102: Hays | C102: GB0004161021 | D102: Industrials | E102: =IF($A102="","",IF(COUNTIF(ExclList,$D102)>0,"Exclude","Include")) -> Include | G102: =IF($A102="","",IF($F102<>"",$F102,$E102)) -> Include
A103: HTWS | B103: Helios Towers | C103: GB00BJVQC708 | D103: Telecommunications | E103: =IF($A103="","",IF(COUNTIF(ExclList,$D103)>0,"Exclude","Include")) -> Include | G103: =IF($A103="","",IF($F103<>"",$F103,$E103)) -> Include
A104: HFEL | B104: Henderson Far East Income | C104: JE00B1GXH751 | D104: Financials | E104: =IF($A104="","",IF(COUNTIF(ExclList,$D104)>0,"Exclude","Include")) -> Exclude | G104: =IF($A104="","",IF($F104<>"",$F104,$E104)) -> Exclude
A105: HSL | B105: Henderson Smaller Companies Investment Trust | C105: GB0009065060 | D105: Financials | E105: =IF($A105="","",IF(COUNTIF(ExclList,$D105)>0,"Exclude","Include")) -> Exclude | G105: =IF($A105="","",IF($F105<>"",$F105,$E105)) -> Exclude
... A116: INCH | B116: Inchcape | C116: GB00B61TVQ02 | D116: Consumer Discretionary | E116: =IF($A116="","",IF(COUNTIF(ExclList,$D116)>0,"Exclude","Include")) -> Include | G116: =IF($A116="","",IF($F116<>"",$F116,$E116)) -> Include
A117: IHP | B117: IntegraFin Holdings | C117: GB00BD45SH49 | D117: Financials | E117: =IF($A117="","",IF(COUNTIF(ExclList,$D117)>0,"Exclude","Include")) -> Exclude | F117: Exclude | G117: =IF($A117="","",IF($F117<>"",$F117,$E117)) -> Exclude
A118: INPP | B118: International Public Partnerships | C118: GB00B188SR50 | D118: Financials | E118: =IF($A118="","",IF(COUNTIF(ExclList,$D118)>0,"Exclude","Include")) -> Exclude | G118: =IF($A118="","",IF($F118<>"",$F118,$E118)) -> Exclude
A119: IWG | B119: International Workplace Group | C119: JE00BYVQYS01 | D119: Industrials | E119: =IF($A119="","",IF(COUNTIF(ExclList,$D119)>0,"Exclude","Include")) -> Include | G119: =IF($A119="","",IF($F119<>"",$F119,$E119)) -> Include
A120: IAD | B120: Invesco Asia Dragon Trust | C120: GB0004535307 | D120: Financials | E120: =IF($A120="","",IF(COUNTIF(ExclList,$D120)>0,"Exclude","Include")) -> Exclude | G120: =IF($A120="","",IF($F120<>"",$F120,$E120)) -> Exclude
A121: IPO | B121: IP Group | D121: Financials | E121: =IF($A121="","",IF(COUNTIF(ExclList,$D121)>0,"Exclude","Include")) -> Exclude | F121: Exclude | G121: =IF($A121="","",IF($F121<>"",$F121,$E121)) -> Exclude
A122: ITV | B122: ITV | C122: GB0033986497 | D122: Consumer Discretionary | E122: =IF($A122="","",IF(COUNTIF(ExclList,$D122)>0,"Exclude","Include")) -> Include | G122: =IF($A122="","",IF($F122<>"",$F122,$E122)) -> Include
A123: JMAT | B123: Johnson Matthey | C123: GB00BTQHVY80 | D123: Basic Materials | E123: =IF($A123="","",IF(COUNTIF(ExclList,$D123)>0,"Exclude","Include")) -> Include | G123: =IF($A123="","",IF($F123<>"",$F123,$E123)) -> Include
...

Sheet Raw_Fund
A1: key | B1: isin_h | C1: fyear_h | E1: gvkey | F1: isin | G1: conm | H1: fyear | I1: datadate | J1: curcd | K1: revt | L1: ebit | M1: ebitda | N1: ni | O1: oancf | P1: capx | Q1: dltt | R1: dlc | S1: che | T1: mib
A2: =IF($F2="","",$F2&"|"&$H2) | B2: =IF(F2<>"",F2,"") | C2: =IF(H2<>"", H2, "")
A3: =IF($F3="","",$F3&"|"&$H3) | B3: =IF(F3<>"",F3,"") | C3: =IF(H3<>"", H3, "")
A4: =IF($F4="","",$F4&"|"&$H4) | B4: =IF(F4<>"",F4,"") | C4: =IF(H4<>"", H4, "")
A5: =IF($F5="","",$F5&"|"&$H5) | B5: =IF(F5<>"",F5,"") | C5: =IF(H5<>"", H5, "")
A6: =IF($F6="","",$F6&"|"&$H6) | B6: =IF(F6<>"",F6,"") | C6: =IF(H6<>"", H6, "")
A7: =IF($F7="","",$F7&"|"&$H7) | B7: =IF(F7<>"",F7,"") | C7: =IF(H7<>"", H7, "")
A8: =IF($F8="","",$F8&"|"&$H8) | B8: =IF(F8<>"",F8,"") | C8: =IF(H8<>"", H8, "")
A9: =IF($F9="","",$F9&"|"&$H9) | B9: =IF(F9<>"",F9,"") | C9: =IF(H9<>"", H9, "")
A10: =IF($F10="","",$F10&"|"&$H10) | B10: =IF(F10<>"",F10,"") | C10: =IF(H10<>"", H10, "")
A11: =IF($F11="","",$F11&"|"&$H11) | B11: =IF(F11<>"",F11,"") | C11: =IF(H11<>"", H11, "")
A12: =IF($F12="","",$F12&"|"&$H12) | B12: =IF(F12<>"",F12,"") | C12: =IF(H12<>"", H12, "")
A13: =IF($F13="","",$F13&"|"&$H13) | B13: =IF(F13<>"",F13,"") | C13: =IF(H13<>"", H13, "")
... A3000: =IF($F3000="","",$F3000&"|"&$H3000) | B3000: =IF(F3000<>"",F3000,"") | C3000: =IF(H3000<>"", H3000, "")

Sheet Raw_Mkt
A1: isin_h | B1: mcap_gbp_m | D1: gvkey | E1: iid | F1: datadate | G1: isin | H1: conm | I1: prccd | J1: cshoc | K1: curcdd
A2: =IF(G2<>"",G2,"") | B2: =IF($G2="","",IFERROR($I2*$J2/1000000/PriceDiv*_xlfn.XLOOKUP($K2,FX_Ccy,FX_Rate),""))
A3: =IF(G3<>"",G3,"") | B3: =IF($G3="","",IFERROR($I3*$J3/1000000/PriceDiv*_xlfn.XLOOKUP($K3,FX_Ccy,FX_Rate),""))
A4: =IF(G4<>"",G4,"") | B4: =IF($G4="","",IFERROR($I4*$J4/1000000/PriceDiv*_xlfn.XLOOKUP($K4,FX_Ccy,FX_Rate),""))
A5: =IF(G5<>"",G5,"") | B5: =IF($G5="","",IFERROR($I5*$J5/1000000/PriceDiv*_xlfn.XLOOKUP($K5,FX_Ccy,FX_Rate),""))
A6: =IF(G6<>"",G6,"") | B6: =IF($G6="","",IFERROR($I6*$J6/1000000/PriceDiv*_xlfn.XLOOKUP($K6,FX_Ccy,FX_Rate),""))
A7: =IF(G7<>"",G7,"") | B7: =IF($G7="","",IFERROR($I7*$J7/1000000/PriceDiv*_xlfn.XLOOKUP($K7,FX_Ccy,FX_Rate),""))
A8: =IF(G8<>"",G8,"") | B8: =IF($G8="","",IFERROR($I8*$J8/1000000/PriceDiv*_xlfn.XLOOKUP($K8,FX_Ccy,FX_Rate),""))
A9: =IF(G9<>"",G9,"") | B9: =IF($G9="","",IFERROR($I9*$J9/1000000/PriceDiv*_xlfn.XLOOKUP($K9,FX_Ccy,FX_Rate),""))
A10: =IF(G10<>"",G10,"") | B10: =IF($G10="","",IFERROR($I10*$J10/1000000/PriceDiv*_xlfn.XLOOKUP($K10,FX_Ccy,FX_Rate),""))
A11: =IF(G11<>"",G11,"") | B11: =IF($G11="","",IFERROR($I11*$J11/1000000/PriceDiv*_xlfn.XLOOKUP($K11,FX_Ccy,FX_Rate),""))
A12: =IF(G12<>"",G12,"") | B12: =IF($G12="","",IFERROR($I12*$J12/1000000/PriceDiv*_xlfn.XLOOKUP($K12,FX_Ccy,FX_Rate),""))
A13: =IF(G13<>"",G13,"") | B13: =IF($G13="","",IFERROR($I13*$J13/1000000/PriceDiv*_xlfn.XLOOKUP($K13,FX_Ccy,FX_Rate),""))
... A1000: =IF(G1000<>"",G1000,"") | B1000: =IF($G1000="","",IFERROR($I1000*$J1000/1000000/PriceDiv*_xlfn.XLOOKUP($K1000,FX_Ccy,FX_Rate),""))

Sheet Data
E3: WRDS field | G3: curcd | I3: revt | J3: revt | K3: ebit | L3: ebitda | M3: ni | N3: ni | O3: ni | P3: oancf | Q3: oancf | R3: oancf | S3: capx | T3: capx | U3: capx | V3: dltt | W3: dlc | X3: che | Y3: mib
E4: Year offset | I4: 0 | J4: -3 | K4: 0 | L4: 0 | M4: 0 | N4: -1 | O4: -2 | P4: 0 | Q4: -1 | R4: -2 | S4: 0 | T4: -1 | U4: -2
A5: Ticker | B5: Company | C5: ISIN | D5: Sector | E5: Status | F5: Latest FY | G5: Currency | H5: FX to GBP | I5: Revenue FY0 | J5: Revenue FY-3 | K5: EBIT FY0 | L5: EBITDA FY0 | M5: Net income FY0 | N5: Net income FY-1 | O5: Net income FY-2 | P5: CFO FY0 | Q5: CFO FY-1 | R5: CFO FY-2 | S5: Capex FY0 | T5: Capex FY-1 | U5: Capex FY-2 | V5: LT debt | W5: ST debt | X5: Cash | Y5: Minority interest | Z5: Market cap
A6: =IF(Universe!A6<>"",Universe!A6,"") -> 3IN | B6: =IF(Universe!B6<>"",Universe!B6,"") -> 3i Infrastructure | C6: =IF(Universe!C6<>"",Universe!C6,"") -> JE00BF5FX167 | D6: =IF(Universe!D6<>"",Universe!D6,"") -> Financials | E6: =Universe!G6 -> Exclude | F6: =IF($E6<>"Include","",_xlfn.LET(_xlpm.latest,_xlfn.MAXIFS(Raw_Fund!$C:$C,Raw_Fund!$B:$B,Data!$C6),IF(_xlpm.latest=0,"",_xlpm.latest))) | G6: =IF($F6="","",INDEX(Raw_Fund!$E:$AZ,MATCH($C6&"|"&$F6,Raw_Fund!$A:$A,0),MATCH(G$3,Raw_Fund!$E$1:$AZ$1,0))) | H6: =IF($G6="","",_xlfn.XLOOKUP($G6,FX_Ccy,FX_Rate,"Missing FX")) | I6: =_xlfn.LET( _xlpm.rowNo, MATCH($C6&"|"& ($F6+I$4),Raw_Fund!$A:$A,0), _xlpm.colNo, MATCH(I$3,Raw_Fund!$E$1:$AZ$1,0), _xlpm.val, INDEX(Raw_Fund!$E:$AZ,_xlpm.rowNo,_xlpm.colNo), IF(ISNUMBER(_xlpm.val),_xlpm.val*$H6,"")) | J6: =_xlfn.LET( _xlpm.rowNo, MATCH($C6&"|"& ($F6+J$4),Raw_Fund!$A:$A,0), _xlpm.colNo, MATCH(J$3,Raw_Fund!$E$1:$AZ$1,0), _xlpm.val, INDEX(Raw_Fund!$E:$AZ,_xlpm.rowNo,_xlpm.colNo), IF(ISNUMBER(_xlpm.val),_xlpm.val*$H6,"")) | K6: =_xlfn.LET( _xlpm.rowNo, MATCH($C6&"|"& ($F6+K$4),Raw_Fund!$A:$A,0), _xlpm.colNo, MATCH(K$3,Raw_Fund!$E$1:$AZ$1,0), _xlpm.val, INDEX(Raw_Fund!$E:$AZ,_xlpm.rowNo,_xlpm.colNo), IF(ISNUMBER(_xlpm.val),_xlpm.val*$H6,"")) | L6: =_xlfn.LET( _xlpm.rowNo, MATCH($C6&"|"& ($F6+L$4),Raw_Fund!$A:$A,0), _xlpm.colNo, MATCH(L$3,Raw_Fund!$E$1:$AZ$1,0), _xlpm.val, INDEX(Raw_Fund!$E:$AZ,_xlpm.rowNo,_xlpm.colNo), IF(ISNUMBER(_xlpm.val),_xlpm.val*$H6,"")) | M6: =_xlfn.LET( _xlpm.rowNo, MATCH($C6&"|"& ($F6+M$4),Raw_Fund!$A:$A,0), _xlpm.colNo, MATCH(M$3,Raw_Fund!$E$1:$AZ$1,0), _xlpm.val, INDEX(Raw_Fund!$E:$AZ,_xlpm.rowNo,_xlpm.colNo), IF(ISNUMBER(_xlpm.val),_xlpm.val*$H6,"")) | N6: =_xlfn.LET( _xlpm.rowNo, MATCH($C6&"|"& ($F6+N$4),Raw_Fund!$A:$A,0), _xlpm.colNo, MATCH(N$3,Raw_Fund!$E$1:$AZ$1,0), _xlpm.val, INDEX(Raw_Fund!$E:$AZ,_xlpm.rowNo,_xlpm.colNo), IF(ISNUMBER(_xlpm.val),_xlpm.val*$H6,"")) | O6: =_xlfn.LET( _xlpm.rowNo, MATCH($C6&"|"& ($F6+O$4),Raw_Fund!$A:$A,0), _xlpm.colNo, MATCH(O$3,Raw_Fund!$E$1:$AZ$1,0), _xlpm.val, INDEX(Raw_Fund!$E:$AZ,_xlpm.rowNo,_xlpm.colNo), IF(ISNUMBER(_xlpm.val),_xlpm.val*$H6,"")) | P6: =_xlfn.LET( _xlpm.rowNo, MATCH($C6&"|"& ($F6+P$4),Raw_Fund!$A:$A,0), _xlpm.colNo, MATCH(P$3,Raw_Fund!$E$1:$AZ$1,0), _xlpm.val, INDEX(Raw_Fund!$E:$AZ,_xlpm.rowNo,_xlpm.colNo), IF(ISNUMBER(_xlpm.val),_xlpm.val*$H6,"")) | ... Y6: =_xlfn.LET( _xlpm.rowNo, MATCH($C6&"|"& ($F6+Y$4),Raw_Fund!$A:$A,0), _xlpm.colNo, MATCH(Y$3,Raw_Fund!$E$1:$AZ$1,0), _xlpm.val, INDEX(Raw_Fund!$E:$AZ,_xlpm.rowNo,_xlpm.colNo), IF(ISNUMBER(_xlpm.val),_xlpm.val*$H6,"")) | Z6: =IF($E6<>"Include","",_xlfn.XLOOKUP($C6,Raw_Mkt!$A:$A,Raw_Mkt!$B:$B))
A7: =IF(Universe!A7<>"",Universe!A7,"") -> FOUR | B7: =IF(Universe!B7<>"",Universe!B7,"") -> 4imprint | C7: =IF(Universe!C7<>"",Universe!C7,"") -> GB0006640972 | D7: =IF(Universe!D7<>"",Universe!D7,"") -> Consumer Discretionary | E7: =Universe!G7 -> Include | F7: =IF($E7<>"Include","",_xlfn.LET(_xlpm.latest,_xlfn.MAXIFS(Raw_Fund!$C:$C,Raw_Fund!$B:$B,Data!$C7),IF(_xlpm.latest=0,"",_xlpm.latest))) | G7: =IF($F7="","",INDEX(Raw_Fund!$E:$AZ,MATCH($C7&"|"&$F7,Raw_Fund!$A:$A,0),MATCH(G$3,Raw_Fund!$E$1:$AZ$1,0))) | H7: =IF($G7="","",_xlfn.XLOOKUP($G7,FX_Ccy,FX_Rate,"Missing FX")) | I7: =_xlfn.LET( _xlpm.rowNo, MATCH($C7&"|"& ($F7+I$4),Raw_Fund!$A:$A,0), _xlpm.colNo, MATCH(I$3,Raw_Fund!$E$1:$AZ$1,0), _xlpm.val, INDEX(Raw_Fund!$E:$AZ,_xlpm.rowNo,_xlpm.colNo), IF(ISNUMBER(_xlpm.val),_xlpm.val*$H7,"")) | J7: =_xlfn.LET( _xlpm.rowNo, MATCH($C7&"|"& ($F7+J$4),Raw_Fund!$A:$A,0), _xlpm.colNo, MATCH(J$3,Raw_Fund!$E$1:$AZ$1,0), _xlpm.val, INDEX(Raw_Fund!$E:$AZ,_xlpm.rowNo,_xlpm.colNo), IF(ISNUMBER(_xlpm.val),_xlpm.val*$H7,"")) | K7: =_xlfn.LET( _xlpm.rowNo, MATCH($C7&"|"& ($F7+K$4),Raw_Fund!$A:$A,0), _xlpm.colNo, MATCH(K$3,Raw_Fund!$E$1:$AZ$1,0), _xlpm.val, INDEX(Raw_Fund!$E:$AZ,_xlpm.rowNo,_xlpm.colNo), IF(ISNUMBER(_xlpm.val),_xlpm.val*$H7,"")) | L7: =_xlfn.LET( _xlpm.rowNo, MATCH($C7&"|"& ($F7+L$4),Raw_Fund!$A:$A,0), _xlpm.colNo, MATCH(L$3,Raw_Fund!$E$1:$AZ$1,0), _xlpm.val, INDEX(Raw_Fund!$E:$AZ,_xlpm.rowNo,_xlpm.colNo), IF(ISNUMBER(_xlpm.val),_xlpm.val*$H7,"")) | M7: =_xlfn.LET( _xlpm.rowNo, MATCH($C7&"|"& ($F7+M$4),Raw_Fund!$A:$A,0), _xlpm.colNo, MATCH(M$3,Raw_Fund!$E$1:$AZ$1,0), _xlpm.val, INDEX(Raw_Fund!$E:$AZ,_xlpm.rowNo,_xlpm.colNo), IF(ISNUMBER(_xlpm.val),_xlpm.val*$H7,"")) | N7: =_xlfn.LET( _xlpm.rowNo, MATCH($C7&"|"& ($F7+N$4),Raw_Fund!$A:$A,0), _xlpm.colNo, MATCH(N$3,Raw_Fund!$E$1:$AZ$1,0), _xlpm.val, INDEX(Raw_Fund!$E:$AZ,_xlpm.rowNo,_xlpm.colNo), IF(ISNUMBER(_xlpm.val),_xlpm.val*$H7,"")) | O7: =_xlfn.LET( _xlpm.rowNo, MATCH($C7&"|"& ($F7+O$4),Raw_Fund!$A:$A,0), _xlpm.colNo, MATCH(O$3,Raw_Fund!$E$1:$AZ$1,0), _xlpm.val, INDEX(Raw_Fund!$E:$AZ,_xlpm.rowNo,_xlpm.colNo), IF(ISNUMBER(_xlpm.val),_xlpm.val*$H7,"")) | P7: =_xlfn.LET( _xlpm.rowNo, MATCH($C7&"|"& ($F7+P$4),Raw_Fund!$A:$A,0), _xlpm.colNo, MATCH(P$3,Raw_Fund!$E$1:$AZ$1,0), _xlpm.val, INDEX(Raw_Fund!$E:$AZ,_xlpm.rowNo,_xlpm.colNo), IF(ISNUMBER(_xlpm.val),_xlpm.val*$H7,"")) | ... Y7: =_xlfn.LET( _xlpm.rowNo, MATCH($C7&"|"& ($F7+Y$4),Raw_Fund!$A:$A,0), _xlpm.colNo, MATCH(Y$3,Raw_Fund!$E$1:$AZ$1,0), _xlpm.val, INDEX(Raw_Fund!$E:$AZ,_xlpm.rowNo,_xlpm.colNo), IF(ISNUMBER(_xlpm.val),_xlpm.val*$H7,"")) | Z7: =IF($E7<>"Include","",_xlfn.XLOOKUP($C7,Raw_Mkt!$A:$A,Raw_Mkt!$B:$B)) -> #N/A
A8: =IF(Universe!A8<>"",Universe!A8,"") -> AAS | B8: =IF(Universe!B8<>"",Universe!B8,"") -> Aberdeen Asia Focus | C8: =IF(Universe!C8<>"",Universe!C8,"") -> GB00BMF19B58 | D8: =IF(Universe!D8<>"",Universe!D8,"") -> Financials | E8: =Universe!G8 -> Exclude | F8: =IF($E8<>"Include","",_xlfn.LET(_xlpm.latest,_xlfn.MAXIFS(Raw_Fund!$C:$C,Raw_Fund!$B:$B,Data!$C8),IF(_xlpm.latest=0,"",_xlpm.latest))) | G8: =IF($F8="","",INDEX(Raw_Fund!$E:$AZ,MATCH($C8&"|"&$F8,Raw_Fund!$A:$A,0),MATCH(G$3,Raw_Fund!$E$1:$AZ$1,0))) | H8: =IF($G8="","",_xlfn.XLOOKUP($G8,FX_Ccy,FX_Rate,"Missing FX")) | I8: =_xlfn.LET( _xlpm.rowNo, MATCH($C8&"|"& ($F8+I$4),Raw_Fund!$A:$A,0), _xlpm.colNo, MATCH(I$3,Raw_Fund!$E$1:$AZ$1,0), _xlpm.val, INDEX(Raw_Fund!$E:$AZ,_xlpm.rowNo,_xlpm.colNo), IF(ISNUMBER(_xlpm.val),_xlpm.val*$H8,"")) | J8: =_xlfn.LET( _xlpm.rowNo, MATCH($C8&"|"& ($F8+J$4),Raw_Fund!$A:$A,0), _xlpm.colNo, MATCH(J$3,Raw_Fund!$E$1:$AZ$1,0), _xlpm.val, INDEX(Raw_Fund!$E:$AZ,_xlpm.rowNo,_xlpm.colNo), IF(ISNUMBER(_xlpm.val),_xlpm.val*$H8,"")) | K8: =_xlfn.LET( _xlpm.rowNo, MATCH($C8&"|"& ($F8+K$4),Raw_Fund!$A:$A,0), _xlpm.colNo, MATCH(K$3,Raw_Fund!$E$1:$AZ$1,0), _xlpm.val, INDEX(Raw_Fund!$E:$AZ,_xlpm.rowNo,_xlpm.colNo), IF(ISNUMBER(_xlpm.val),_xlpm.val*$H8,"")) | L8: =_xlfn.LET( _xlpm.rowNo, MATCH($C8&"|"& ($F8+L$4),Raw_Fund!$A:$A,0), _xlpm.colNo, MATCH(L$3,Raw_Fund!$E$1:$AZ$1,0), _xlpm.val, INDEX(Raw_Fund!$E:$AZ,_xlpm.rowNo,_xlpm.colNo), IF(ISNUMBER(_xlpm.val),_xlpm.val*$H8,"")) | M8: =_xlfn.LET( _xlpm.rowNo, MATCH($C8&"|"& ($F8+M$4),Raw_Fund!$A:$A,0), _xlpm.colNo, MATCH(M$3,Raw_Fund!$E$1:$AZ$1,0), _xlpm.val, INDEX(Raw_Fund!$E:$AZ,_xlpm.rowNo,_xlpm.colNo), IF(ISNUMBER(_xlpm.val),_xlpm.val*$H8,"")) | N8: =_xlfn.LET( _xlpm.rowNo, MATCH($C8&"|"& ($F8+N$4),Raw_Fund!$A:$A,0), _xlpm.colNo, MATCH(N$3,Raw_Fund!$E$1:$AZ$1,0), _xlpm.val, INDEX(Raw_Fund!$E:$AZ,_xlpm.rowNo,_xlpm.colNo), IF(ISNUMBER(_xlpm.val),_xlpm.val*$H8,"")) | O8: =_xlfn.LET( _xlpm.rowNo, MATCH($C8&"|"& ($F8+O$4),Raw_Fund!$A:$A,0), _xlpm.colNo, MATCH(O$3,Raw_Fund!$E$1:$AZ$1,0), _xlpm.val, INDEX(Raw_Fund!$E:$AZ,_xlpm.rowNo,_xlpm.colNo), IF(ISNUMBER(_xlpm.val),_xlpm.val*$H8,"")) | P8: =_xlfn.LET( _xlpm.rowNo, MATCH($C8&"|"& ($F8+P$4),Raw_Fund!$A:$A,0), _xlpm.colNo, MATCH(P$3,Raw_Fund!$E$1:$AZ$1,0), _xlpm.val, INDEX(Raw_Fund!$E:$AZ,_xlpm.rowNo,_xlpm.colNo), IF(ISNUMBER(_xlpm.val),_xlpm.val*$H8,"")) | ... Y8: =_xlfn.LET( _xlpm.rowNo, MATCH($C8&"|"& ($F8+Y$4),Raw_Fund!$A:$A,0), _xlpm.colNo, MATCH(Y$3,Raw_Fund!$E$1:$AZ$1,0), _xlpm.val, INDEX(Raw_Fund!$E:$AZ,_xlpm.rowNo,_xlpm.colNo), IF(ISNUMBER(_xlpm.val),_xlpm.val*$H8,"")) | Z8: =IF($E8<>"Include","",_xlfn.XLOOKUP($C8,Raw_Mkt!$A:$A,Raw_Mkt!$B:$B))
A9: =IF(Universe!A9<>"",Universe!A9,"") -> ASL | B9: =IF(Universe!B9<>"",Universe!B9,"") -> Aberforth Smaller Companies Trust | C9: =IF(Universe!C9<>"",Universe!C9,"") -> GB0000066554 | D9: =IF(Universe!D9<>"",Universe!D9,"") -> Financials | E9: =Universe!G9 -> Exclude | F9: =IF($E9<>"Include","",_xlfn.LET(_xlpm.latest,_xlfn.MAXIFS(Raw_Fund!$C:$C,Raw_Fund!$B:$B,Data!$C9),IF(_xlpm.latest=0,"",_xlpm.latest))) | G9: =IF($F9="","",INDEX(Raw_Fund!$E:$AZ,MATCH($C9&"|"&$F9,Raw_Fund!$A:$A,0),MATCH(G$3,Raw_Fund!$E$1:$AZ$1,0))) | H9: =IF($G9="","",_xlfn.XLOOKUP($G9,FX_Ccy,FX_Rate,"Missing FX")) | I9: =_xlfn.LET( _xlpm.rowNo, MATCH($C9&"|"& ($F9+I$4),Raw_Fund!$A:$A,0), _xlpm.colNo, MATCH(I$3,Raw_Fund!$E$1:$AZ$1,0), _xlpm.val, INDEX(Raw_Fund!$E:$AZ,_xlpm.rowNo,_xlpm.colNo), IF(ISNUMBER(_xlpm.val),_xlpm.val*$H9,"")) | J9: =_xlfn.LET( _xlpm.rowNo, MATCH($C9&"|"& ($F9+J$4),Raw_Fund!$A:$A,0), _xlpm.colNo, MATCH(J$3,Raw_Fund!$E$1:$AZ$1,0), _xlpm.val, INDEX(Raw_Fund!$E:$AZ,_xlpm.rowNo,_xlpm.colNo), IF(ISNUMBER(_xlpm.val),_xlpm.val*$H9,"")) | K9: =_xlfn.LET( _xlpm.rowNo, MATCH($C9&"|"& ($F9+K$4),Raw_Fund!$A:$A,0), _xlpm.colNo, MATCH(K$3,Raw_Fund!$E$1:$AZ$1,0), _xlpm.val, INDEX(Raw_Fund!$E:$AZ,_xlpm.rowNo,_xlpm.colNo), IF(ISNUMBER(_xlpm.val),_xlpm.val*$H9,"")) | L9: =_xlfn.LET( _xlpm.rowNo, MATCH($C9&"|"& ($F9+L$4),Raw_Fund!$A:$A,0), _xlpm.colNo, MATCH(L$3,Raw_Fund!$E$1:$AZ$1,0), _xlpm.val, INDEX(Raw_Fund!$E:$AZ,_xlpm.rowNo,_xlpm.colNo), IF(ISNUMBER(_xlpm.val),_xlpm.val*$H9,"")) | M9: =_xlfn.LET( _xlpm.rowNo, MATCH($C9&"|"& ($F9+M$4),Raw_Fund!$A:$A,0), _xlpm.colNo, MATCH(M$3,Raw_Fund!$E$1:$AZ$1,0), _xlpm.val, INDEX(Raw_Fund!$E:$AZ,_xlpm.rowNo,_xlpm.colNo), IF(ISNUMBER(_xlpm.val),_xlpm.val*$H9,"")) | N9: =_xlfn.LET( _xlpm.rowNo, MATCH($C9&"|"& ($F9+N$4),Raw_Fund!$A:$A,0), _xlpm.colNo, MATCH(N$3,Raw_Fund!$E$1:$AZ$1,0), _xlpm.val, INDEX(Raw_Fund!$E:$AZ,_xlpm.rowNo,_xlpm.colNo), IF(ISNUMBER(_xlpm.val),_xlpm.val*$H9,"")) | O9: =_xlfn.LET( _xlpm.rowNo, MATCH($C9&"|"& ($F9+O$4),Raw_Fund!$A:$A,0), _xlpm.colNo, MATCH(O$3,Raw_Fund!$E$1:$AZ$1,0), _xlpm.val, INDEX(Raw_Fund!$E:$AZ,_xlpm.rowNo,_xlpm.colNo), IF(ISNUMBER(_xlpm.val),_xlpm.val*$H9,"")) | P9: =_xlfn.LET( _xlpm.rowNo, MATCH($C9&"|"& ($F9+P$4),Raw_Fund!$A:$A,0), _xlpm.colNo, MATCH(P$3,Raw_Fund!$E$1:$AZ$1,0), _xlpm.val, INDEX(Raw_Fund!$E:$AZ,_xlpm.rowNo,_xlpm.colNo), IF(ISNUMBER(_xlpm.val),_xlpm.val*$H9,"")) | ... Y9: =_xlfn.LET( _xlpm.rowNo, MATCH($C9&"|"& ($F9+Y$4),Raw_Fund!$A:$A,0), _xlpm.colNo, MATCH(Y$3,Raw_Fund!$E$1:$AZ$1,0), _xlpm.val, INDEX(Raw_Fund!$E:$AZ,_xlpm.rowNo,_xlpm.colNo), IF(ISNUMBER(_xlpm.val),_xlpm.val*$H9,"")) | Z9: =IF($E9<>"Include","",_xlfn.XLOOKUP($C9,Raw_Mkt!$A:$A,Raw_Mkt!$B:$B))
A10: =IF(Universe!A10<>"",Universe!A10,"") -> AEP | B10: =IF(Universe!B10<>"",Universe!B10,"") -> AEP Plantations | C10: =IF(Universe!C10<>"",Universe!C10,"") -> GB00BWPD4D87 | D10: =IF(Universe!D10<>"",Universe!D10,"") -> Consumer Staples | E10: =Universe!G10 -> Include | F10: =IF($E10<>"Include","",_xlfn.LET(_xlpm.latest,_xlfn.MAXIFS(Raw_Fund!$C:$C,Raw_Fund!$B:$B,Data!$C10),IF(_xlpm.latest=0,"",_xlpm.latest))) | G10: =IF($F10="","",INDEX(Raw_Fund!$E:$AZ,MATCH($C10&"|"&$F10,Raw_Fund!$A:$A,0),MATCH(G$3,Raw_Fund!$E$1:$AZ$1,0))) | H10: =IF($G10="","",_xlfn.XLOOKUP($G10,FX_Ccy,FX_Rate,"Missing FX")) | I10: =_xlfn.LET( _xlpm.rowNo, MATCH($C10&"|"& ($F10+I$4),Raw_Fund!$A:$A,0), _xlpm.colNo, MATCH(I$3,Raw_Fund!$E$1:$AZ$1,0), _xlpm.val, INDEX(Raw_Fund!$E:$AZ,_xlpm.rowNo,_xlpm.colNo), IF(ISNUMBER(_xlpm.val),_xlpm.val*$H10,"")) | J10: =_xlfn.LET( _xlpm.rowNo, MATCH($C10&"|"& ($F10+J$4),Raw_Fund!$A:$A,0), _xlpm.colNo, MATCH(J$3,Raw_Fund!$E$1:$AZ$1,0), _xlpm.val, INDEX(Raw_Fund!$E:$AZ,_xlpm.rowNo,_xlpm.colNo), IF(ISNUMBER(_xlpm.val),_xlpm.val*$H10,"")) | K10: =_xlfn.LET( _xlpm.rowNo, MATCH($C10&"|"& ($F10+K$4),Raw_Fund!$A:$A,0), _xlpm.colNo, MATCH(K$3,Raw_Fund!$E$1:$AZ$1,0), _xlpm.val, INDEX(Raw_Fund!$E:$AZ,_xlpm.rowNo,_xlpm.colNo), IF(ISNUMBER(_xlpm.val),_xlpm.val*$H10,"")) | L10: =_xlfn.LET( _xlpm.rowNo, MATCH($C10&"|"& ($F10+L$4),Raw_Fund!$A:$A,0), _xlpm.colNo, MATCH(L$3,Raw_Fund!$E$1:$AZ$1,0), _xlpm.val, INDEX(Raw_Fund!$E:$AZ,_xlpm.rowNo,_xlpm.colNo), IF(ISNUMBER(_xlpm.val),_xlpm.val*$H10,"")) | M10: =_xlfn.LET( _xlpm.rowNo, MATCH($C10&"|"& ($F10+M$4),Raw_Fund!$A:$A,0), _xlpm.colNo, MATCH(M$3,Raw_Fund!$E$1:$AZ$1,0), _xlpm.val, INDEX(Raw_Fund!$E:$AZ,_xlpm.rowNo,_xlpm.colNo), IF(ISNUMBER(_xlpm.val),_xlpm.val*$H10,"")) | N10: =_xlfn.LET( _xlpm.rowNo, MATCH($C10&"|"& ($F10+N$4),Raw_Fund!$A:$A,0), _xlpm.colNo, MATCH(N$3,Raw_Fund!$E$1:$AZ$1,0), _xlpm.val, INDEX(Raw_Fund!$E:$AZ,_xlpm.rowNo,_xlpm.colNo), IF(ISNUMBER(_xlpm.val),_xlpm.val*$H10,"")) | O10: =_xlfn.LET( _xlpm.rowNo, MATCH($C10&"|"& ($F10+O$4),Raw_Fund!$A:$A,0), _xlpm.colNo, MATCH(O$3,Raw_Fund!$E$1:$AZ$1,0), _xlpm.val, INDEX(Raw_Fund!$E:$AZ,_xlpm.rowNo,_xlpm.colNo), IF(ISNUMBER(_xlpm.val),_xlpm.val*$H10,"")) | P10: =_xlfn.LET( _xlpm.rowNo, MATCH($C10&"|"& ($F10+P$4),Raw_Fund!$A:$A,0), _xlpm.colNo, MATCH(P$3,Raw_Fund!$E$1:$AZ$1,0), _xlpm.val, INDEX(Raw_Fund!$E:$AZ,_xlpm.rowNo,_xlpm.colNo), IF(ISNUMBER(_xlpm.val),_xlpm.val*$H10,"")) | ... Y10: =_xlfn.LET( _xlpm.rowNo, MATCH($C10&"|"& ($F10+Y$4),Raw_Fund!$A:$A,0), _xlpm.colNo, MATCH(Y$3,Raw_Fund!$E$1:$AZ$1,0), _xlpm.val, INDEX(Raw_Fund!$E:$AZ,_xlpm.rowNo,_xlpm.colNo), IF(ISNUMBER(_xlpm.val),_xlpm.val*$H10,"")) | Z10: =IF($E10<>"Include","",_xlfn.XLOOKUP($C10,Raw_Mkt!$A:$A,Raw_Mkt!$B:$B)) -> #N/A
A11: =IF(Universe!A11<>"",Universe!A11,"") -> ALFA | B11: =IF(Universe!B11<>"",Universe!B11,"") -> Alfa Financial Software | C11: =IF(Universe!C11<>"",Universe!C11,"") -> GB00BDHXPG30 | D11: =IF(Universe!D11<>"",Universe!D11,"") -> Technology | E11: =Universe!G11 -> Include | F11: =IF($E11<>"Include","",_xlfn.LET(_xlpm.latest,_xlfn.MAXIFS(Raw_Fund!$C:$C,Raw_Fund!$B:$B,Data!$C11),IF(_xlpm.latest=0,"",_xlpm.latest))) | G11: =IF($F11="","",INDEX(Raw_Fund!$E:$AZ,MATCH($C11&"|"&$F11,Raw_Fund!$A:$A,0),MATCH(G$3,Raw_Fund!$E$1:$AZ$1,0))) | H11: =IF($G11="","",_xlfn.XLOOKUP($G11,FX_Ccy,FX_Rate,"Missing FX")) | I11: =_xlfn.LET( _xlpm.rowNo, MATCH($C11&"|"& ($F11+I$4),Raw_Fund!$A:$A,0), _xlpm.colNo, MATCH(I$3,Raw_Fund!$E$1:$AZ$1,0), _xlpm.val, INDEX(Raw_Fund!$E:$AZ,_xlpm.rowNo,_xlpm.colNo), IF(ISNUMBER(_xlpm.val),_xlpm.val*$H11,"")) | J11: =_xlfn.LET( _xlpm.rowNo, MATCH($C11&"|"& ($F11+J$4),Raw_Fund!$A:$A,0), _xlpm.colNo, MATCH(J$3,Raw_Fund!$E$1:$AZ$1,0), _xlpm.val, INDEX(Raw_Fund!$E:$AZ,_xlpm.rowNo,_xlpm.colNo), IF(ISNUMBER(_xlpm.val),_xlpm.val*$H11,"")) | K11: =_xlfn.LET( _xlpm.rowNo, MATCH($C11&"|"& ($F11+K$4),Raw_Fund!$A:$A,0), _xlpm.colNo, MATCH(K$3,Raw_Fund!$E$1:$AZ$1,0), _xlpm.val, INDEX(Raw_Fund!$E:$AZ,_xlpm.rowNo,_xlpm.colNo), IF(ISNUMBER(_xlpm.val),_xlpm.val*$H11,"")) | L11: =_xlfn.LET( _xlpm.rowNo, MATCH($C11&"|"& ($F11+L$4),Raw_Fund!$A:$A,0), _xlpm.colNo, MATCH(L$3,Raw_Fund!$E$1:$AZ$1,0), _xlpm.val, INDEX(Raw_Fund!$E:$AZ,_xlpm.rowNo,_xlpm.colNo), IF(ISNUMBER(_xlpm.val),_xlpm.val*$H11,"")) | M11: =_xlfn.LET( _xlpm.rowNo, MATCH($C11&"|"& ($F11+M$4),Raw_Fund!$A:$A,0), _xlpm.colNo, MATCH(M$3,Raw_Fund!$E$1:$AZ$1,0), _xlpm.val, INDEX(Raw_Fund!$E:$AZ,_xlpm.rowNo,_xlpm.colNo), IF(ISNUMBER(_xlpm.val),_xlpm.val*$H11,"")) | N11: =_xlfn.LET( _xlpm.rowNo, MATCH($C11&"|"& ($F11+N$4),Raw_Fund!$A:$A,0), _xlpm.colNo, MATCH(N$3,Raw_Fund!$E$1:$AZ$1,0), _xlpm.val, INDEX(Raw_Fund!$E:$AZ,_xlpm.rowNo,_xlpm.colNo), IF(ISNUMBER(_xlpm.val),_xlpm.val*$H11,"")) | O11: =_xlfn.LET( _xlpm.rowNo, MATCH($C11&"|"& ($F11+O$4),Raw_Fund!$A:$A,0), _xlpm.colNo, MATCH(O$3,Raw_Fund!$E$1:$AZ$1,0), _xlpm.val, INDEX(Raw_Fund!$E:$AZ,_xlpm.rowNo,_xlpm.colNo), IF(ISNUMBER(_xlpm.val),_xlpm.val*$H11,"")) | P11: =_xlfn.LET( _xlpm.rowNo, MATCH($C11&"|"& ($F11+P$4),Raw_Fund!$A:$A,0), _xlpm.colNo, MATCH(P$3,Raw_Fund!$E$1:$AZ$1,0), _xlpm.val, INDEX(Raw_Fund!$E:$AZ,_xlpm.rowNo,_xlpm.colNo), IF(ISNUMBER(_xlpm.val),_xlpm.val*$H11,"")) | ... Y11: =_xlfn.LET( _xlpm.rowNo, MATCH($C11&"|"& ($F11+Y$4),Raw_Fund!$A:$A,0), _xlpm.colNo, MATCH(Y$3,Raw_Fund!$E$1:$AZ$1,0), _xlpm.val, INDEX(Raw_Fund!$E:$AZ,_xlpm.rowNo,_xlpm.colNo), IF(ISNUMBER(_xlpm.val),_xlpm.val*$H11,"")) | Z11: =IF($E11<>"Include","",_xlfn.XLOOKUP($C11,Raw_Mkt!$A:$A,Raw_Mkt!$B:$B)) -> #N/A
A12: =IF(Universe!A12<>"",Universe!A12,"") -> ATT | B12: =IF(Universe!B12<>"",Universe!B12,"") -> Allianz Technology Trust | C12: =IF(Universe!C12<>"",Universe!C12,"") -> GB00BNG2M159 | D12: =IF(Universe!D12<>"",Universe!D12,"") -> Financials | E12: =Universe!G12 -> Exclude | F12: =IF($E12<>"Include","",_xlfn.LET(_xlpm.latest,_xlfn.MAXIFS(Raw_Fund!$C:$C,Raw_Fund!$B:$B,Data!$C12),IF(_xlpm.latest=0,"",_xlpm.latest))) | G12: =IF($F12="","",INDEX(Raw_Fund!$E:$AZ,MATCH($C12&"|"&$F12,Raw_Fund!$A:$A,0),MATCH(G$3,Raw_Fund!$E$1:$AZ$1,0))) | H12: =IF($G12="","",_xlfn.XLOOKUP($G12,FX_Ccy,FX_Rate,"Missing FX")) | I12: =_xlfn.LET( _xlpm.rowNo, MATCH($C12&"|"& ($F12+I$4),Raw_Fund!$A:$A,0), _xlpm.colNo, MATCH(I$3,Raw_Fund!$E$1:$AZ$1,0), _xlpm.val, INDEX(Raw_Fund!$E:$AZ,_xlpm.rowNo,_xlpm.colNo), IF(ISNUMBER(_xlpm.val),_xlpm.val*$H12,"")) | J12: =_xlfn.LET( _xlpm.rowNo, MATCH($C12&"|"& ($F12+J$4),Raw_Fund!$A:$A,0), _xlpm.colNo, MATCH(J$3,Raw_Fund!$E$1:$AZ$1,0), _xlpm.val, INDEX(Raw_Fund!$E:$AZ,_xlpm.rowNo,_xlpm.colNo), IF(ISNUMBER(_xlpm.val),_xlpm.val*$H12,"")) | K12: =_xlfn.LET( _xlpm.rowNo, MATCH($C12&"|"& ($F12+K$4),Raw_Fund!$A:$A,0), _xlpm.colNo, MATCH(K$3,Raw_Fund!$E$1:$AZ$1,0), _xlpm.val, INDEX(Raw_Fund!$E:$AZ,_xlpm.rowNo,_xlpm.colNo), IF(ISNUMBER(_xlpm.val),_xlpm.val*$H12,"")) | L12: =_xlfn.LET( _xlpm.rowNo, MATCH($C12&"|"& ($F12+L$4),Raw_Fund!$A:$A,0), _xlpm.colNo, MATCH(L$3,Raw_Fund!$E$1:$AZ$1,0), _xlpm.val, INDEX(Raw_Fund!$E:$AZ,_xlpm.rowNo,_xlpm.colNo), IF(ISNUMBER(_xlpm.val),_xlpm.val*$H12,"")) | M12: =_xlfn.LET( _xlpm.rowNo, MATCH($C12&"|"& ($F12+M$4),Raw_Fund!$A:$A,0), _xlpm.colNo, MATCH(M$3,Raw_Fund!$E$1:$AZ$1,0), _xlpm.val, INDEX(Raw_Fund!$E:$AZ,_xlpm.rowNo,_xlpm.colNo), IF(ISNUMBER(_xlpm.val),_xlpm.val*$H12,"")) | N12: =_xlfn.LET( _xlpm.rowNo, MATCH($C12&"|"& ($F12+N$4),Raw_Fund!$A:$A,0), _xlpm.colNo, MATCH(N$3,Raw_Fund!$E$1:$AZ$1,0), _xlpm.val, INDEX(Raw_Fund!$E:$AZ,_xlpm.rowNo,_xlpm.colNo), IF(ISNUMBER(_xlpm.val),_xlpm.val*$H12,"")) | O12: =_xlfn.LET( _xlpm.rowNo, MATCH($C12&"|"& ($F12+O$4),Raw_Fund!$A:$A,0), _xlpm.colNo, MATCH(O$3,Raw_Fund!$E$1:$AZ$1,0), _xlpm.val, INDEX(Raw_Fund!$E:$AZ,_xlpm.rowNo,_xlpm.colNo), IF(ISNUMBER(_xlpm.val),_xlpm.val*$H12,"")) | P12: =_xlfn.LET( _xlpm.rowNo, MATCH($C12&"|"& ($F12+P$4),Raw_Fund!$A:$A,0), _xlpm.colNo, MATCH(P$3,Raw_Fund!$E$1:$AZ$1,0), _xlpm.val, INDEX(Raw_Fund!$E:$AZ,_xlpm.rowNo,_xlpm.colNo), IF(ISNUMBER(_xlpm.val),_xlpm.val*$H12,"")) | ... Y12: =_xlfn.LET( _xlpm.rowNo, MATCH($C12&"|"& ($F12+Y$4),Raw_Fund!$A:$A,0), _xlpm.colNo, MATCH(Y$3,Raw_Fund!$E$1:$AZ$1,0), _xlpm.val, INDEX(Raw_Fund!$E:$AZ,_xlpm.rowNo,_xlpm.colNo), IF(ISNUMBER(_xlpm.val),_xlpm.val*$H12,"")) | Z12: =IF($E12<>"Include","",_xlfn.XLOOKUP($C12,Raw_Mkt!$A:$A,Raw_Mkt!$B:$B))
A13: =IF(Universe!A13<>"",Universe!A13,"") -> AMRQ | B13: =IF(Universe!B13<>"",Universe!B13,"") -> Amaroq | C13: =IF(Universe!C13<>"",Universe!C13,"") | D13: =IF(Universe!D13<>"",Universe!D13,"") -> Basic Materials | E13: =Universe!G13 -> Exclude | F13: =IF($E13<>"Include","",_xlfn.LET(_xlpm.latest,_xlfn.MAXIFS(Raw_Fund!$C:$C,Raw_Fund!$B:$B,Data!$C13),IF(_xlpm.latest=0,"",_xlpm.latest))) | G13: =IF($F13="","",INDEX(Raw_Fund!$E:$AZ,MATCH($C13&"|"&$F13,Raw_Fund!$A:$A,0),MATCH(G$3,Raw_Fund!$E$1:$AZ$1,0))) | H13: =IF($G13="","",_xlfn.XLOOKUP($G13,FX_Ccy,FX_Rate,"Missing FX")) | I13: =_xlfn.LET( _xlpm.rowNo, MATCH($C13&"|"& ($F13+I$4),Raw_Fund!$A:$A,0), _xlpm.colNo, MATCH(I$3,Raw_Fund!$E$1:$AZ$1,0), _xlpm.val, INDEX(Raw_Fund!$E:$AZ,_xlpm.rowNo,_xlpm.colNo), IF(ISNUMBER(_xlpm.val),_xlpm.val*$H13,"")) | J13: =_xlfn.LET( _xlpm.rowNo, MATCH($C13&"|"& ($F13+J$4),Raw_Fund!$A:$A,0), _xlpm.colNo, MATCH(J$3,Raw_Fund!$E$1:$AZ$1,0), _xlpm.val, INDEX(Raw_Fund!$E:$AZ,_xlpm.rowNo,_xlpm.colNo), IF(ISNUMBER(_xlpm.val),_xlpm.val*$H13,"")) | K13: =_xlfn.LET( _xlpm.rowNo, MATCH($C13&"|"& ($F13+K$4),Raw_Fund!$A:$A,0), _xlpm.colNo, MATCH(K$3,Raw_Fund!$E$1:$AZ$1,0), _xlpm.val, INDEX(Raw_Fund!$E:$AZ,_xlpm.rowNo,_xlpm.colNo), IF(ISNUMBER(_xlpm.val),_xlpm.val*$H13,"")) | L13: =_xlfn.LET( _xlpm.rowNo, MATCH($C13&"|"& ($F13+L$4),Raw_Fund!$A:$A,0), _xlpm.colNo, MATCH(L$3,Raw_Fund!$E$1:$AZ$1,0), _xlpm.val, INDEX(Raw_Fund!$E:$AZ,_xlpm.rowNo,_xlpm.colNo), IF(ISNUMBER(_xlpm.val),_xlpm.val*$H13,"")) | M13: =_xlfn.LET( _xlpm.rowNo, MATCH($C13&"|"& ($F13+M$4),Raw_Fund!$A:$A,0), _xlpm.colNo, MATCH(M$3,Raw_Fund!$E$1:$AZ$1,0), _xlpm.val, INDEX(Raw_Fund!$E:$AZ,_xlpm.rowNo,_xlpm.colNo), IF(ISNUMBER(_xlpm.val),_xlpm.val*$H13,"")) | N13: =_xlfn.LET( _xlpm.rowNo, MATCH($C13&"|"& ($F13+N$4),Raw_Fund!$A:$A,0), _xlpm.colNo, MATCH(N$3,Raw_Fund!$E$1:$AZ$1,0), _xlpm.val, INDEX(Raw_Fund!$E:$AZ,_xlpm.rowNo,_xlpm.colNo), IF(ISNUMBER(_xlpm.val),_xlpm.val*$H13,"")) | O13: =_xlfn.LET( _xlpm.rowNo, MATCH($C13&"|"& ($F13+O$4),Raw_Fund!$A:$A,0), _xlpm.colNo, MATCH(O$3,Raw_Fund!$E$1:$AZ$1,0), _xlpm.val, INDEX(Raw_Fund!$E:$AZ,_xlpm.rowNo,_xlpm.colNo), IF(ISNUMBER(_xlpm.val),_xlpm.val*$H13,"")) | P13: =_xlfn.LET( _xlpm.rowNo, MATCH($C13&"|"& ($F13+P$4),Raw_Fund!$A:$A,0), _xlpm.colNo, MATCH(P$3,Raw_Fund!$E$1:$AZ$1,0), _xlpm.val, INDEX(Raw_Fund!$E:$AZ,_xlpm.rowNo,_xlpm.colNo), IF(ISNUMBER(_xlpm.val),_xlpm.val*$H13,"")) | ... Y13: =_xlfn.LET( _xlpm.rowNo, MATCH($C13&"|"& ($F13+Y$4),Raw_Fund!$A:$A,0), _xlpm.colNo, MATCH(Y$3,Raw_Fund!$E$1:$AZ$1,0), _xlpm.val, INDEX(Raw_Fund!$E:$AZ,_xlpm.rowNo,_xlpm.colNo), IF(ISNUMBER(_xlpm.val),_xlpm.val*$H13,"")) | Z13: =IF($E13<>"Include","",_xlfn.XLOOKUP($C13,Raw_Mkt!$A:$A,Raw_Mkt!$B:$B))
A14: =IF(Universe!A14<>"",Universe!A14,"") -> AO | B14: =IF(Universe!B14<>"",Universe!B14,"") -> AO World | C14: =IF(Universe!C14<>"",Universe!C14,"") -> GB00BJTNFH41 | D14: =IF(Universe!D14<>"",Universe!D14,"") -> Consumer Discretionary | E14: =Universe!G14 -> Include | F14: =IF($E14<>"Include","",_xlfn.LET(_xlpm.latest,_xlfn.MAXIFS(Raw_Fund!$C:$C,Raw_Fund!$B:$B,Data!$C14),IF(_xlpm.latest=0,"",_xlpm.latest))) | G14: =IF($F14="","",INDEX(Raw_Fund!$E:$AZ,MATCH($C14&"|"&$F14,Raw_Fund!$A:$A,0),MATCH(G$3,Raw_Fund!$E$1:$AZ$1,0))) | H14: =IF($G14="","",_xlfn.XLOOKUP($G14,FX_Ccy,FX_Rate,"Missing FX")) | I14: =_xlfn.LET( _xlpm.rowNo, MATCH($C14&"|"& ($F14+I$4),Raw_Fund!$A:$A,0), _xlpm.colNo, MATCH(I$3,Raw_Fund!$E$1:$AZ$1,0), _xlpm.val, INDEX(Raw_Fund!$E:$AZ,_xlpm.rowNo,_xlpm.colNo), IF(ISNUMBER(_xlpm.val),_xlpm.val*$H14,"")) | J14: =_xlfn.LET( _xlpm.rowNo, MATCH($C14&"|"& ($F14+J$4),Raw_Fund!$A:$A,0), _xlpm.colNo, MATCH(J$3,Raw_Fund!$E$1:$AZ$1,0), _xlpm.val, INDEX(Raw_Fund!$E:$AZ,_xlpm.rowNo,_xlpm.colNo), IF(ISNUMBER(_xlpm.val),_xlpm.val*$H14,"")) | K14: =_xlfn.LET( _xlpm.rowNo, MATCH($C14&"|"& ($F14+K$4),Raw_Fund!$A:$A,0), _xlpm.colNo, MATCH(K$3,Raw_Fund!$E$1:$AZ$1,0), _xlpm.val, INDEX(Raw_Fund!$E:$AZ,_xlpm.rowNo,_xlpm.colNo), IF(ISNUMBER(_xlpm.val),_xlpm.val*$H14,"")) | L14: =_xlfn.LET( _xlpm.rowNo, MATCH($C14&"|"& ($F14+L$4),Raw_Fund!$A:$A,0), _xlpm.colNo, MATCH(L$3,Raw_Fund!$E$1:$AZ$1,0), _xlpm.val, INDEX(Raw_Fund!$E:$AZ,_xlpm.rowNo,_xlpm.colNo), IF(ISNUMBER(_xlpm.val),_xlpm.val*$H14,"")) | M14: =_xlfn.LET( _xlpm.rowNo, MATCH($C14&"|"& ($F14+M$4),Raw_Fund!$A:$A,0), _xlpm.colNo, MATCH(M$3,Raw_Fund!$E$1:$AZ$1,0), _xlpm.val, INDEX(Raw_Fund!$E:$AZ,_xlpm.rowNo,_xlpm.colNo), IF(ISNUMBER(_xlpm.val),_xlpm.val*$H14,"")) | N14: =_xlfn.LET( _xlpm.rowNo, MATCH($C14&"|"& ($F14+N$4),Raw_Fund!$A:$A,0), _xlpm.colNo, MATCH(N$3,Raw_Fund!$E$1:$AZ$1,0), _xlpm.val, INDEX(Raw_Fund!$E:$AZ,_xlpm.rowNo,_xlpm.colNo), IF(ISNUMBER(_xlpm.val),_xlpm.val*$H14,"")) | O14: =_xlfn.LET( _xlpm.rowNo, MATCH($C14&"|"& ($F14+O$4),Raw_Fund!$A:$A,0), _xlpm.colNo, MATCH(O$3,Raw_Fund!$E$1:$AZ$1,0), _xlpm.val, INDEX(Raw_Fund!$E:$AZ,_xlpm.rowNo,_xlpm.colNo), IF(ISNUMBER(_xlpm.val),_xlpm.val*$H14,"")) | P14: =_xlfn.LET( _xlpm.rowNo, MATCH($C14&"|"& ($F14+P$4),Raw_Fund!$A:$A,0), _xlpm.colNo, MATCH(P$3,Raw_Fund!$E$1:$AZ$1,0), _xlpm.val, INDEX(Raw_Fund!$E:$AZ,_xlpm.rowNo,_xlpm.colNo), IF(ISNUMBER(_xlpm.val),_xlpm.val*$H14,"")) | ... Y14: =_xlfn.LET( _xlpm.rowNo, MATCH($C14&"|"& ($F14+Y$4),Raw_Fund!$A:$A,0), _xlpm.colNo, MATCH(Y$3,Raw_Fund!$E$1:$AZ$1,0), _xlpm.val, INDEX(Raw_Fund!$E:$AZ,_xlpm.rowNo,_xlpm.colNo), IF(ISNUMBER(_xlpm.val),_xlpm.val*$H14,"")) | Z14: =IF($E14<>"Include","",_xlfn.XLOOKUP($C14,Raw_Mkt!$A:$A,Raw_Mkt!$B:$B)) -> #N/A
A15: =IF(Universe!A15<>"",Universe!A15,"") -> APN | B15: =IF(Universe!B15<>"",Universe!B15,"") -> Applied Nutrition | C15: =IF(Universe!C15<>"",Universe!C15,"") -> GB00BPVDXX64 | D15: =IF(Universe!D15<>"",Universe!D15,"") -> Consumer Staples | E15: =Universe!G15 -> Include | F15: =IF($E15<>"Include","",_xlfn.LET(_xlpm.latest,_xlfn.MAXIFS(Raw_Fund!$C:$C,Raw_Fund!$B:$B,Data!$C15),IF(_xlpm.latest=0,"",_xlpm.latest))) | G15: =IF($F15="","",INDEX(Raw_Fund!$E:$AZ,MATCH($C15&"|"&$F15,Raw_Fund!$A:$A,0),MATCH(G$3,Raw_Fund!$E$1:$AZ$1,0))) | H15: =IF($G15="","",_xlfn.XLOOKUP($G15,FX_Ccy,FX_Rate,"Missing FX")) | I15: =_xlfn.LET( _xlpm.rowNo, MATCH($C15&"|"& ($F15+I$4),Raw_Fund!$A:$A,0), _xlpm.colNo, MATCH(I$3,Raw_Fund!$E$1:$AZ$1,0), _xlpm.val, INDEX(Raw_Fund!$E:$AZ,_xlpm.rowNo,_xlpm.colNo), IF(ISNUMBER(_xlpm.val),_xlpm.val*$H15,"")) | J15: =_xlfn.LET( _xlpm.rowNo, MATCH($C15&"|"& ($F15+J$4),Raw_Fund!$A:$A,0), _xlpm.colNo, MATCH(J$3,Raw_Fund!$E$1:$AZ$1,0), _xlpm.val, INDEX(Raw_Fund!$E:$AZ,_xlpm.rowNo,_xlpm.colNo), IF(ISNUMBER(_xlpm.val),_xlpm.val*$H15,"")) | K15: =_xlfn.LET( _xlpm.rowNo, MATCH($C15&"|"& ($F15+K$4),Raw_Fund!$A:$A,0), _xlpm.colNo, MATCH(K$3,Raw_Fund!$E$1:$AZ$1,0), _xlpm.val, INDEX(Raw_Fund!$E:$AZ,_xlpm.rowNo,_xlpm.colNo), IF(ISNUMBER(_xlpm.val),_xlpm.val*$H15,"")) | L15: =_xlfn.LET( _xlpm.rowNo, MATCH($C15&"|"& ($F15+L$4),Raw_Fund!$A:$A,0), _xlpm.colNo, MATCH(L$3,Raw_Fund!$E$1:$AZ$1,0), _xlpm.val, INDEX(Raw_Fund!$E:$AZ,_xlpm.rowNo,_xlpm.colNo), IF(ISNUMBER(_xlpm.val),_xlpm.val*$H15,"")) | M15: =_xlfn.LET( _xlpm.rowNo, MATCH($C15&"|"& ($F15+M$4),Raw_Fund!$A:$A,0), _xlpm.colNo, MATCH(M$3,Raw_Fund!$E$1:$AZ$1,0), _xlpm.val, INDEX(Raw_Fund!$E:$AZ,_xlpm.rowNo,_xlpm.colNo), IF(ISNUMBER(_xlpm.val),_xlpm.val*$H15,"")) | N15: =_xlfn.LET( _xlpm.rowNo, MATCH($C15&"|"& ($F15+N$4),Raw_Fund!$A:$A,0), _xlpm.colNo, MATCH(N$3,Raw_Fund!$E$1:$AZ$1,0), _xlpm.val, INDEX(Raw_Fund!$E:$AZ,_xlpm.rowNo,_xlpm.colNo), IF(ISNUMBER(_xlpm.val),_xlpm.val*$H15,"")) | O15: =_xlfn.LET( _xlpm.rowNo, MATCH($C15&"|"& ($F15+O$4),Raw_Fund!$A:$A,0), _xlpm.colNo, MATCH(O$3,Raw_Fund!$E$1:$AZ$1,0), _xlpm.val, INDEX(Raw_Fund!$E:$AZ,_xlpm.rowNo,_xlpm.colNo), IF(ISNUMBER(_xlpm.val),_xlpm.val*$H15,"")) | P15: =_xlfn.LET( _xlpm.rowNo, MATCH($C15&"|"& ($F15+P$4),Raw_Fund!$A:$A,0), _xlpm.colNo, MATCH(P$3,Raw_Fund!$E$1:$AZ$1,0), _xlpm.val, INDEX(Raw_Fund!$E:$AZ,_xlpm.rowNo,_xlpm.colNo), IF(ISNUMBER(_xlpm.val),_xlpm.val*$H15,"")) | ... Y15: =_xlfn.LET( _xlpm.rowNo, MATCH($C15&"|"& ($F15+Y$4),Raw_Fund!$A:$A,0), _xlpm.colNo, MATCH(Y$3,Raw_Fund!$E$1:$AZ$1,0), _xlpm.val, INDEX(Raw_Fund!$E:$AZ,_xlpm.rowNo,_xlpm.colNo), IF(ISNUMBER(_xlpm.val),_xlpm.val*$H15,"")) | Z15: =IF($E15<>"Include","",_xlfn.XLOOKUP($C15,Raw_Mkt!$A:$A,Raw_Mkt!$B:$B)) -> #N/A
A16: =IF(Universe!A16<>"",Universe!A16,"") -> ASHM | B16: =IF(Universe!B16<>"",Universe!B16,"") -> Ashmore Group | C16: =IF(Universe!C16<>"",Universe!C16,"") -> GB00B132NW22 | D16: =IF(Universe!D16<>"",Universe!D16,"") -> Financials | E16: =Universe!G16 -> Exclude | G16: =IF($F16="","",INDEX(Raw_Fund!$E:$AZ,MATCH($C16&"|"&$F16,Raw_Fund!$A:$A,0),MATCH(G$3,Raw_Fund!$E$1:$AZ$1,0))) | H16: =IF($G16="","",_xlfn.XLOOKUP($G16,FX_Ccy,FX_Rate,"Missing FX")) | I16: =_xlfn.LET( _xlpm.rowNo, MATCH($C16&"|"& ($F16+I$4),Raw_Fund!$A:$A,0), _xlpm.colNo, MATCH(I$3,Raw_Fund!$E$1:$AZ$1,0), _xlpm.val, INDEX(Raw_Fund!$E:$AZ,_xlpm.rowNo,_xlpm.colNo), IF(ISNUMBER(_xlpm.val),_xlpm.val*$H16,"")) | J16: =_xlfn.LET( _xlpm.rowNo, MATCH($C16&"|"& ($F16+J$4),Raw_Fund!$A:$A,0), _xlpm.colNo, MATCH(J$3,Raw_Fund!$E$1:$AZ$1,0), _xlpm.val, INDEX(Raw_Fund!$E:$AZ,_xlpm.rowNo,_xlpm.colNo), IF(ISNUMBER(_xlpm.val),_xlpm.val*$H16,"")) | K16: =_xlfn.LET( _xlpm.rowNo, MATCH($C16&"|"& ($F16+K$4),Raw_Fund!$A:$A,0), _xlpm.colNo, MATCH(K$3,Raw_Fund!$E$1:$AZ$1,0), _xlpm.val, INDEX(Raw_Fund!$E:$AZ,_xlpm.rowNo,_xlpm.colNo), IF(ISNUMBER(_xlpm.val),_xlpm.val*$H16,"")) | L16: =_xlfn.LET( _xlpm.rowNo, MATCH($C16&"|"& ($F16+L$4),Raw_Fund!$A:$A,0), _xlpm.colNo, MATCH(L$3,Raw_Fund!$E$1:$AZ$1,0), _xlpm.val, INDEX(Raw_Fund!$E:$AZ,_xlpm.rowNo,_xlpm.colNo), IF(ISNUMBER(_xlpm.val),_xlpm.val*$H16,"")) | M16: =_xlfn.LET( _xlpm.rowNo, MATCH($C16&"|"& ($F16+M$4),Raw_Fund!$A:$A,0), _xlpm.colNo, MATCH(M$3,Raw_Fund!$E$1:$AZ$1,0), _xlpm.val, INDEX(Raw_Fund!$E:$AZ,_xlpm.rowNo,_xlpm.colNo), IF(ISNUMBER(_xlpm.val),_xlpm.val*$H16,"")) | N16: =_xlfn.LET( _xlpm.rowNo, MATCH($C16&"|"& ($F16+N$4),Raw_Fund!$A:$A,0), _xlpm.colNo, MATCH(N$3,Raw_Fund!$E$1:$AZ$1,0), _xlpm.val, INDEX(Raw_Fund!$E:$AZ,_xlpm.rowNo,_xlpm.colNo), IF(ISNUMBER(_xlpm.val),_xlpm.val*$H16,"")) | O16: =_xlfn.LET( _xlpm.rowNo, MATCH($C16&"|"& ($F16+O$4),Raw_Fund!$A:$A,0), _xlpm.colNo, MATCH(O$3,Raw_Fund!$E$1:$AZ$1,0), _xlpm.val, INDEX(Raw_Fund!$E:$AZ,_xlpm.rowNo,_xlpm.colNo), IF(ISNUMBER(_xlpm.val),_xlpm.val*$H16,"")) | P16: =_xlfn.LET( _xlpm.rowNo, MATCH($C16&"|"& ($F16+P$4),Raw_Fund!$A:$A,0), _xlpm.colNo, MATCH(P$3,Raw_Fund!$E$1:$AZ$1,0), _xlpm.val, INDEX(Raw_Fund!$E:$AZ,_xlpm.rowNo,_xlpm.colNo), IF(ISNUMBER(_xlpm.val),_xlpm.val*$H16,"")) | ... Y16: =_xlfn.LET( _xlpm.rowNo, MATCH($C16&"|"& ($F16+Y$4),Raw_Fund!$A:$A,0), _xlpm.colNo, MATCH(Y$3,Raw_Fund!$E$1:$AZ$1,0), _xlpm.val, INDEX(Raw_Fund!$E:$AZ,_xlpm.rowNo,_xlpm.colNo), IF(ISNUMBER(_xlpm.val),_xlpm.val*$H16,"")) | Z16: =IF($E16<>"Include","",_xlfn.XLOOKUP($C16,Raw_Mkt!$A:$A,Raw_Mkt!$B:$B))
A17: =IF(Universe!A17<>"",Universe!A17,"") -> AIE | B17: =IF(Universe!B17<>"",Universe!B17,"") -> Ashoka India Equity Investment Trust | C17: =IF(Universe!C17<>"",Universe!C17,"") -> GB00BF50VS41 | D17: =IF(Universe!D17<>"",Universe!D17,"") -> Financials | E17: =Universe!G17 -> Exclude | F17: =IF($E17<>"Include","",_xlfn.LET(_xlpm.latest,_xlfn.MAXIFS(Raw_Fund!$C:$C,Raw_Fund!$B:$B,Data!$C17),IF(_xlpm.latest=0,"",_xlpm.latest))) | G17: =IF($F17="","",INDEX(Raw_Fund!$E:$AZ,MATCH($C17&"|"&$F17,Raw_Fund!$A:$A,0),MATCH(G$3,Raw_Fund!$E$1:$AZ$1,0))) | H17: =IF($G17="","",_xlfn.XLOOKUP($G17,FX_Ccy,FX_Rate,"Missing FX")) | I17: =_xlfn.LET( _xlpm.rowNo, MATCH($C17&"|"& ($F17+I$4),Raw_Fund!$A:$A,0), _xlpm.colNo, MATCH(I$3,Raw_Fund!$E$1:$AZ$1,0), _xlpm.val, INDEX(Raw_Fund!$E:$AZ,_xlpm.rowNo,_xlpm.colNo), IF(ISNUMBER(_xlpm.val),_xlpm.val*$H17,"")) | J17: =_xlfn.LET( _xlpm.rowNo, MATCH($C17&"|"& ($F17+J$4),Raw_Fund!$A:$A,0), _xlpm.colNo, MATCH(J$3,Raw_Fund!$E$1:$AZ$1,0), _xlpm.val, INDEX(Raw_Fund!$E:$AZ,_xlpm.rowNo,_xlpm.colNo), IF(ISNUMBER(_xlpm.val),_xlpm.val*$H17,"")) | K17: =_xlfn.LET( _xlpm.rowNo, MATCH($C17&"|"& ($F17+K$4),Raw_Fund!$A:$A,0), _xlpm.colNo, MATCH(K$3,Raw_Fund!$E$1:$AZ$1,0), _xlpm.val, INDEX(Raw_Fund!$E:$AZ,_xlpm.rowNo,_xlpm.colNo), IF(ISNUMBER(_xlpm.val),_xlpm.val*$H17,"")) | L17: =_xlfn.LET( _xlpm.rowNo, MATCH($C17&"|"& ($F17+L$4),Raw_Fund!$A:$A,0), _xlpm.colNo, MATCH(L$3,Raw_Fund!$E$1:$AZ$1,0), _xlpm.val, INDEX(Raw_Fund!$E:$AZ,_xlpm.rowNo,_xlpm.colNo), IF(ISNUMBER(_xlpm.val),_xlpm.val*$H17,"")) | M17: =_xlfn.LET( _xlpm.rowNo, MATCH($C17&"|"& ($F17+M$4),Raw_Fund!$A:$A,0), _xlpm.colNo, MATCH(M$3,Raw_Fund!$E$1:$AZ$1,0), _xlpm.val, INDEX(Raw_Fund!$E:$AZ,_xlpm.rowNo,_xlpm.colNo), IF(ISNUMBER(_xlpm.val),_xlpm.val*$H17,"")) | N17: =_xlfn.LET( _xlpm.rowNo, MATCH($C17&"|"& ($F17+N$4),Raw_Fund!$A:$A,0), _xlpm.colNo, MATCH(N$3,Raw_Fund!$E$1:$AZ$1,0), _xlpm.val, INDEX(Raw_Fund!$E:$AZ,_xlpm.rowNo,_xlpm.colNo), IF(ISNUMBER(_xlpm.val),_xlpm.val*$H17,"")) | O17: =_xlfn.LET( _xlpm.rowNo, MATCH($C17&"|"& ($F17+O$4),Raw_Fund!$A:$A,0), _xlpm.colNo, MATCH(O$3,Raw_Fund!$E$1:$AZ$1,0), _xlpm.val, INDEX(Raw_Fund!$E:$AZ,_xlpm.rowNo,_xlpm.colNo), IF(ISNUMBER(_xlpm.val),_xlpm.val*$H17,"")) | P17: =_xlfn.LET( _xlpm.rowNo, MATCH($C17&"|"& ($F17+P$4),Raw_Fund!$A:$A,0), _xlpm.colNo, MATCH(P$3,Raw_Fund!$E$1:$AZ$1,0), _xlpm.val, INDEX(Raw_Fund!$E:$AZ,_xlpm.rowNo,_xlpm.colNo), IF(ISNUMBER(_xlpm.val),_xlpm.val*$H17,"")) | ... Y17: =_xlfn.LET( _xlpm.rowNo, MATCH($C17&"|"& ($F17+Y$4),Raw_Fund!$A:$A,0), _xlpm.colNo, MATCH(Y$3,Raw_Fund!$E$1:$AZ$1,0), _xlpm.val, INDEX(Raw_Fund!$E:$AZ,_xlpm.rowNo,_xlpm.colNo), IF(ISNUMBER(_xlpm.val),_xlpm.val*$H17,"")) | Z17: =IF($E17<>"Include","",_xlfn.XLOOKUP($C17,Raw_Mkt!$A:$A,Raw_Mkt!$B:$B))
A18: =IF(Universe!A18<>"",Universe!A18,"") -> ASC | B18: =IF(Universe!B18<>"",Universe!B18,"") -> ASOS | C18: =IF(Universe!C18<>"",Universe!C18,"") -> GB0030927254 | D18: =IF(Universe!D18<>"",Universe!D18,"") -> Consumer Discretionary | E18: =Universe!G18 -> Include | F18: =IF($E18<>"Include","",_xlfn.LET(_xlpm.latest,_xlfn.MAXIFS(Raw_Fund!$C:$C,Raw_Fund!$B:$B,Data!$C18),IF(_xlpm.latest=0,"",_xlpm.latest))) | G18: =IF($F18="","",INDEX(Raw_Fund!$E:$AZ,MATCH($C18&"|"&$F18,Raw_Fund!$A:$A,0),MATCH(G$3,Raw_Fund!$E$1:$AZ$1,0))) | H18: =IF($G18="","",_xlfn.XLOOKUP($G18,FX_Ccy,FX_Rate,"Missing FX")) | I18: =_xlfn.LET( _xlpm.rowNo, MATCH($C18&"|"& ($F18+I$4),Raw_Fund!$A:$A,0), _xlpm.colNo, MATCH(I$3,Raw_Fund!$E$1:$AZ$1,0), _xlpm.val, INDEX(Raw_Fund!$E:$AZ,_xlpm.rowNo,_xlpm.colNo), IF(ISNUMBER(_xlpm.val),_xlpm.val*$H18,"")) | J18: =_xlfn.LET( _xlpm.rowNo, MATCH($C18&"|"& ($F18+J$4),Raw_Fund!$A:$A,0), _xlpm.colNo, MATCH(J$3,Raw_Fund!$E$1:$AZ$1,0), _xlpm.val, INDEX(Raw_Fund!$E:$AZ,_xlpm.rowNo,_xlpm.colNo), IF(ISNUMBER(_xlpm.val),_xlpm.val*$H18,"")) | K18: =_xlfn.LET( _xlpm.rowNo, MATCH($C18&"|"& ($F18+K$4),Raw_Fund!$A:$A,0), _xlpm.colNo, MATCH(K$3,Raw_Fund!$E$1:$AZ$1,0), _xlpm.val, INDEX(Raw_Fund!$E:$AZ,_xlpm.rowNo,_xlpm.colNo), IF(ISNUMBER(_xlpm.val),_xlpm.val*$H18,"")) | L18: =_xlfn.LET( _xlpm.rowNo, MATCH($C18&"|"& ($F18+L$4),Raw_Fund!$A:$A,0), _xlpm.colNo, MATCH(L$3,Raw_Fund!$E$1:$AZ$1,0), _xlpm.val, INDEX(Raw_Fund!$E:$AZ,_xlpm.rowNo,_xlpm.colNo), IF(ISNUMBER(_xlpm.val),_xlpm.val*$H18,"")) | M18: =_xlfn.LET( _xlpm.rowNo, MATCH($C18&"|"& ($F18+M$4),Raw_Fund!$A:$A,0), _xlpm.colNo, MATCH(M$3,Raw_Fund!$E$1:$AZ$1,0), _xlpm.val, INDEX(Raw_Fund!$E:$AZ,_xlpm.rowNo,_xlpm.colNo), IF(ISNUMBER(_xlpm.val),_xlpm.val*$H18,"")) | N18: =_xlfn.LET( _xlpm.rowNo, MATCH($C18&"|"& ($F18+N$4),Raw_Fund!$A:$A,0), _xlpm.colNo, MATCH(N$3,Raw_Fund!$E$1:$AZ$1,0), _xlpm.val, INDEX(Raw_Fund!$E:$AZ,_xlpm.rowNo,_xlpm.colNo), IF(ISNUMBER(_xlpm.val),_xlpm.val*$H18,"")) | O18: =_xlfn.LET( _xlpm.rowNo, MATCH($C18&"|"& ($F18+O$4),Raw_Fund!$A:$A,0), _xlpm.colNo, MATCH(O$3,Raw_Fund!$E$1:$AZ$1,0), _xlpm.val, INDEX(Raw_Fund!$E:$AZ,_xlpm.rowNo,_xlpm.colNo), IF(ISNUMBER(_xlpm.val),_xlpm.val*$H18,"")) | P18: =_xlfn.LET( _xlpm.rowNo, MATCH($C18&"|"& ($F18+P$4),Raw_Fund!$A:$A,0), _xlpm.colNo, MATCH(P$3,Raw_Fund!$E$1:$AZ$1,0), _xlpm.val, INDEX(Raw_Fund!$E:$AZ,_xlpm.rowNo,_xlpm.colNo), IF(ISNUMBER(_xlpm.val),_xlpm.val*$H18,"")) | ... Y18: =_xlfn.LET( _xlpm.rowNo, MATCH($C18&"|"& ($F18+Y$4),Raw_Fund!$A:$A,0), _xlpm.colNo, MATCH(Y$3,Raw_Fund!$E$1:$AZ$1,0), _xlpm.val, INDEX(Raw_Fund!$E:$AZ,_xlpm.rowNo,_xlpm.colNo), IF(ISNUMBER(_xlpm.val),_xlpm.val*$H18,"")) | Z18: =IF($E18<>"Include","",_xlfn.XLOOKUP($C18,Raw_Mkt!$A:$A,Raw_Mkt!$B:$B)) -> #N/A
A19: =IF(Universe!A19<>"",Universe!A19,"") -> ATYM | B19: =IF(Universe!B19<>"",Universe!B19,"") -> Atalaya Mining | C19: =IF(Universe!C19<>"",Universe!C19,"") -> CY0106002112 | D19: =IF(Universe!D19<>"",Universe!D19,"") -> Basic Materials | E19: =Universe!G19 -> Include | F19: =IF($E19<>"Include","",_xlfn.LET(_xlpm.latest,_xlfn.MAXIFS(Raw_Fund!$C:$C,Raw_Fund!$B:$B,Data!$C19),IF(_xlpm.latest=0,"",_xlpm.latest))) | G19: =IF($F19="","",INDEX(Raw_Fund!$E:$AZ,MATCH($C19&"|"&$F19,Raw_Fund!$A:$A,0),MATCH(G$3,Raw_Fund!$E$1:$AZ$1,0))) | H19: =IF($G19="","",_xlfn.XLOOKUP($G19,FX_Ccy,FX_Rate,"Missing FX")) | I19: =_xlfn.LET( _xlpm.rowNo, MATCH($C19&"|"& ($F19+I$4),Raw_Fund!$A:$A,0), _xlpm.colNo, MATCH(I$3,Raw_Fund!$E$1:$AZ$1,0), _xlpm.val, INDEX(Raw_Fund!$E:$AZ,_xlpm.rowNo,_xlpm.colNo), IF(ISNUMBER(_xlpm.val),_xlpm.val*$H19,"")) | J19: =_xlfn.LET( _xlpm.rowNo, MATCH($C19&"|"& ($F19+J$4),Raw_Fund!$A:$A,0), _xlpm.colNo, MATCH(J$3,Raw_Fund!$E$1:$AZ$1,0), _xlpm.val, INDEX(Raw_Fund!$E:$AZ,_xlpm.rowNo,_xlpm.colNo), IF(ISNUMBER(_xlpm.val),_xlpm.val*$H19,"")) | K19: =_xlfn.LET( _xlpm.rowNo, MATCH($C19&"|"& ($F19+K$4),Raw_Fund!$A:$A,0), _xlpm.colNo, MATCH(K$3,Raw_Fund!$E$1:$AZ$1,0), _xlpm.val, INDEX(Raw_Fund!$E:$AZ,_xlpm.rowNo,_xlpm.colNo), IF(ISNUMBER(_xlpm.val),_xlpm.val*$H19,"")) | L19: =_xlfn.LET( _xlpm.rowNo, MATCH($C19&"|"& ($F19+L$4),Raw_Fund!$A:$A,0), _xlpm.colNo, MATCH(L$3,Raw_Fund!$E$1:$AZ$1,0), _xlpm.val, INDEX(Raw_Fund!$E:$AZ,_xlpm.rowNo,_xlpm.colNo), IF(ISNUMBER(_xlpm.val),_xlpm.val*$H19,"")) | M19: =_xlfn.LET( _xlpm.rowNo, MATCH($C19&"|"& ($F19+M$4),Raw_Fund!$A:$A,0), _xlpm.colNo, MATCH(M$3,Raw_Fund!$E$1:$AZ$1,0), _xlpm.val, INDEX(Raw_Fund!$E:$AZ,_xlpm.rowNo,_xlpm.colNo), IF(ISNUMBER(_xlpm.val),_xlpm.val*$H19,"")) | N19: =_xlfn.LET( _xlpm.rowNo, MATCH($C19&"|"& ($F19+N$4),Raw_Fund!$A:$A,0), _xlpm.colNo, MATCH(N$3,Raw_Fund!$E$1:$AZ$1,0), _xlpm.val, INDEX(Raw_Fund!$E:$AZ,_xlpm.rowNo,_xlpm.colNo), IF(ISNUMBER(_xlpm.val),_xlpm.val*$H19,"")) | O19: =_xlfn.LET( _xlpm.rowNo, MATCH($C19&"|"& ($F19+O$4),Raw_Fund!$A:$A,0), _xlpm.colNo, MATCH(O$3,Raw_Fund!$E$1:$AZ$1,0), _xlpm.val, INDEX(Raw_Fund!$E:$AZ,_xlpm.rowNo,_xlpm.colNo), IF(ISNUMBER(_xlpm.val),_xlpm.val*$H19,"")) | P19: =_xlfn.LET( _xlpm.rowNo, MATCH($C19&"|"& ($F19+P$4),Raw_Fund!$A:$A,0), _xlpm.colNo, MATCH(P$3,Raw_Fund!$E$1:$AZ$1,0), _xlpm.val, INDEX(Raw_Fund!$E:$AZ,_xlpm.rowNo,_xlpm.colNo), IF(ISNUMBER(_xlpm.val),_xlpm.val*$H19,"")) | ... Y19: =_xlfn.LET( _xlpm.rowNo, MATCH($C19&"|"& ($F19+Y$4),Raw_Fund!$A:$A,0), _xlpm.colNo, MATCH(Y$3,Raw_Fund!$E$1:$AZ$1,0), _xlpm.val, INDEX(Raw_Fund!$E:$AZ,_xlpm.rowNo,_xlpm.colNo), IF(ISNUMBER(_xlpm.val),_xlpm.val*$H19,"")) | Z19: =IF($E19<>"Include","",_xlfn.XLOOKUP($C19,Raw_Mkt!$A:$A,Raw_Mkt!$B:$B)) -> #N/A
A20: =IF(Universe!A20<>"",Universe!A20,"") -> ATG | B20: =IF(Universe!B20<>"",Universe!B20,"") -> Auction Technology Group | C20: =IF(Universe!C20<>"",Universe!C20,"") -> GB00BMVQDZ64 | D20: =IF(Universe!D20<>"",Universe!D20,"") -> Technology | E20: =Universe!G20 -> Include | F20: =IF($E20<>"Include","",_xlfn.LET(_xlpm.latest,_xlfn.MAXIFS(Raw_Fund!$C:$C,Raw_Fund!$B:$B,Data!$C20),IF(_xlpm.latest=0,"",_xlpm.latest))) | G20: =IF($F20="","",INDEX(Raw_Fund!$E:$AZ,MATCH($C20&"|"&$F20,Raw_Fund!$A:$A,0),MATCH(G$3,Raw_Fund!$E$1:$AZ$1,0))) | H20: =IF($G20="","",_xlfn.XLOOKUP($G20,FX_Ccy,FX_Rate,"Missing FX")) | I20: =_xlfn.LET( _xlpm.rowNo, MATCH($C20&"|"& ($F20+I$4),Raw_Fund!$A:$A,0), _xlpm.colNo, MATCH(I$3,Raw_Fund!$E$1:$AZ$1,0), _xlpm.val, INDEX(Raw_Fund!$E:$AZ,_xlpm.rowNo,_xlpm.colNo), IF(ISNUMBER(_xlpm.val),_xlpm.val*$H20,"")) | J20: =_xlfn.LET( _xlpm.rowNo, MATCH($C20&"|"& ($F20+J$4),Raw_Fund!$A:$A,0), _xlpm.colNo, MATCH(J$3,Raw_Fund!$E$1:$AZ$1,0), _xlpm.val, INDEX(Raw_Fund!$E:$AZ,_xlpm.rowNo,_xlpm.colNo), IF(ISNUMBER(_xlpm.val),_xlpm.val*$H20,"")) | K20: =_xlfn.LET( _xlpm.rowNo, MATCH($C20&"|"& ($F20+K$4),Raw_Fund!$A:$A,0), _xlpm.colNo, MATCH(K$3,Raw_Fund!$E$1:$AZ$1,0), _xlpm.val, INDEX(Raw_Fund!$E:$AZ,_xlpm.rowNo,_xlpm.colNo), IF(ISNUMBER(_xlpm.val),_xlpm.val*$H20,"")) | L20: =_xlfn.LET( _xlpm.rowNo, MATCH($C20&"|"& ($F20+L$4),Raw_Fund!$A:$A,0), _xlpm.colNo, MATCH(L$3,Raw_Fund!$E$1:$AZ$1,0), _xlpm.val, INDEX(Raw_Fund!$E:$AZ,_xlpm.rowNo,_xlpm.colNo), IF(ISNUMBER(_xlpm.val),_xlpm.val*$H20,"")) | M20: =_xlfn.LET( _xlpm.rowNo, MATCH($C20&"|"& ($F20+M$4),Raw_Fund!$A:$A,0), _xlpm.colNo, MATCH(M$3,Raw_Fund!$E$1:$AZ$1,0), _xlpm.val, INDEX(Raw_Fund!$E:$AZ,_xlpm.rowNo,_xlpm.colNo), IF(ISNUMBER(_xlpm.val),_xlpm.val*$H20,"")) | N20: =_xlfn.LET( _xlpm.rowNo, MATCH($C20&"|"& ($F20+N$4),Raw_Fund!$A:$A,0), _xlpm.colNo, MATCH(N$3,Raw_Fund!$E$1:$AZ$1,0), _xlpm.val, INDEX(Raw_Fund!$E:$AZ,_xlpm.rowNo,_xlpm.colNo), IF(ISNUMBER(_xlpm.val),_xlpm.val*$H20,"")) | O20: =_xlfn.LET( _xlpm.rowNo, MATCH($C20&"|"& ($F20+O$4),Raw_Fund!$A:$A,0), _xlpm.colNo, MATCH(O$3,Raw_Fund!$E$1:$AZ$1,0), _xlpm.val, INDEX(Raw_Fund!$E:$AZ,_xlpm.rowNo,_xlpm.colNo), IF(ISNUMBER(_xlpm.val),_xlpm.val*$H20,"")) | P20: =_xlfn.LET( _xlpm.rowNo, MATCH($C20&"|"& ($F20+P$4),Raw_Fund!$A:$A,0), _xlpm.colNo, MATCH(P$3,Raw_Fund!$E$1:$AZ$1,0), _xlpm.val, INDEX(Raw_Fund!$E:$AZ,_xlpm.rowNo,_xlpm.colNo), IF(ISNUMBER(_xlpm.val),_xlpm.val*$H20,"")) | ... Y20: =_xlfn.LET( _xlpm.rowNo, MATCH($C20&"|"& ($F20+Y$4),Raw_Fund!$A:$A,0), _xlpm.colNo, MATCH(Y$3,Raw_Fund!$E$1:$AZ$1,0), _xlpm.val, INDEX(Raw_Fund!$E:$AZ,_xlpm.rowNo,_xlpm.colNo), IF(ISNUMBER(_xlpm.val),_xlpm.val*$H20,"")) | Z20: =IF($E20<>"Include","",_xlfn.XLOOKUP($C20,Raw_Mkt!$A:$A,Raw_Mkt!$B:$B)) -> #N/A
A21: =IF(Universe!A21<>"",Universe!A21,"") -> AGT | B21: =IF(Universe!B21<>"",Universe!B21,"") -> AVI Global Trust | C21: =IF(Universe!C21<>"",Universe!C21,"") -> GB00BLH3CY60 | D21: =IF(Universe!D21<>"",Universe!D21,"") -> Financials | E21: =Universe!G21 -> Exclude | F21: =IF($E21<>"Include","",_xlfn.LET(_xlpm.latest,_xlfn.MAXIFS(Raw_Fund!$C:$C,Raw_Fund!$B:$B,Data!$C21),IF(_xlpm.latest=0,"",_xlpm.latest))) | G21: =IF($F21="","",INDEX(Raw_Fund!$E:$AZ,MATCH($C21&"|"&$F21,Raw_Fund!$A:$A,0),MATCH(G$3,Raw_Fund!$E$1:$AZ$1,0))) | H21: =IF($G21="","",_xlfn.XLOOKUP($G21,FX_Ccy,FX_Rate,"Missing FX")) | I21: =_xlfn.LET( _xlpm.rowNo, MATCH($C21&"|"& ($F21+I$4),Raw_Fund!$A:$A,0), _xlpm.colNo, MATCH(I$3,Raw_Fund!$E$1:$AZ$1,0), _xlpm.val, INDEX(Raw_Fund!$E:$AZ,_xlpm.rowNo,_xlpm.colNo), IF(ISNUMBER(_xlpm.val),_xlpm.val*$H21,"")) | J21: =_xlfn.LET( _xlpm.rowNo, MATCH($C21&"|"& ($F21+J$4),Raw_Fund!$A:$A,0), _xlpm.colNo, MATCH(J$3,Raw_Fund!$E$1:$AZ$1,0), _xlpm.val, INDEX(Raw_Fund!$E:$AZ,_xlpm.rowNo,_xlpm.colNo), IF(ISNUMBER(_xlpm.val),_xlpm.val*$H21,"")) | K21: =_xlfn.LET( _xlpm.rowNo, MATCH($C21&"|"& ($F21+K$4),Raw_Fund!$A:$A,0), _xlpm.colNo, MATCH(K$3,Raw_Fund!$E$1:$AZ$1,0), _xlpm.val, INDEX(Raw_Fund!$E:$AZ,_xlpm.rowNo,_xlpm.colNo), IF(ISNUMBER(_xlpm.val),_xlpm.val*$H21,"")) | L21: =_xlfn.LET( _xlpm.rowNo, MATCH($C21&"|"& ($F21+L$4),Raw_Fund!$A:$A,0), _xlpm.colNo, MATCH(L$3,Raw_Fund!$E$1:$AZ$1,0), _xlpm.val, INDEX(Raw_Fund!$E:$AZ,_xlpm.rowNo,_xlpm.colNo), IF(ISNUMBER(_xlpm.val),_xlpm.val*$H21,"")) | M21: =_xlfn.LET( _xlpm.rowNo, MATCH($C21&"|"& ($F21+M$4),Raw_Fund!$A:$A,0), _xlpm.colNo, MATCH(M$3,Raw_Fund!$E$1:$AZ$1,0), _xlpm.val, INDEX(Raw_Fund!$E:$AZ,_xlpm.rowNo,_xlpm.colNo), IF(ISNUMBER(_xlpm.val),_xlpm.val*$H21,"")) | N21: =_xlfn.LET( _xlpm.rowNo, MATCH($C21&"|"& ($F21+N$4),Raw_Fund!$A:$A,0), _xlpm.colNo, MATCH(N$3,Raw_Fund!$E$1:$AZ$1,0), _xlpm.val, INDEX(Raw_Fund!$E:$AZ,_xlpm.rowNo,_xlpm.colNo), IF(ISNUMBER(_xlpm.val),_xlpm.val*$H21,"")) | O21: =_xlfn.LET( _xlpm.rowNo, MATCH($C21&"|"& ($F21+O$4),Raw_Fund!$A:$A,0), _xlpm.colNo, MATCH(O$3,Raw_Fund!$E$1:$AZ$1,0), _xlpm.val, INDEX(Raw_Fund!$E:$AZ,_xlpm.rowNo,_xlpm.colNo), IF(ISNUMBER(_xlpm.val),_xlpm.val*$H21,"")) | P21: =_xlfn.LET( _xlpm.rowNo, MATCH($C21&"|"& ($F21+P$4),Raw_Fund!$A:$A,0), _xlpm.colNo, MATCH(P$3,Raw_Fund!$E$1:$AZ$1,0), _xlpm.val, INDEX(Raw_Fund!$E:$AZ,_xlpm.rowNo,_xlpm.colNo), IF(ISNUMBER(_xlpm.val),_xlpm.val*$H21,"")) | ... Y21: =_xlfn.LET( _xlpm.rowNo, MATCH($C21&"|"& ($F21+Y$4),Raw_Fund!$A:$A,0), _xlpm.colNo, MATCH(Y$3,Raw_Fund!$E$1:$AZ$1,0), _xlpm.val, INDEX(Raw_Fund!$E:$AZ,_xlpm.rowNo,_xlpm.colNo), IF(ISNUMBER(_xlpm.val),_xlpm.val*$H21,"")) | Z21: =IF($E21<>"Include","",_xlfn.XLOOKUP($C21,Raw_Mkt!$A:$A,Raw_Mkt!$B:$B))
A22: =IF(Universe!A22<>"",Universe!A22,"") -> AVON | B22: =IF(Universe!B22<>"",Universe!B22,"") -> Avon Technologies | C22: =IF(Universe!C22<>"",Universe!C22,"") -> GB0000667013 | D22: =IF(Universe!D22<>"",Universe!D22,"") -> Industrials | E22: =Universe!G22 -> Include | F22: =IF($E22<>"Include","",_xlfn.LET(_xlpm.latest,_xlfn.MAXIFS(Raw_Fund!$C:$C,Raw_Fund!$B:$B,Data!$C22),IF(_xlpm.latest=0,"",_xlpm.latest))) | G22: =IF($F22="","",INDEX(Raw_Fund!$E:$AZ,MATCH($C22&"|"&$F22,Raw_Fund!$A:$A,0),MATCH(G$3,Raw_Fund!$E$1:$AZ$1,0))) | H22: =IF($G22="","",_xlfn.XLOOKUP($G22,FX_Ccy,FX_Rate,"Missing FX")) | I22: =_xlfn.LET( _xlpm.rowNo, MATCH($C22&"|"& ($F22+I$4),Raw_Fund!$A:$A,0), _xlpm.colNo, MATCH(I$3,Raw_Fund!$E$1:$AZ$1,0), _xlpm.val, INDEX(Raw_Fund!$E:$AZ,_xlpm.rowNo,_xlpm.colNo), IF(ISNUMBER(_xlpm.val),_xlpm.val*$H22,"")) | J22: =_xlfn.LET( _xlpm.rowNo, MATCH($C22&"|"& ($F22+J$4),Raw_Fund!$A:$A,0), _xlpm.colNo, MATCH(J$3,Raw_Fund!$E$1:$AZ$1,0), _xlpm.val, INDEX(Raw_Fund!$E:$AZ,_xlpm.rowNo,_xlpm.colNo), IF(ISNUMBER(_xlpm.val),_xlpm.val*$H22,"")) | K22: =_xlfn.LET( _xlpm.rowNo, MATCH($C22&"|"& ($F22+K$4),Raw_Fund!$A:$A,0), _xlpm.colNo, MATCH(K$3,Raw_Fund!$E$1:$AZ$1,0), _xlpm.val, INDEX(Raw_Fund!$E:$AZ,_xlpm.rowNo,_xlpm.colNo), IF(ISNUMBER(_xlpm.val),_xlpm.val*$H22,"")) | L22: =_xlfn.LET( _xlpm.rowNo, MATCH($C22&"|"& ($F22+L$4),Raw_Fund!$A:$A,0), _xlpm.colNo, MATCH(L$3,Raw_Fund!$E$1:$AZ$1,0), _xlpm.val, INDEX(Raw_Fund!$E:$AZ,_xlpm.rowNo,_xlpm.colNo), IF(ISNUMBER(_xlpm.val),_xlpm.val*$H22,"")) | M22: =_xlfn.LET( _xlpm.rowNo, MATCH($C22&"|"& ($F22+M$4),Raw_Fund!$A:$A,0), _xlpm.colNo, MATCH(M$3,Raw_Fund!$E$1:$AZ$1,0), _xlpm.val, INDEX(Raw_Fund!$E:$AZ,_xlpm.rowNo,_xlpm.colNo), IF(ISNUMBER(_xlpm.val),_xlpm.val*$H22,"")) | N22: =_xlfn.LET( _xlpm.rowNo, MATCH($C22&"|"& ($F22+N$4),Raw_Fund!$A:$A,0), _xlpm.colNo, MATCH(N$3,Raw_Fund!$E$1:$AZ$1,0), _xlpm.val, INDEX(Raw_Fund!$E:$AZ,_xlpm.rowNo,_xlpm.colNo), IF(ISNUMBER(_xlpm.val),_xlpm.val*$H22,"")) | O22: =_xlfn.LET( _xlpm.rowNo, MATCH($C22&"|"& ($F22+O$4),Raw_Fund!$A:$A,0), _xlpm.colNo, MATCH(O$3,Raw_Fund!$E$1:$AZ$1,0), _xlpm.val, INDEX(Raw_Fund!$E:$AZ,_xlpm.rowNo,_xlpm.colNo), IF(ISNUMBER(_xlpm.val),_xlpm.val*$H22,"")) | P22: =_xlfn.LET( _xlpm.rowNo, MATCH($C22&"|"& ($F22+P$4),Raw_Fund!$A:$A,0), _xlpm.colNo, MATCH(P$3,Raw_Fund!$E$1:$AZ$1,0), _xlpm.val, INDEX(Raw_Fund!$E:$AZ,_xlpm.rowNo,_xlpm.colNo), IF(ISNUMBER(_xlpm.val),_xlpm.val*$H22,"")) | ... Y22: =_xlfn.LET( _xlpm.rowNo, MATCH($C22&"|"& ($F22+Y$4),Raw_Fund!$A:$A,0), _xlpm.colNo, MATCH(Y$3,Raw_Fund!$E$1:$AZ$1,0), _xlpm.val, INDEX(Raw_Fund!$E:$AZ,_xlpm.rowNo,_xlpm.colNo), IF(ISNUMBER(_xlpm.val),_xlpm.val*$H22,"")) | Z22: =IF($E22<>"Include","",_xlfn.XLOOKUP($C22,Raw_Mkt!$A:$A,Raw_Mkt!$B:$B)) -> #N/A
A23: =IF(Universe!A23<>"",Universe!A23,"") -> BME | B23: =IF(Universe!B23<>"",Universe!B23,"") -> B&M | C23: =IF(Universe!C23<>"",Universe!C23,"") -> JE00BVSYJW51 | D23: =IF(Universe!D23<>"",Universe!D23,"") -> Consumer Discretionary | E23: =Universe!G23 -> Include | F23: =IF($E23<>"Include","",_xlfn.LET(_xlpm.latest,_xlfn.MAXIFS(Raw_Fund!$C:$C,Raw_Fund!$B:$B,Data!$C23),IF(_xlpm.latest=0,"",_xlpm.latest))) | G23: =IF($F23="","",INDEX(Raw_Fund!$E:$AZ,MATCH($C23&"|"&$F23,Raw_Fund!$A:$A,0),MATCH(G$3,Raw_Fund!$E$1:$AZ$1,0))) | H23: =IF($G23="","",_xlfn.XLOOKUP($G23,FX_Ccy,FX_Rate,"Missing FX")) | I23: =_xlfn.LET( _xlpm.rowNo, MATCH($C23&"|"& ($F23+I$4),Raw_Fund!$A:$A,0), _xlpm.colNo, MATCH(I$3,Raw_Fund!$E$1:$AZ$1,0), _xlpm.val, INDEX(Raw_Fund!$E:$AZ,_xlpm.rowNo,_xlpm.colNo), IF(ISNUMBER(_xlpm.val),_xlpm.val*$H23,"")) | J23: =_xlfn.LET( _xlpm.rowNo, MATCH($C23&"|"& ($F23+J$4),Raw_Fund!$A:$A,0), _xlpm.colNo, MATCH(J$3,Raw_Fund!$E$1:$AZ$1,0), _xlpm.val, INDEX(Raw_Fund!$E:$AZ,_xlpm.rowNo,_xlpm.colNo), IF(ISNUMBER(_xlpm.val),_xlpm.val*$H23,"")) | K23: =_xlfn.LET( _xlpm.rowNo, MATCH($C23&"|"& ($F23+K$4),Raw_Fund!$A:$A,0), _xlpm.colNo, MATCH(K$3,Raw_Fund!$E$1:$AZ$1,0), _xlpm.val, INDEX(Raw_Fund!$E:$AZ,_xlpm.rowNo,_xlpm.colNo), IF(ISNUMBER(_xlpm.val),_xlpm.val*$H23,"")) | L23: =_xlfn.LET( _xlpm.rowNo, MATCH($C23&"|"& ($F23+L$4),Raw_Fund!$A:$A,0), _xlpm.colNo, MATCH(L$3,Raw_Fund!$E$1:$AZ$1,0), _xlpm.val, INDEX(Raw_Fund!$E:$AZ,_xlpm.rowNo,_xlpm.colNo), IF(ISNUMBER(_xlpm.val),_xlpm.val*$H23,"")) | M23: =_xlfn.LET( _xlpm.rowNo, MATCH($C23&"|"& ($F23+M$4),Raw_Fund!$A:$A,0), _xlpm.colNo, MATCH(M$3,Raw_Fund!$E$1:$AZ$1,0), _xlpm.val, INDEX(Raw_Fund!$E:$AZ,_xlpm.rowNo,_xlpm.colNo), IF(ISNUMBER(_xlpm.val),_xlpm.val*$H23,"")) | N23: =_xlfn.LET( _xlpm.rowNo, MATCH($C23&"|"& ($F23+N$4),Raw_Fund!$A:$A,0), _xlpm.colNo, MATCH(N$3,Raw_Fund!$E$1:$AZ$1,0), _xlpm.val, INDEX(Raw_Fund!$E:$AZ,_xlpm.rowNo,_xlpm.colNo), IF(ISNUMBER(_xlpm.val),_xlpm.val*$H23,"")) | O23: =_xlfn.LET( _xlpm.rowNo, MATCH($C23&"|"& ($F23+O$4),Raw_Fund!$A:$A,0), _xlpm.colNo, MATCH(O$3,Raw_Fund!$E$1:$AZ$1,0), _xlpm.val, INDEX(Raw_Fund!$E:$AZ,_xlpm.rowNo,_xlpm.colNo), IF(ISNUMBER(_xlpm.val),_xlpm.val*$H23,"")) | P23: =_xlfn.LET( _xlpm.rowNo, MATCH($C23&"|"& ($F23+P$4),Raw_Fund!$A:$A,0), _xlpm.colNo, MATCH(P$3,Raw_Fund!$E$1:$AZ$1,0), _xlpm.val, INDEX(Raw_Fund!$E:$AZ,_xlpm.rowNo,_xlpm.colNo), IF(ISNUMBER(_xlpm.val),_xlpm.val*$H23,"")) | ... Y23: =_xlfn.LET( _xlpm.rowNo, MATCH($C23&"|"& ($F23+Y$4),Raw_Fund!$A:$A,0), _xlpm.colNo, MATCH(Y$3,Raw_Fund!$E$1:$AZ$1,0), _xlpm.val, INDEX(Raw_Fund!$E:$AZ,_xlpm.rowNo,_xlpm.colNo), IF(ISNUMBER(_xlpm.val),_xlpm.val*$H23,"")) | Z23: =IF($E23<>"Include","",_xlfn.XLOOKUP($C23,Raw_Mkt!$A:$A,Raw_Mkt!$B:$B)) -> #N/A
A24: =IF(Universe!A24<>"",Universe!A24,"") -> BGFD | B24: =IF(Universe!B24<>"",Universe!B24,"") -> Baillie Gifford Japan Trust | C24: =IF(Universe!C24<>"",Universe!C24,"") -> GB0000485838 | D24: =IF(Universe!D24<>"",Universe!D24,"") -> Financials | E24: =Universe!G24 -> Exclude | F24: =IF($E24<>"Include","",_xlfn.LET(_xlpm.latest,_xlfn.MAXIFS(Raw_Fund!$C:$C,Raw_Fund!$B:$B,Data!$C24),IF(_xlpm.latest=0,"",_xlpm.latest))) | G24: =IF($F24="","",INDEX(Raw_Fund!$E:$AZ,MATCH($C24&"|"&$F24,Raw_Fund!$A:$A,0),MATCH(G$3,Raw_Fund!$E$1:$AZ$1,0))) | H24: =IF($G24="","",_xlfn.XLOOKUP($G24,FX_Ccy,FX_Rate,"Missing FX")) | I24: =_xlfn.LET( _xlpm.rowNo, MATCH($C24&"|"& ($F24+I$4),Raw_Fund!$A:$A,0), _xlpm.colNo, MATCH(I$3,Raw_Fund!$E$1:$AZ$1,0), _xlpm.val, INDEX(Raw_Fund!$E:$AZ,_xlpm.rowNo,_xlpm.colNo), IF(ISNUMBER(_xlpm.val),_xlpm.val*$H24,"")) | J24: =_xlfn.LET( _xlpm.rowNo, MATCH($C24&"|"& ($F24+J$4),Raw_Fund!$A:$A,0), _xlpm.colNo, MATCH(J$3,Raw_Fund!$E$1:$AZ$1,0), _xlpm.val, INDEX(Raw_Fund!$E:$AZ,_xlpm.rowNo,_xlpm.colNo), IF(ISNUMBER(_xlpm.val),_xlpm.val*$H24,"")) | K24: =_xlfn.LET( _xlpm.rowNo, MATCH($C24&"|"& ($F24+K$4),Raw_Fund!$A:$A,0), _xlpm.colNo, MATCH(K$3,Raw_Fund!$E$1:$AZ$1,0), _xlpm.val, INDEX(Raw_Fund!$E:$AZ,_xlpm.rowNo,_xlpm.colNo), IF(ISNUMBER(_xlpm.val),_xlpm.val*$H24,"")) | L24: =_xlfn.LET( _xlpm.rowNo, MATCH($C24&"|"& ($F24+L$4),Raw_Fund!$A:$A,0), _xlpm.colNo, MATCH(L$3,Raw_Fund!$E$1:$AZ$1,0), _xlpm.val, INDEX(Raw_Fund!$E:$AZ,_xlpm.rowNo,_xlpm.colNo), IF(ISNUMBER(_xlpm.val),_xlpm.val*$H24,"")) | M24: =_xlfn.LET( _xlpm.rowNo, MATCH($C24&"|"& ($F24+M$4),Raw_Fund!$A:$A,0), _xlpm.colNo, MATCH(M$3,Raw_Fund!$E$1:$AZ$1,0), _xlpm.val, INDEX(Raw_Fund!$E:$AZ,_xlpm.rowNo,_xlpm.colNo), IF(ISNUMBER(_xlpm.val),_xlpm.val*$H24,"")) | N24: =_xlfn.LET( _xlpm.rowNo, MATCH($C24&"|"& ($F24+N$4),Raw_Fund!$A:$A,0), _xlpm.colNo, MATCH(N$3,Raw_Fund!$E$1:$AZ$1,0), _xlpm.val, INDEX(Raw_Fund!$E:$AZ,_xlpm.rowNo,_xlpm.colNo), IF(ISNUMBER(_xlpm.val),_xlpm.val*$H24,"")) | O24: =_xlfn.LET( _xlpm.rowNo, MATCH($C24&"|"& ($F24+O$4),Raw_Fund!$A:$A,0), _xlpm.colNo, MATCH(O$3,Raw_Fund!$E$1:$AZ$1,0), _xlpm.val, INDEX(Raw_Fund!$E:$AZ,_xlpm.rowNo,_xlpm.colNo), IF(ISNUMBER(_xlpm.val),_xlpm.val*$H24,"")) | P24: =_xlfn.LET( _xlpm.rowNo, MATCH($C24&"|"& ($F24+P$4),Raw_Fund!$A:$A,0), _xlpm.colNo, MATCH(P$3,Raw_Fund!$E$1:$AZ$1,0), _xlpm.val, INDEX(Raw_Fund!$E:$AZ,_xlpm.rowNo,_xlpm.colNo), IF(ISNUMBER(_xlpm.val),_xlpm.val*$H24,"")) | ... Y24: =_xlfn.LET( _xlpm.rowNo, MATCH($C24&"|"& ($F24+Y$4),Raw_Fund!$A:$A,0), _xlpm.colNo, MATCH(Y$3,Raw_Fund!$E$1:$AZ$1,0), _xlpm.val, INDEX(Raw_Fund!$E:$AZ,_xlpm.rowNo,_xlpm.colNo), IF(ISNUMBER(_xlpm.val),_xlpm.val*$H24,"")) | Z24: =IF($E24<>"Include","",_xlfn.XLOOKUP($C24,Raw_Mkt!$A:$A,Raw_Mkt!$B:$B))
A25: =IF(Universe!A25<>"",Universe!A25,"") -> USA | B25: =IF(Universe!B25<>"",Universe!B25,"") -> Baillie Gifford US Growth Trust | C25: =IF(Universe!C25<>"",Universe!C25,"") -> GB00BDFGHW41 | D25: =IF(Universe!D25<>"",Universe!D25,"") -> Financials | E25: =Universe!G25 -> Exclude | F25: =IF($E25<>"Include","",_xlfn.LET(_xlpm.latest,_xlfn.MAXIFS(Raw_Fund!$C:$C,Raw_Fund!$B:$B,Data!$C25),IF(_xlpm.latest=0,"",_xlpm.latest))) | G25: =IF($F25="","",INDEX(Raw_Fund!$E:$AZ,MATCH($C25&"|"&$F25,Raw_Fund!$A:$A,0),MATCH(G$3,Raw_Fund!$E$1:$AZ$1,0))) | H25: =IF($G25="","",_xlfn.XLOOKUP($G25,FX_Ccy,FX_Rate,"Missing FX")) | I25: =_xlfn.LET( _xlpm.rowNo, MATCH($C25&"|"& ($F25+I$4),Raw_Fund!$A:$A,0), _xlpm.colNo, MATCH(I$3,Raw_Fund!$E$1:$AZ$1,0), _xlpm.val, INDEX(Raw_Fund!$E:$AZ,_xlpm.rowNo,_xlpm.colNo), IF(ISNUMBER(_xlpm.val),_xlpm.val*$H25,"")) | J25: =_xlfn.LET( _xlpm.rowNo, MATCH($C25&"|"& ($F25+J$4),Raw_Fund!$A:$A,0), _xlpm.colNo, MATCH(J$3,Raw_Fund!$E$1:$AZ$1,0), _xlpm.val, INDEX(Raw_Fund!$E:$AZ,_xlpm.rowNo,_xlpm.colNo), IF(ISNUMBER(_xlpm.val),_xlpm.val*$H25,"")) | K25: =_xlfn.LET( _xlpm.rowNo, MATCH($C25&"|"& ($F25+K$4),Raw_Fund!$A:$A,0), _xlpm.colNo, MATCH(K$3,Raw_Fund!$E$1:$AZ$1,0), _xlpm.val, INDEX(Raw_Fund!$E:$AZ,_xlpm.rowNo,_xlpm.colNo), IF(ISNUMBER(_xlpm.val),_xlpm.val*$H25,"")) | L25: =_xlfn.LET( _xlpm.rowNo, MATCH($C25&"|"& ($F25+L$4),Raw_Fund!$A:$A,0), _xlpm.colNo, MATCH(L$3,Raw_Fund!$E$1:$AZ$1,0), _xlpm.val, INDEX(Raw_Fund!$E:$AZ,_xlpm.rowNo,_xlpm.colNo), IF(ISNUMBER(_xlpm.val),_xlpm.val*$H25,"")) | M25: =_xlfn.LET( _xlpm.rowNo, MATCH($C25&"|"& ($F25+M$4),Raw_Fund!$A:$A,0), _xlpm.colNo, MATCH(M$3,Raw_Fund!$E$1:$AZ$1,0), _xlpm.val, INDEX(Raw_Fund!$E:$AZ,_xlpm.rowNo,_xlpm.colNo), IF(ISNUMBER(_xlpm.val),_xlpm.val*$H25,"")) | N25: =_xlfn.LET( _xlpm.rowNo, MATCH($C25&"|"& ($F25+N$4),Raw_Fund!$A:$A,0), _xlpm.colNo, MATCH(N$3,Raw_Fund!$E$1:$AZ$1,0), _xlpm.val, INDEX(Raw_Fund!$E:$AZ,_xlpm.rowNo,_xlpm.colNo), IF(ISNUMBER(_xlpm.val),_xlpm.val*$H25,"")) | O25: =_xlfn.LET( _xlpm.rowNo, MATCH($C25&"|"& ($F25+O$4),Raw_Fund!$A:$A,0), _xlpm.colNo, MATCH(O$3,Raw_Fund!$E$1:$AZ$1,0), _xlpm.val, INDEX(Raw_Fund!$E:$AZ,_xlpm.rowNo,_xlpm.colNo), IF(ISNUMBER(_xlpm.val),_xlpm.val*$H25,"")) | P25: =_xlfn.LET( _xlpm.rowNo, MATCH($C25&"|"& ($F25+P$4),Raw_Fund!$A:$A,0), _xlpm.colNo, MATCH(P$3,Raw_Fund!$E$1:$AZ$1,0), _xlpm.val, INDEX(Raw_Fund!$E:$AZ,_xlpm.rowNo,_xlpm.colNo), IF(ISNUMBER(_xlpm.val),_xlpm.val*$H25,"")) | ... Y25: =_xlfn.LET( _xlpm.rowNo, MATCH($C25&"|"& ($F25+Y$4),Raw_Fund!$A:$A,0), _xlpm.colNo, MATCH(Y$3,Raw_Fund!$E$1:$AZ$1,0), _xlpm.val, INDEX(Raw_Fund!$E:$AZ,_xlpm.rowNo,_xlpm.colNo), IF(ISNUMBER(_xlpm.val),_xlpm.val*$H25,"")) | Z25: =IF($E25<>"Include","",_xlfn.XLOOKUP($C25,Raw_Mkt!$A:$A,Raw_Mkt!$B:$B))
A26: =IF(Universe!A26<>"",Universe!A26,"") -> BCG | B26: =IF(Universe!B26<>"",Universe!B26,"") -> Baltic Classifieds | C26: =IF(Universe!C26<>"",Universe!C26,"") -> GB00BN44P254 | D26: =IF(Universe!D26<>"",Universe!D26,"") -> Consumer Discretionary | E26: =Universe!G26 -> Include | F26: =IF($E26<>"Include","",_xlfn.LET(_xlpm.latest,_xlfn.MAXIFS(Raw_Fund!$C:$C,Raw_Fund!$B:$B,Data!$C26),IF(_xlpm.latest=0,"",_xlpm.latest))) | G26: =IF($F26="","",INDEX(Raw_Fund!$E:$AZ,MATCH($C26&"|"&$F26,Raw_Fund!$A:$A,0),MATCH(G$3,Raw_Fund!$E$1:$AZ$1,0))) | H26: =IF($G26="","",_xlfn.XLOOKUP($G26,FX_Ccy,FX_Rate,"Missing FX")) | I26: =_xlfn.LET( _xlpm.rowNo, MATCH($C26&"|"& ($F26+I$4),Raw_Fund!$A:$A,0), _xlpm.colNo, MATCH(I$3,Raw_Fund!$E$1:$AZ$1,0), _xlpm.val, INDEX(Raw_Fund!$E:$AZ,_xlpm.rowNo,_xlpm.colNo), IF(ISNUMBER(_xlpm.val),_xlpm.val*$H26,"")) | J26: =_xlfn.LET( _xlpm.rowNo, MATCH($C26&"|"& ($F26+J$4),Raw_Fund!$A:$A,0), _xlpm.colNo, MATCH(J$3,Raw_Fund!$E$1:$AZ$1,0), _xlpm.val, INDEX(Raw_Fund!$E:$AZ,_xlpm.rowNo,_xlpm.colNo), IF(ISNUMBER(_xlpm.val),_xlpm.val*$H26,"")) | K26: =_xlfn.LET( _xlpm.rowNo, MATCH($C26&"|"& ($F26+K$4),Raw_Fund!$A:$A,0), _xlpm.colNo, MATCH(K$3,Raw_Fund!$E$1:$AZ$1,0), _xlpm.val, INDEX(Raw_Fund!$E:$AZ,_xlpm.rowNo,_xlpm.colNo), IF(ISNUMBER(_xlpm.val),_xlpm.val*$H26,"")) | L26: =_xlfn.LET( _xlpm.rowNo, MATCH($C26&"|"& ($F26+L$4),Raw_Fund!$A:$A,0), _xlpm.colNo, MATCH(L$3,Raw_Fund!$E$1:$AZ$1,0), _xlpm.val, INDEX(Raw_Fund!$E:$AZ,_xlpm.rowNo,_xlpm.colNo), IF(ISNUMBER(_xlpm.val),_xlpm.val*$H26,"")) | M26: =_xlfn.LET( _xlpm.rowNo, MATCH($C26&"|"& ($F26+M$4),Raw_Fund!$A:$A,0), _xlpm.colNo, MATCH(M$3,Raw_Fund!$E$1:$AZ$1,0), _xlpm.val, INDEX(Raw_Fund!$E:$AZ,_xlpm.rowNo,_xlpm.colNo), IF(ISNUMBER(_xlpm.val),_xlpm.val*$H26,"")) | N26: =_xlfn.LET( _xlpm.rowNo, MATCH($C26&"|"& ($F26+N$4),Raw_Fund!$A:$A,0), _xlpm.colNo, MATCH(N$3,Raw_Fund!$E$1:$AZ$1,0), _xlpm.val, INDEX(Raw_Fund!$E:$AZ,_xlpm.rowNo,_xlpm.colNo), IF(ISNUMBER(_xlpm.val),_xlpm.val*$H26,"")) | O26: =_xlfn.LET( _xlpm.rowNo, MATCH($C26&"|"& ($F26+O$4),Raw_Fund!$A:$A,0), _xlpm.colNo, MATCH(O$3,Raw_Fund!$E$1:$AZ$1,0), _xlpm.val, INDEX(Raw_Fund!$E:$AZ,_xlpm.rowNo,_xlpm.colNo), IF(ISNUMBER(_xlpm.val),_xlpm.val*$H26,"")) | P26: =_xlfn.LET( _xlpm.rowNo, MATCH($C26&"|"& ($F26+P$4),Raw_Fund!$A:$A,0), _xlpm.colNo, MATCH(P$3,Raw_Fund!$E$1:$AZ$1,0), _xlpm.val, INDEX(Raw_Fund!$E:$AZ,_xlpm.rowNo,_xlpm.colNo), IF(ISNUMBER(_xlpm.val),_xlpm.val*$H26,"")) | ... Y26: =_xlfn.LET( _xlpm.rowNo, MATCH($C26&"|"& ($F26+Y$4),Raw_Fund!$A:$A,0), _xlpm.colNo, MATCH(Y$3,Raw_Fund!$E$1:$AZ$1,0), _xlpm.val, INDEX(Raw_Fund!$E:$AZ,_xlpm.rowNo,_xlpm.colNo), IF(ISNUMBER(_xlpm.val),_xlpm.val*$H26,"")) | Z26: =IF($E26<>"Include","",_xlfn.XLOOKUP($C26,Raw_Mkt!$A:$A,Raw_Mkt!$B:$B)) -> #N/A
A27: =IF(Universe!A27<>"",Universe!A27,"") -> BNKR | B27: =IF(Universe!B27<>"",Universe!B27,"") -> Bankers Investment Trust | C27: =IF(Universe!C27<>"",Universe!C27,"") -> GB00BN4NDR39 | D27: =IF(Universe!D27<>"",Universe!D27,"") -> Financials | E27: =Universe!G27 -> Exclude | F27: =IF($E27<>"Include","",_xlfn.LET(_xlpm.latest,_xlfn.MAXIFS(Raw_Fund!$C:$C,Raw_Fund!$B:$B,Data!$C27),IF(_xlpm.latest=0,"",_xlpm.latest))) | G27: =IF($F27="","",INDEX(Raw_Fund!$E:$AZ,MATCH($C27&"|"&$F27,Raw_Fund!$A:$A,0),MATCH(G$3,Raw_Fund!$E$1:$AZ$1,0))) | H27: =IF($G27="","",_xlfn.XLOOKUP($G27,FX_Ccy,FX_Rate,"Missing FX")) | I27: =_xlfn.LET( _xlpm.rowNo, MATCH($C27&"|"& ($F27+I$4),Raw_Fund!$A:$A,0), _xlpm.colNo, MATCH(I$3,Raw_Fund!$E$1:$AZ$1,0), _xlpm.val, INDEX(Raw_Fund!$E:$AZ,_xlpm.rowNo,_xlpm.colNo), IF(ISNUMBER(_xlpm.val),_xlpm.val*$H27,"")) | J27: =_xlfn.LET( _xlpm.rowNo, MATCH($C27&"|"& ($F27+J$4),Raw_Fund!$A:$A,0), _xlpm.colNo, MATCH(J$3,Raw_Fund!$E$1:$AZ$1,0), _xlpm.val, INDEX(Raw_Fund!$E:$AZ,_xlpm.rowNo,_xlpm.colNo), IF(ISNUMBER(_xlpm.val),_xlpm.val*$H27,"")) | K27: =_xlfn.LET( _xlpm.rowNo, MATCH($C27&"|"& ($F27+K$4),Raw_Fund!$A:$A,0), _xlpm.colNo, MATCH(K$3,Raw_Fund!$E$1:$AZ$1,0), _xlpm.val, INDEX(Raw_Fund!$E:$AZ,_xlpm.rowNo,_xlpm.colNo), IF(ISNUMBER(_xlpm.val),_xlpm.val*$H27,"")) | L27: =_xlfn.LET( _xlpm.rowNo, MATCH($C27&"|"& ($F27+L$4),Raw_Fund!$A:$A,0), _xlpm.colNo, MATCH(L$3,Raw_Fund!$E$1:$AZ$1,0), _xlpm.val, INDEX(Raw_Fund!$E:$AZ,_xlpm.rowNo,_xlpm.colNo), IF(ISNUMBER(_xlpm.val),_xlpm.val*$H27,"")) | M27: =_xlfn.LET( _xlpm.rowNo, MATCH($C27&"|"& ($F27+M$4),Raw_Fund!$A:$A,0), _xlpm.colNo, MATCH(M$3,Raw_Fund!$E$1:$AZ$1,0), _xlpm.val, INDEX(Raw_Fund!$E:$AZ,_xlpm.rowNo,_xlpm.colNo), IF(ISNUMBER(_xlpm.val),_xlpm.val*$H27,"")) | N27: =_xlfn.LET( _xlpm.rowNo, MATCH($C27&"|"& ($F27+N$4),Raw_Fund!$A:$A,0), _xlpm.colNo, MATCH(N$3,Raw_Fund!$E$1:$AZ$1,0), _xlpm.val, INDEX(Raw_Fund!$E:$AZ,_xlpm.rowNo,_xlpm.colNo), IF(ISNUMBER(_xlpm.val),_xlpm.val*$H27,"")) | O27: =_xlfn.LET( _xlpm.rowNo, MATCH($C27&"|"& ($F27+O$4),Raw_Fund!$A:$A,0), _xlpm.colNo, MATCH(O$3,Raw_Fund!$E$1:$AZ$1,0), _xlpm.val, INDEX(Raw_Fund!$E:$AZ,_xlpm.rowNo,_xlpm.colNo), IF(ISNUMBER(_xlpm.val),_xlpm.val*$H27,"")) | P27: =_xlfn.LET( _xlpm.rowNo, MATCH($C27&"|"& ($F27+P$4),Raw_Fund!$A:$A,0), _xlpm.colNo, MATCH(P$3,Raw_Fund!$E$1:$AZ$1,0), _xlpm.val, INDEX(Raw_Fund!$E:$AZ,_xlpm.rowNo,_xlpm.colNo), IF(ISNUMBER(_xlpm.val),_xlpm.val*$H27,"")) | ... Y27: =_xlfn.LET( _xlpm.rowNo, MATCH($C27&"|"& ($F27+Y$4),Raw_Fund!$A:$A,0), _xlpm.colNo, MATCH(Y$3,Raw_Fund!$E$1:$AZ$1,0), _xlpm.val, INDEX(Raw_Fund!$E:$AZ,_xlpm.rowNo,_xlpm.colNo), IF(ISNUMBER(_xlpm.val),_xlpm.val*$H27,"")) | Z27: =IF($E27<>"Include","",_xlfn.XLOOKUP($C27,Raw_Mkt!$A:$A,Raw_Mkt!$B:$B))
A28: =IF(Universe!A28<>"",Universe!A28,"") -> BAG | B28: =IF(Universe!B28<>"",Universe!B28,"") -> A.G. Barr | C28: =IF(Universe!C28<>"",Universe!C28,"") -> GB00B6XZKY75 | D28: =IF(Universe!D28<>"",Universe!D28,"") -> Consumer Staples | E28: =Universe!G28 -> Include | F28: =IF($E28<>"Include","",_xlfn.LET(_xlpm.latest,_xlfn.MAXIFS(Raw_Fund!$C:$C,Raw_Fund!$B:$B,Data!$C28),IF(_xlpm.latest=0,"",_xlpm.latest))) | G28: =IF($F28="","",INDEX(Raw_Fund!$E:$AZ,MATCH($C28&"|"&$F28,Raw_Fund!$A:$A,0),MATCH(G$3,Raw_Fund!$E$1:$AZ$1,0))) | H28: =IF($G28="","",_xlfn.XLOOKUP($G28,FX_Ccy,FX_Rate,"Missing FX")) | I28: =_xlfn.LET( _xlpm.rowNo, MATCH($C28&"|"& ($F28+I$4),Raw_Fund!$A:$A,0), _xlpm.colNo, MATCH(I$3,Raw_Fund!$E$1:$AZ$1,0), _xlpm.val, INDEX(Raw_Fund!$E:$AZ,_xlpm.rowNo,_xlpm.colNo), IF(ISNUMBER(_xlpm.val),_xlpm.val*$H28,"")) | J28: =_xlfn.LET( _xlpm.rowNo, MATCH($C28&"|"& ($F28+J$4),Raw_Fund!$A:$A,0), _xlpm.colNo, MATCH(J$3,Raw_Fund!$E$1:$AZ$1,0), _xlpm.val, INDEX(Raw_Fund!$E:$AZ,_xlpm.rowNo,_xlpm.colNo), IF(ISNUMBER(_xlpm.val),_xlpm.val*$H28,"")) | K28: =_xlfn.LET( _xlpm.rowNo, MATCH($C28&"|"& ($F28+K$4),Raw_Fund!$A:$A,0), _xlpm.colNo, MATCH(K$3,Raw_Fund!$E$1:$AZ$1,0), _xlpm.val, INDEX(Raw_Fund!$E:$AZ,_xlpm.rowNo,_xlpm.colNo), IF(ISNUMBER(_xlpm.val),_xlpm.val*$H28,"")) | L28: =_xlfn.LET( _xlpm.rowNo, MATCH($C28&"|"& ($F28+L$4),Raw_Fund!$A:$A,0), _xlpm.colNo, MATCH(L$3,Raw_Fund!$E$1:$AZ$1,0), _xlpm.val, INDEX(Raw_Fund!$E:$AZ,_xlpm.rowNo,_xlpm.colNo), IF(ISNUMBER(_xlpm.val),_xlpm.val*$H28,"")) | M28: =_xlfn.LET( _xlpm.rowNo, MATCH($C28&"|"& ($F28+M$4),Raw_Fund!$A:$A,0), _xlpm.colNo, MATCH(M$3,Raw_Fund!$E$1:$AZ$1,0), _xlpm.val, INDEX(Raw_Fund!$E:$AZ,_xlpm.rowNo,_xlpm.colNo), IF(ISNUMBER(_xlpm.val),_xlpm.val*$H28,"")) | N28: =_xlfn.LET( _xlpm.rowNo, MATCH($C28&"|"& ($F28+N$4),Raw_Fund!$A:$A,0), _xlpm.colNo, MATCH(N$3,Raw_Fund!$E$1:$AZ$1,0), _xlpm.val, INDEX(Raw_Fund!$E:$AZ,_xlpm.rowNo,_xlpm.colNo), IF(ISNUMBER(_xlpm.val),_xlpm.val*$H28,"")) | O28: =_xlfn.LET( _xlpm.rowNo, MATCH($C28&"|"& ($F28+O$4),Raw_Fund!$A:$A,0), _xlpm.colNo, MATCH(O$3,Raw_Fund!$E$1:$AZ$1,0), _xlpm.val, INDEX(Raw_Fund!$E:$AZ,_xlpm.rowNo,_xlpm.colNo), IF(ISNUMBER(_xlpm.val),_xlpm.val*$H28,"")) | P28: =_xlfn.LET( _xlpm.rowNo, MATCH($C28&"|"& ($F28+P$4),Raw_Fund!$A:$A,0), _xlpm.colNo, MATCH(P$3,Raw_Fund!$E$1:$AZ$1,0), _xlpm.val, INDEX(Raw_Fund!$E:$AZ,_xlpm.rowNo,_xlpm.colNo), IF(ISNUMBER(_xlpm.val),_xlpm.val*$H28,"")) | ... Y28: =_xlfn.LET( _xlpm.rowNo, MATCH($C28&"|"& ($F28+Y$4),Raw_Fund!$A:$A,0), _xlpm.colNo, MATCH(Y$3,Raw_Fund!$E$1:$AZ$1,0), _xlpm.val, INDEX(Raw_Fund!$E:$AZ,_xlpm.rowNo,_xlpm.colNo), IF(ISNUMBER(_xlpm.val),_xlpm.val*$H28,"")) | Z28: =IF($E28<>"Include","",_xlfn.XLOOKUP($C28,Raw_Mkt!$A:$A,Raw_Mkt!$B:$B)) -> #N/A
... A305: =IF(Universe!A305<>"",Universe!A305,"") | B305: =IF(Universe!B305<>"",Universe!B305,"") | C305: =IF(Universe!C305<>"",Universe!C305,"") | D305: =IF(Universe!D305<>"",Universe!D305,"") | E305: =Universe!G305 | F305: =IF($E305<>"Include","",_xlfn.LET(_xlpm.latest,_xlfn.MAXIFS(Raw_Fund!$C:$C,Raw_Fund!$B:$B,Data!$C305),IF(_xlpm.latest=0,"",_xlpm.latest))) | G305: =IF($F305="","",INDEX(Raw_Fund!$E:$AZ,MATCH($C305&"|"&$F305,Raw_Fund!$A:$A,0),MATCH(G$3,Raw_Fund!$E$1:$AZ$1,0))) | H305: =IF($G305="","",_xlfn.XLOOKUP($G305,FX_Ccy,FX_Rate,"Missing FX")) | I305: =_xlfn.LET( _xlpm.rowNo, MATCH($C305&"|"& ($F305+I$4),Raw_Fund!$A:$A,0), _xlpm.colNo, MATCH(I$3,Raw_Fund!$E$1:$AZ$1,0), _xlpm.val, INDEX(Raw_Fund!$E:$AZ,_xlpm.rowNo,_xlpm.colNo), IF(ISNUMBER(_xlpm.val),_xlpm.val*$H305,"")) | J305: =_xlfn.LET( _xlpm.rowNo, MATCH($C305&"|"& ($F305+J$4),Raw_Fund!$A:$A,0), _xlpm.colNo, MATCH(J$3,Raw_Fund!$E$1:$AZ$1,0), _xlpm.val, INDEX(Raw_Fund!$E:$AZ,_xlpm.rowNo,_xlpm.colNo), IF(ISNUMBER(_xlpm.val),_xlpm.val*$H305,"")) | K305: =_xlfn.LET( _xlpm.rowNo, MATCH($C305&"|"& ($F305+K$4),Raw_Fund!$A:$A,0), _xlpm.colNo, MATCH(K$3,Raw_Fund!$E$1:$AZ$1,0), _xlpm.val, INDEX(Raw_Fund!$E:$AZ,_xlpm.rowNo,_xlpm.colNo), IF(ISNUMBER(_xlpm.val),_xlpm.val*$H305,"")) | L305: =_xlfn.LET( _xlpm.rowNo, MATCH($C305&"|"& ($F305+L$4),Raw_Fund!$A:$A,0), _xlpm.colNo, MATCH(L$3,Raw_Fund!$E$1:$AZ$1,0), _xlpm.val, INDEX(Raw_Fund!$E:$AZ,_xlpm.rowNo,_xlpm.colNo), IF(ISNUMBER(_xlpm.val),_xlpm.val*$H305,"")) | M305: =_xlfn.LET( _xlpm.rowNo, MATCH($C305&"|"& ($F305+M$4),Raw_Fund!$A:$A,0), _xlpm.colNo, MATCH(M$3,Raw_Fund!$E$1:$AZ$1,0), _xlpm.val, INDEX(Raw_Fund!$E:$AZ,_xlpm.rowNo,_xlpm.colNo), IF(ISNUMBER(_xlpm.val),_xlpm.val*$H305,"")) | N305: =_xlfn.LET( _xlpm.rowNo, MATCH($C305&"|"& ($F305+N$4),Raw_Fund!$A:$A,0), _xlpm.colNo, MATCH(N$3,Raw_Fund!$E$1:$AZ$1,0), _xlpm.val, INDEX(Raw_Fund!$E:$AZ,_xlpm.rowNo,_xlpm.colNo), IF(ISNUMBER(_xlpm.val),_xlpm.val*$H305,"")) | O305: =_xlfn.LET( _xlpm.rowNo, MATCH($C305&"|"& ($F305+O$4),Raw_Fund!$A:$A,0), _xlpm.colNo, MATCH(O$3,Raw_Fund!$E$1:$AZ$1,0), _xlpm.val, INDEX(Raw_Fund!$E:$AZ,_xlpm.rowNo,_xlpm.colNo), IF(ISNUMBER(_xlpm.val),_xlpm.val*$H305,"")) | P305: =_xlfn.LET( _xlpm.rowNo, MATCH($C305&"|"& ($F305+P$4),Raw_Fund!$A:$A,0), _xlpm.colNo, MATCH(P$3,Raw_Fund!$E$1:$AZ$1,0), _xlpm.val, INDEX(Raw_Fund!$E:$AZ,_xlpm.rowNo,_xlpm.colNo), IF(ISNUMBER(_xlpm.val),_xlpm.val*$H305,"")) | ... Y305: =_xlfn.LET( _xlpm.rowNo, MATCH($C305&"|"& ($F305+Y$4),Raw_Fund!$A:$A,0), _xlpm.colNo, MATCH(Y$3,Raw_Fund!$E$1:$AZ$1,0), _xlpm.val, INDEX(Raw_Fund!$E:$AZ,_xlpm.rowNo,_xlpm.colNo), IF(ISNUMBER(_xlpm.val),_xlpm.val*$H305,"")) | Z305: =IF($E305<>"Include","",_xlfn.XLOOKUP($C305,Raw_Mkt!$A:$A,Raw_Mkt!$B:$B))

Sheet Metrics
E3: LT debt + ST debt - Cash | F3: Mkt Cap + Net debt + minority interest | G3: CFO FY0 - Capex FY0 | O3: =Inputs!C4 -> 0.3 | P3: =Inputs!C5 -> 0.25 | Q3: =Inputs!C6 -> 0.2 | R3: =Inputs!C7 -> 0.15 | S3: =Inputs!C8 -> 0.1
O4: =IF(Inputs!D4="Lower",1,0) -> 1 | P4: =IF(Inputs!D5="Lower",1,0) -> 0 | Q4: =IF(Inputs!D6="Lower",1,0) -> 0 | R4: =IF(Inputs!D7="Lower",1,0) -> 1 | S4: =IF(Inputs!D8="Lower",1,0) -> 0
A5: Ticker | B5: Company | C5: Sector | D5: Status | E5: Net Debt £m | F5: EV £m | G5: FCF £m | H5: FCF 3yr £m | I5: Net Income 3yr £m | J5: EV/EBIT | K5: FCF Yield | L5: Cash conversion | M5: Net debt/EBITDA | N5: Revenue CAGR | O5: Rank EV/EBIT | P5: Rank FCF yield | Q5: Rank Cash Conversion | R5: Rank Leverage | S5: Rank Growth | T5: Composite Score | U5: Final Rank
A6: =Data!A6 -> 3IN | B6: =Data!B6 -> 3i Infrastructure | C6: =Data!D6 -> Financials | D6: =Data!E6 -> Exclude | E6: =IF($D6<>"Include","",SUM(Data!V6:W6)-SUM(Data!X6)) | F6: =IF($D6<>"Include","",SUM(Data!Z6,Data!Y6,Metrics!E6)) | G6: =IF($D6<>"Include","",IFERROR(Data!P6-Data!S6,"")) | H6: =IF($D6<>"Include","",IFERROR(SUM(Data!P6:R6)-SUM(Data!S6:U6),"")) | I6: =IF($D6<>"Include","",SUM(Data!M6:O6)) | J6: =IF($D6<>"Include","",IFERROR(IF(OR(Data!K6<=0,F6<=0),"n/m",($F6/Data!K6)),"")) | K6: =IF($D6<>"Include","",IFERROR(G6/Data!Z6,"")) | L6: =IF($D6<>"Include","",IFERROR(IF(I6<=0,"n/m",H6/I6),"")) | M6: =IF($D6<>"Include","",IFERROR(IF(Data!L6<=0,"n,m",E6/Data!L6),"")) | N6: =IF($D6<>"Include","",IFERROR(IF(OR(Data!I6<=0,Data!J6<=0),"n/m",(Data!I6/Data!J6)^(1/3)-1),"")) | O6: =IF($D6<>"Include","",IF(ISNUMBER(J6),_xlfn.RANK.EQ(J6,J$6:J$305,O$4),N_Co)) | P6: =IF($D6<>"Include","",IF(ISNUMBER(K6),_xlfn.RANK.EQ(K6,K$6:K$305,P$4),N_Co)) | Q6: =IF($D6<>"Include","",IF(ISNUMBER(L6),_xlfn.RANK.EQ(L6,L$6:L$305,Q$4),N_Co)) | R6: =IF($D6<>"Include","",IF(ISNUMBER(M6),_xlfn.RANK.EQ(M6,M$6:M$305,R$4),N_Co)) | S6: =IF($D6<>"Include","",IF(ISNUMBER(N6),_xlfn.RANK.EQ(N6,N$6:N$305,S$4),N_Co)) | T6: =IF($D6<>"Include","",ROUND(SUMPRODUCT(O6:S6,$O$3:$S$3),6)) | U6: =IF($D6<>"Include","",_xlfn.RANK.EQ(T6,T$6:T$305,1)+COUNTIFS(T$6:T6,T6)-1)
A7: =Data!A7 -> FOUR | B7: =Data!B7 -> 4imprint | C7: =Data!D7 -> Consumer Discretionary | D7: =Data!E7 -> Include | E7: =IF($D7<>"Include","",SUM(Data!V7:W7)-SUM(Data!X7)) -> 0 | F7: =IF($D7<>"Include","",SUM(Data!Z7,Data!Y7,Metrics!E7)) -> #N/A | G7: =IF($D7<>"Include","",IFERROR(Data!P7-Data!S7,"")) | H7: =IF($D7<>"Include","",IFERROR(SUM(Data!P7:R7)-SUM(Data!S7:U7),"")) -> 0 | I7: =IF($D7<>"Include","",SUM(Data!M7:O7)) -> 0 | J7: =IF($D7<>"Include","",IFERROR(IF(OR(Data!K7<=0,F7<=0),"n/m",($F7/Data!K7)),"")) | K7: =IF($D7<>"Include","",IFERROR(G7/Data!Z7,"")) | L7: =IF($D7<>"Include","",IFERROR(IF(I7<=0,"n/m",H7/I7),"")) -> n/m | M7: =IF($D7<>"Include","",IFERROR(IF(Data!L7<=0,"n,m",E7/Data!L7),"")) | N7: =IF($D7<>"Include","",IFERROR(IF(OR(Data!I7<=0,Data!J7<=0),"n/m",(Data!I7/Data!J7)^(1/3)-1),"")) | O7: =IF($D7<>"Include","",IF(ISNUMBER(J7),_xlfn.RANK.EQ(J7,J$6:J$305,O$4),N_Co)) -> 119 | P7: =IF($D7<>"Include","",IF(ISNUMBER(K7),_xlfn.RANK.EQ(K7,K$6:K$305,P$4),N_Co)) -> 119 | Q7: =IF($D7<>"Include","",IF(ISNUMBER(L7),_xlfn.RANK.EQ(L7,L$6:L$305,Q$4),N_Co)) -> 119 | R7: =IF($D7<>"Include","",IF(ISNUMBER(M7),_xlfn.RANK.EQ(M7,M$6:M$305,R$4),N_Co)) -> 119 | S7: =IF($D7<>"Include","",IF(ISNUMBER(N7),_xlfn.RANK.EQ(N7,N$6:N$305,S$4),N_Co)) -> 119 | T7: =IF($D7<>"Include","",ROUND(SUMPRODUCT(O7:S7,$O$3:$S$3),6)) -> 119 | U7: =IF($D7<>"Include","",_xlfn.RANK.EQ(T7,T$6:T$305,1)+COUNTIFS(T$6:T7,T7)-1) -> 1
A8: =Data!A8 -> AAS | B8: =Data!B8 -> Aberdeen Asia Focus | C8: =Data!D8 -> Financials | D8: =Data!E8 -> Exclude | E8: =IF($D8<>"Include","",SUM(Data!V8:W8)-SUM(Data!X8)) | F8: =IF($D8<>"Include","",SUM(Data!Z8,Data!Y8,Metrics!E8)) | G8: =IF($D8<>"Include","",IFERROR(Data!P8-Data!S8,"")) | H8: =IF($D8<>"Include","",IFERROR(SUM(Data!P8:R8)-SUM(Data!S8:U8),"")) | I8: =IF($D8<>"Include","",SUM(Data!M8:O8)) | J8: =IF($D8<>"Include","",IFERROR(IF(OR(Data!K8<=0,F8<=0),"n/m",($F8/Data!K8)),"")) | K8: =IF($D8<>"Include","",IFERROR(G8/Data!Z8,"")) | L8: =IF($D8<>"Include","",IFERROR(IF(I8<=0,"n/m",H8/I8),"")) | M8: =IF($D8<>"Include","",IFERROR(IF(Data!L8<=0,"n,m",E8/Data!L8),"")) | N8: =IF($D8<>"Include","",IFERROR(IF(OR(Data!I8<=0,Data!J8<=0),"n/m",(Data!I8/Data!J8)^(1/3)-1),"")) | O8: =IF($D8<>"Include","",IF(ISNUMBER(J8),_xlfn.RANK.EQ(J8,J$6:J$305,O$4),N_Co)) | P8: =IF($D8<>"Include","",IF(ISNUMBER(K8),_xlfn.RANK.EQ(K8,K$6:K$305,P$4),N_Co)) | Q8: =IF($D8<>"Include","",IF(ISNUMBER(L8),_xlfn.RANK.EQ(L8,L$6:L$305,Q$4),N_Co)) | R8: =IF($D8<>"Include","",IF(ISNUMBER(M8),_xlfn.RANK.EQ(M8,M$6:M$305,R$4),N_Co)) | S8: =IF($D8<>"Include","",IF(ISNUMBER(N8),_xlfn.RANK.EQ(N8,N$6:N$305,S$4),N_Co)) | T8: =IF($D8<>"Include","",ROUND(SUMPRODUCT(O8:S8,$O$3:$S$3),6)) | U8: =IF($D8<>"Include","",_xlfn.RANK.EQ(T8,T$6:T$305,1)+COUNTIFS(T$6:T8,T8)-1)
A9: =Data!A9 -> ASL | B9: =Data!B9 -> Aberforth Smaller Companies Trust | C9: =Data!D9 -> Financials | D9: =Data!E9 -> Exclude | E9: =IF($D9<>"Include","",SUM(Data!V9:W9)-SUM(Data!X9)) | F9: =IF($D9<>"Include","",SUM(Data!Z9,Data!Y9,Metrics!E9)) | G9: =IF($D9<>"Include","",IFERROR(Data!P9-Data!S9,"")) | H9: =IF($D9<>"Include","",IFERROR(SUM(Data!P9:R9)-SUM(Data!S9:U9),"")) | I9: =IF($D9<>"Include","",SUM(Data!M9:O9)) | J9: =IF($D9<>"Include","",IFERROR(IF(OR(Data!K9<=0,F9<=0),"n/m",($F9/Data!K9)),"")) | K9: =IF($D9<>"Include","",IFERROR(G9/Data!Z9,"")) | L9: =IF($D9<>"Include","",IFERROR(IF(I9<=0,"n/m",H9/I9),"")) | M9: =IF($D9<>"Include","",IFERROR(IF(Data!L9<=0,"n,m",E9/Data!L9),"")) | N9: =IF($D9<>"Include","",IFERROR(IF(OR(Data!I9<=0,Data!J9<=0),"n/m",(Data!I9/Data!J9)^(1/3)-1),"")) | O9: =IF($D9<>"Include","",IF(ISNUMBER(J9),_xlfn.RANK.EQ(J9,J$6:J$305,O$4),N_Co)) | P9: =IF($D9<>"Include","",IF(ISNUMBER(K9),_xlfn.RANK.EQ(K9,K$6:K$305,P$4),N_Co)) | Q9: =IF($D9<>"Include","",IF(ISNUMBER(L9),_xlfn.RANK.EQ(L9,L$6:L$305,Q$4),N_Co)) | R9: =IF($D9<>"Include","",IF(ISNUMBER(M9),_xlfn.RANK.EQ(M9,M$6:M$305,R$4),N_Co)) | S9: =IF($D9<>"Include","",IF(ISNUMBER(N9),_xlfn.RANK.EQ(N9,N$6:N$305,S$4),N_Co)) | T9: =IF($D9<>"Include","",ROUND(SUMPRODUCT(O9:S9,$O$3:$S$3),6)) | U9: =IF($D9<>"Include","",_xlfn.RANK.EQ(T9,T$6:T$305,1)+COUNTIFS(T$6:T9,T9)-1)
A10: =Data!A10 -> AEP | B10: =Data!B10 -> AEP Plantations | C10: =Data!D10 -> Consumer Staples | D10: =Data!E10 -> Include | E10: =IF($D10<>"Include","",SUM(Data!V10:W10)-SUM(Data!X10)) -> 0 | F10: =IF($D10<>"Include","",SUM(Data!Z10,Data!Y10,Metrics!E10)) -> #N/A | G10: =IF($D10<>"Include","",IFERROR(Data!P10-Data!S10,"")) | H10: =IF($D10<>"Include","",IFERROR(SUM(Data!P10:R10)-SUM(Data!S10:U10),"")) -> 0 | I10: =IF($D10<>"Include","",SUM(Data!M10:O10)) -> 0 | J10: =IF($D10<>"Include","",IFERROR(IF(OR(Data!K10<=0,F10<=0),"n/m",($F10/Data!K10)),"")) | K10: =IF($D10<>"Include","",IFERROR(G10/Data!Z10,"")) | L10: =IF($D10<>"Include","",IFERROR(IF(I10<=0,"n/m",H10/I10),"")) -> n/m | M10: =IF($D10<>"Include","",IFERROR(IF(Data!L10<=0,"n,m",E10/Data!L10),"")) | N10: =IF($D10<>"Include","",IFERROR(IF(OR(Data!I10<=0,Data!J10<=0),"n/m",(Data!I10/Data!J10)^(1/3)-1),"")) | O10: =IF($D10<>"Include","",IF(ISNUMBER(J10),_xlfn.RANK.EQ(J10,J$6:J$305,O$4),N_Co)) -> 119 | P10: =IF($D10<>"Include","",IF(ISNUMBER(K10),_xlfn.RANK.EQ(K10,K$6:K$305,P$4),N_Co)) -> 119 | Q10: =IF($D10<>"Include","",IF(ISNUMBER(L10),_xlfn.RANK.EQ(L10,L$6:L$305,Q$4),N_Co)) -> 119 | R10: =IF($D10<>"Include","",IF(ISNUMBER(M10),_xlfn.RANK.EQ(M10,M$6:M$305,R$4),N_Co)) -> 119 | S10: =IF($D10<>"Include","",IF(ISNUMBER(N10),_xlfn.RANK.EQ(N10,N$6:N$305,S$4),N_Co)) -> 119 | T10: =IF($D10<>"Include","",ROUND(SUMPRODUCT(O10:S10,$O$3:$S$3),6)) -> 119 | U10: =IF($D10<>"Include","",_xlfn.RANK.EQ(T10,T$6:T$305,1)+COUNTIFS(T$6:T10,T10)-1) -> 2
A11: =Data!A11 -> ALFA | B11: =Data!B11 -> Alfa Financial Software | C11: =Data!D11 -> Technology | D11: =Data!E11 -> Include | E11: =IF($D11<>"Include","",SUM(Data!V11:W11)-SUM(Data!X11)) -> 0 | F11: =IF($D11<>"Include","",SUM(Data!Z11,Data!Y11,Metrics!E11)) -> #N/A | G11: =IF($D11<>"Include","",IFERROR(Data!P11-Data!S11,"")) | H11: =IF($D11<>"Include","",IFERROR(SUM(Data!P11:R11)-SUM(Data!S11:U11),"")) -> 0 | I11: =IF($D11<>"Include","",SUM(Data!M11:O11)) -> 0 | J11: =IF($D11<>"Include","",IFERROR(IF(OR(Data!K11<=0,F11<=0),"n/m",($F11/Data!K11)),"")) | K11: =IF($D11<>"Include","",IFERROR(G11/Data!Z11,"")) | L11: =IF($D11<>"Include","",IFERROR(IF(I11<=0,"n/m",H11/I11),"")) -> n/m | M11: =IF($D11<>"Include","",IFERROR(IF(Data!L11<=0,"n,m",E11/Data!L11),"")) | N11: =IF($D11<>"Include","",IFERROR(IF(OR(Data!I11<=0,Data!J11<=0),"n/m",(Data!I11/Data!J11)^(1/3)-1),"")) | O11: =IF($D11<>"Include","",IF(ISNUMBER(J11),_xlfn.RANK.EQ(J11,J$6:J$305,O$4),N_Co)) -> 119 | P11: =IF($D11<>"Include","",IF(ISNUMBER(K11),_xlfn.RANK.EQ(K11,K$6:K$305,P$4),N_Co)) -> 119 | Q11: =IF($D11<>"Include","",IF(ISNUMBER(L11),_xlfn.RANK.EQ(L11,L$6:L$305,Q$4),N_Co)) -> 119 | R11: =IF($D11<>"Include","",IF(ISNUMBER(M11),_xlfn.RANK.EQ(M11,M$6:M$305,R$4),N_Co)) -> 119 | S11: =IF($D11<>"Include","",IF(ISNUMBER(N11),_xlfn.RANK.EQ(N11,N$6:N$305,S$4),N_Co)) -> 119 | T11: =IF($D11<>"Include","",ROUND(SUMPRODUCT(O11:S11,$O$3:$S$3),6)) -> 119 | U11: =IF($D11<>"Include","",_xlfn.RANK.EQ(T11,T$6:T$305,1)+COUNTIFS(T$6:T11,T11)-1) -> 3
A12: =Data!A12 -> ATT | B12: =Data!B12 -> Allianz Technology Trust | C12: =Data!D12 -> Financials | D12: =Data!E12 -> Exclude | E12: =IF($D12<>"Include","",SUM(Data!V12:W12)-SUM(Data!X12)) | F12: =IF($D12<>"Include","",SUM(Data!Z12,Data!Y12,Metrics!E12)) | G12: =IF($D12<>"Include","",IFERROR(Data!P12-Data!S12,"")) | H12: =IF($D12<>"Include","",IFERROR(SUM(Data!P12:R12)-SUM(Data!S12:U12),"")) | I12: =IF($D12<>"Include","",SUM(Data!M12:O12)) | J12: =IF($D12<>"Include","",IFERROR(IF(OR(Data!K12<=0,F12<=0),"n/m",($F12/Data!K12)),"")) | K12: =IF($D12<>"Include","",IFERROR(G12/Data!Z12,"")) | L12: =IF($D12<>"Include","",IFERROR(IF(I12<=0,"n/m",H12/I12),"")) | M12: =IF($D12<>"Include","",IFERROR(IF(Data!L12<=0,"n,m",E12/Data!L12),"")) | N12: =IF($D12<>"Include","",IFERROR(IF(OR(Data!I12<=0,Data!J12<=0),"n/m",(Data!I12/Data!J12)^(1/3)-1),"")) | O12: =IF($D12<>"Include","",IF(ISNUMBER(J12),_xlfn.RANK.EQ(J12,J$6:J$305,O$4),N_Co)) | P12: =IF($D12<>"Include","",IF(ISNUMBER(K12),_xlfn.RANK.EQ(K12,K$6:K$305,P$4),N_Co)) | Q12: =IF($D12<>"Include","",IF(ISNUMBER(L12),_xlfn.RANK.EQ(L12,L$6:L$305,Q$4),N_Co)) | R12: =IF($D12<>"Include","",IF(ISNUMBER(M12),_xlfn.RANK.EQ(M12,M$6:M$305,R$4),N_Co)) | S12: =IF($D12<>"Include","",IF(ISNUMBER(N12),_xlfn.RANK.EQ(N12,N$6:N$305,S$4),N_Co)) | T12: =IF($D12<>"Include","",ROUND(SUMPRODUCT(O12:S12,$O$3:$S$3),6)) | U12: =IF($D12<>"Include","",_xlfn.RANK.EQ(T12,T$6:T$305,1)+COUNTIFS(T$6:T12,T12)-1)
A13: =Data!A13 -> AMRQ | B13: =Data!B13 -> Amaroq | C13: =Data!D13 -> Basic Materials | D13: =Data!E13 -> Exclude | E13: =IF($D13<>"Include","",SUM(Data!V13:W13)-SUM(Data!X13)) | F13: =IF($D13<>"Include","",SUM(Data!Z13,Data!Y13,Metrics!E13)) | G13: =IF($D13<>"Include","",IFERROR(Data!P13-Data!S13,"")) | H13: =IF($D13<>"Include","",IFERROR(SUM(Data!P13:R13)-SUM(Data!S13:U13),"")) | I13: =IF($D13<>"Include","",SUM(Data!M13:O13)) | J13: =IF($D13<>"Include","",IFERROR(IF(OR(Data!K13<=0,F13<=0),"n/m",($F13/Data!K13)),"")) | K13: =IF($D13<>"Include","",IFERROR(G13/Data!Z13,"")) | L13: =IF($D13<>"Include","",IFERROR(IF(I13<=0,"n/m",H13/I13),"")) | M13: =IF($D13<>"Include","",IFERROR(IF(Data!L13<=0,"n,m",E13/Data!L13),"")) | N13: =IF($D13<>"Include","",IFERROR(IF(OR(Data!I13<=0,Data!J13<=0),"n/m",(Data!I13/Data!J13)^(1/3)-1),"")) | O13: =IF($D13<>"Include","",IF(ISNUMBER(J13),_xlfn.RANK.EQ(J13,J$6:J$305,O$4),N_Co)) | P13: =IF($D13<>"Include","",IF(ISNUMBER(K13),_xlfn.RANK.EQ(K13,K$6:K$305,P$4),N_Co)) | Q13: =IF($D13<>"Include","",IF(ISNUMBER(L13),_xlfn.RANK.EQ(L13,L$6:L$305,Q$4),N_Co)) | R13: =IF($D13<>"Include","",IF(ISNUMBER(M13),_xlfn.RANK.EQ(M13,M$6:M$305,R$4),N_Co)) | S13: =IF($D13<>"Include","",IF(ISNUMBER(N13),_xlfn.RANK.EQ(N13,N$6:N$305,S$4),N_Co)) | T13: =IF($D13<>"Include","",ROUND(SUMPRODUCT(O13:S13,$O$3:$S$3),6)) | U13: =IF($D13<>"Include","",_xlfn.RANK.EQ(T13,T$6:T$305,1)+COUNTIFS(T$6:T13,T13)-1)
A14: =Data!A14 -> AO | B14: =Data!B14 -> AO World | C14: =Data!D14 -> Consumer Discretionary | D14: =Data!E14 -> Include | E14: =IF($D14<>"Include","",SUM(Data!V14:W14)-SUM(Data!X14)) -> 0 | F14: =IF($D14<>"Include","",SUM(Data!Z14,Data!Y14,Metrics!E14)) -> #N/A | G14: =IF($D14<>"Include","",IFERROR(Data!P14-Data!S14,"")) | H14: =IF($D14<>"Include","",IFERROR(SUM(Data!P14:R14)-SUM(Data!S14:U14),"")) -> 0 | I14: =IF($D14<>"Include","",SUM(Data!M14:O14)) -> 0 | J14: =IF($D14<>"Include","",IFERROR(IF(OR(Data!K14<=0,F14<=0),"n/m",($F14/Data!K14)),"")) | K14: =IF($D14<>"Include","",IFERROR(G14/Data!Z14,"")) | L14: =IF($D14<>"Include","",IFERROR(IF(I14<=0,"n/m",H14/I14),"")) -> n/m | M14: =IF($D14<>"Include","",IFERROR(IF(Data!L14<=0,"n,m",E14/Data!L14),"")) | N14: =IF($D14<>"Include","",IFERROR(IF(OR(Data!I14<=0,Data!J14<=0),"n/m",(Data!I14/Data!J14)^(1/3)-1),"")) | O14: =IF($D14<>"Include","",IF(ISNUMBER(J14),_xlfn.RANK.EQ(J14,J$6:J$305,O$4),N_Co)) -> 119 | P14: =IF($D14<>"Include","",IF(ISNUMBER(K14),_xlfn.RANK.EQ(K14,K$6:K$305,P$4),N_Co)) -> 119 | Q14: =IF($D14<>"Include","",IF(ISNUMBER(L14),_xlfn.RANK.EQ(L14,L$6:L$305,Q$4),N_Co)) -> 119 | R14: =IF($D14<>"Include","",IF(ISNUMBER(M14),_xlfn.RANK.EQ(M14,M$6:M$305,R$4),N_Co)) -> 119 | S14: =IF($D14<>"Include","",IF(ISNUMBER(N14),_xlfn.RANK.EQ(N14,N$6:N$305,S$4),N_Co)) -> 119 | T14: =IF($D14<>"Include","",ROUND(SUMPRODUCT(O14:S14,$O$3:$S$3),6)) -> 119 | U14: =IF($D14<>"Include","",_xlfn.RANK.EQ(T14,T$6:T$305,1)+COUNTIFS(T$6:T14,T14)-1) -> 4
A15: =Data!A15 -> APN | B15: =Data!B15 -> Applied Nutrition | C15: =Data!D15 -> Consumer Staples | D15: =Data!E15 -> Include | E15: =IF($D15<>"Include","",SUM(Data!V15:W15)-SUM(Data!X15)) -> 0 | F15: =IF($D15<>"Include","",SUM(Data!Z15,Data!Y15,Metrics!E15)) -> #N/A | G15: =IF($D15<>"Include","",IFERROR(Data!P15-Data!S15,"")) | H15: =IF($D15<>"Include","",IFERROR(SUM(Data!P15:R15)-SUM(Data!S15:U15),"")) -> 0 | I15: =IF($D15<>"Include","",SUM(Data!M15:O15)) -> 0 | J15: =IF($D15<>"Include","",IFERROR(IF(OR(Data!K15<=0,F15<=0),"n/m",($F15/Data!K15)),"")) | K15: =IF($D15<>"Include","",IFERROR(G15/Data!Z15,"")) | L15: =IF($D15<>"Include","",IFERROR(IF(I15<=0,"n/m",H15/I15),"")) -> n/m | M15: =IF($D15<>"Include","",IFERROR(IF(Data!L15<=0,"n,m",E15/Data!L15),"")) | N15: =IF($D15<>"Include","",IFERROR(IF(OR(Data!I15<=0,Data!J15<=0),"n/m",(Data!I15/Data!J15)^(1/3)-1),"")) | O15: =IF($D15<>"Include","",IF(ISNUMBER(J15),_xlfn.RANK.EQ(J15,J$6:J$305,O$4),N_Co)) -> 119 | P15: =IF($D15<>"Include","",IF(ISNUMBER(K15),_xlfn.RANK.EQ(K15,K$6:K$305,P$4),N_Co)) -> 119 | Q15: =IF($D15<>"Include","",IF(ISNUMBER(L15),_xlfn.RANK.EQ(L15,L$6:L$305,Q$4),N_Co)) -> 119 | R15: =IF($D15<>"Include","",IF(ISNUMBER(M15),_xlfn.RANK.EQ(M15,M$6:M$305,R$4),N_Co)) -> 119 | S15: =IF($D15<>"Include","",IF(ISNUMBER(N15),_xlfn.RANK.EQ(N15,N$6:N$305,S$4),N_Co)) -> 119 | T15: =IF($D15<>"Include","",ROUND(SUMPRODUCT(O15:S15,$O$3:$S$3),6)) -> 119 | U15: =IF($D15<>"Include","",_xlfn.RANK.EQ(T15,T$6:T$305,1)+COUNTIFS(T$6:T15,T15)-1) -> 5
A16: =Data!A16 -> ASHM | B16: =Data!B16 -> Ashmore Group | C16: =Data!D16 -> Financials | D16: =Data!E16 -> Exclude | E16: =IF($D16<>"Include","",SUM(Data!V16:W16)-SUM(Data!X16)) | F16: =IF($D16<>"Include","",SUM(Data!Z16,Data!Y16,Metrics!E16)) | G16: =IF($D16<>"Include","",IFERROR(Data!P16-Data!S16,"")) | H16: =IF($D16<>"Include","",IFERROR(SUM(Data!P16:R16)-SUM(Data!S16:U16),"")) | I16: =IF($D16<>"Include","",SUM(Data!M16:O16)) | J16: =IF($D16<>"Include","",IFERROR(IF(OR(Data!K16<=0,F16<=0),"n/m",($F16/Data!K16)),"")) | K16: =IF($D16<>"Include","",IFERROR(G16/Data!Z16,"")) | L16: =IF($D16<>"Include","",IFERROR(IF(I16<=0,"n/m",H16/I16),"")) | M16: =IF($D16<>"Include","",IFERROR(IF(Data!L16<=0,"n,m",E16/Data!L16),"")) | N16: =IF($D16<>"Include","",IFERROR(IF(OR(Data!I16<=0,Data!J16<=0),"n/m",(Data!I16/Data!J16)^(1/3)-1),"")) | O16: =IF($D16<>"Include","",IF(ISNUMBER(J16),_xlfn.RANK.EQ(J16,J$6:J$305,O$4),N_Co)) | P16: =IF($D16<>"Include","",IF(ISNUMBER(K16),_xlfn.RANK.EQ(K16,K$6:K$305,P$4),N_Co)) | Q16: =IF($D16<>"Include","",IF(ISNUMBER(L16),_xlfn.RANK.EQ(L16,L$6:L$305,Q$4),N_Co)) | R16: =IF($D16<>"Include","",IF(ISNUMBER(M16),_xlfn.RANK.EQ(M16,M$6:M$305,R$4),N_Co)) | S16: =IF($D16<>"Include","",IF(ISNUMBER(N16),_xlfn.RANK.EQ(N16,N$6:N$305,S$4),N_Co)) | T16: =IF($D16<>"Include","",ROUND(SUMPRODUCT(O16:S16,$O$3:$S$3),6)) | U16: =IF($D16<>"Include","",_xlfn.RANK.EQ(T16,T$6:T$305,1)+COUNTIFS(T$6:T16,T16)-1)
A17: =Data!A17 -> AIE | B17: =Data!B17 -> Ashoka India Equity Investment Trust | C17: =Data!D17 -> Financials | D17: =Data!E17 -> Exclude | E17: =IF($D17<>"Include","",SUM(Data!V17:W17)-SUM(Data!X17)) | F17: =IF($D17<>"Include","",SUM(Data!Z17,Data!Y17,Metrics!E17)) | G17: =IF($D17<>"Include","",IFERROR(Data!P17-Data!S17,"")) | H17: =IF($D17<>"Include","",IFERROR(SUM(Data!P17:R17)-SUM(Data!S17:U17),"")) | I17: =IF($D17<>"Include","",SUM(Data!M17:O17)) | J17: =IF($D17<>"Include","",IFERROR(IF(OR(Data!K17<=0,F17<=0),"n/m",($F17/Data!K17)),"")) | K17: =IF($D17<>"Include","",IFERROR(G17/Data!Z17,"")) | L17: =IF($D17<>"Include","",IFERROR(IF(I17<=0,"n/m",H17/I17),"")) | M17: =IF($D17<>"Include","",IFERROR(IF(Data!L17<=0,"n,m",E17/Data!L17),"")) | N17: =IF($D17<>"Include","",IFERROR(IF(OR(Data!I17<=0,Data!J17<=0),"n/m",(Data!I17/Data!J17)^(1/3)-1),"")) | O17: =IF($D17<>"Include","",IF(ISNUMBER(J17),_xlfn.RANK.EQ(J17,J$6:J$305,O$4),N_Co)) | P17: =IF($D17<>"Include","",IF(ISNUMBER(K17),_xlfn.RANK.EQ(K17,K$6:K$305,P$4),N_Co)) | Q17: =IF($D17<>"Include","",IF(ISNUMBER(L17),_xlfn.RANK.EQ(L17,L$6:L$305,Q$4),N_Co)) | R17: =IF($D17<>"Include","",IF(ISNUMBER(M17),_xlfn.RANK.EQ(M17,M$6:M$305,R$4),N_Co)) | S17: =IF($D17<>"Include","",IF(ISNUMBER(N17),_xlfn.RANK.EQ(N17,N$6:N$305,S$4),N_Co)) | T17: =IF($D17<>"Include","",ROUND(SUMPRODUCT(O17:S17,$O$3:$S$3),6)) | U17: =IF($D17<>"Include","",_xlfn.RANK.EQ(T17,T$6:T$305,1)+COUNTIFS(T$6:T17,T17)-1)
... A305: =Data!A305 | B305: =Data!B305 | C305: =Data!D305 | D305: =Data!E305 | E305: =IF($D305<>"Include","",SUM(Data!V305:W305)-SUM(Data!X305)) | F305: =IF($D305<>"Include","",SUM(Data!Z305,Data!Y305,Metrics!E305)) | G305: =IF($D305<>"Include","",IFERROR(Data!P305-Data!S305,"")) | H305: =IF($D305<>"Include","",IFERROR(SUM(Data!P305:R305)-SUM(Data!S305:U305),"")) | I305: =IF($D305<>"Include","",SUM(Data!M305:O305)) | J305: =IF($D305<>"Include","",IFERROR(IF(OR(Data!K305<=0,F305<=0),"n/m",($F305/Data!K305)),"")) | K305: =IF($D305<>"Include","",IFERROR(G305/Data!Z305,"")) | L305: =IF($D305<>"Include","",IFERROR(IF(I305<=0,"n/m",H305/I305),"")) | M305: =IF($D305<>"Include","",IFERROR(IF(Data!L305<=0,"n,m",E305/Data!L305),"")) | N305: =IF($D305<>"Include","",IFERROR(IF(OR(Data!I305<=0,Data!J305<=0),"n/m",(Data!I305/Data!J305)^(1/3)-1),"")) | O305: =IF($D305<>"Include","",IF(ISNUMBER(J305),_xlfn.RANK.EQ(J305,J$6:J$305,O$4),N_Co)) | P305: =IF($D305<>"Include","",IF(ISNUMBER(K305),_xlfn.RANK.EQ(K305,K$6:K$305,P$4),N_Co)) | Q305: =IF($D305<>"Include","",IF(ISNUMBER(L305),_xlfn.RANK.EQ(L305,L$6:L$305,Q$4),N_Co)) | R305: =IF($D305<>"Include","",IF(ISNUMBER(M305),_xlfn.RANK.EQ(M305,M$6:M$305,R$4),N_Co)) | S305: =IF($D305<>"Include","",IF(ISNUMBER(N305),_xlfn.RANK.EQ(N305,N$6:N$305,S$4),N_Co)) | T305: =IF($D305<>"Include","",ROUND(SUMPRODUCT(O305:S305,$O$3:$S$3),6)) | U305: =IF($D305<>"Include","",_xlfn.RANK.EQ(T305,T$6:T$305,1)+COUNTIFS(T$6:T305,T305)-1)

Sheet Screen
A1: FTSE 250 Value Screen
B2: =Checks!C3 -> Fix issues on Checks sheet
B3: ="Prices as at "&TEXT(ScreenDate,"dd mmm yyyy")&", "& N_Co&" companies ranked" -> Prices as at 30 Sep 2026, 119 companies ranked
A5: Rank | B5: Ticker | C5: Company | D5: Sector | E5: EV £m | F5: EV/EBIT | G5: FCF yield | H5: Cash conversion | I5: Net debt/EBITDA | J5: Revenue CAGR | K5: Composite score | L5: Rank EV/EBIT | M5: Rank FCF yield | N5: Rank cash conversion | O5: Rank leverage | P5: Rank growth
A6: =IF(N_Co>=1,1,"") -> 1 | B6: =IF($A6="","",INDEX(Metrics!$A$6:$U$305,MATCH($A6,Metrics!$U$6:$U$305,0),MATCH(B$5,Metrics!$A$5:$U$5,0))) -> FOUR | C6: =IF($A6="","",INDEX(Metrics!$A$6:$U$305,MATCH($A6,Metrics!$U$6:$U$305,0),MATCH(C$5,Metrics!$A$5:$U$5,0))) -> 4imprint | D6: =IF($A6="","",INDEX(Metrics!$A$6:$U$305,MATCH($A6,Metrics!$U$6:$U$305,0),MATCH(D$5,Metrics!$A$5:$U$5,0))) -> Consumer Discretionary | E6: =IF($A6="","",INDEX(Metrics!$A$6:$U$305,MATCH($A6,Metrics!$U$6:$U$305,0),MATCH(E$5,Metrics!$A$5:$U$5,0))) -> #N/A | F6: =IF($A6="","",INDEX(Metrics!$A$6:$U$305,MATCH($A6,Metrics!$U$6:$U$305,0),MATCH(F$5,Metrics!$A$5:$U$5,0))) | G6: =IF($A6="","",INDEX(Metrics!$A$6:$U$305,MATCH($A6,Metrics!$U$6:$U$305,0),MATCH(G$5,Metrics!$A$5:$U$5,0))) | H6: =IF($A6="","",INDEX(Metrics!$A$6:$U$305,MATCH($A6,Metrics!$U$6:$U$305,0),MATCH(H$5,Metrics!$A$5:$U$5,0))) -> n/m | I6: =IF($A6="","",INDEX(Metrics!$A$6:$U$305,MATCH($A6,Metrics!$U$6:$U$305,0),MATCH(I$5,Metrics!$A$5:$U$5,0))) | ... P6: =IF($A6="","",INDEX(Metrics!$A$6:$U$305,MATCH($A6,Metrics!$U$6:$U$305,0),MATCH(P$5,Metrics!$A$5:$U$5,0))) -> 119
A7: =IF($A6="","",IF($A6+1>N_Co,"",$A6+1)) -> 2 | B7: =IF($A7="","",INDEX(Metrics!$A$6:$U$305,MATCH($A7,Metrics!$U$6:$U$305,0),MATCH(B$5,Metrics!$A$5:$U$5,0))) -> AEP | C7: =IF($A7="","",INDEX(Metrics!$A$6:$U$305,MATCH($A7,Metrics!$U$6:$U$305,0),MATCH(C$5,Metrics!$A$5:$U$5,0))) -> AEP Plantations | D7: =IF($A7="","",INDEX(Metrics!$A$6:$U$305,MATCH($A7,Metrics!$U$6:$U$305,0),MATCH(D$5,Metrics!$A$5:$U$5,0))) -> Consumer Staples | E7: =IF($A7="","",INDEX(Metrics!$A$6:$U$305,MATCH($A7,Metrics!$U$6:$U$305,0),MATCH(E$5,Metrics!$A$5:$U$5,0))) -> #N/A | F7: =IF($A7="","",INDEX(Metrics!$A$6:$U$305,MATCH($A7,Metrics!$U$6:$U$305,0),MATCH(F$5,Metrics!$A$5:$U$5,0))) | G7: =IF($A7="","",INDEX(Metrics!$A$6:$U$305,MATCH($A7,Metrics!$U$6:$U$305,0),MATCH(G$5,Metrics!$A$5:$U$5,0))) | H7: =IF($A7="","",INDEX(Metrics!$A$6:$U$305,MATCH($A7,Metrics!$U$6:$U$305,0),MATCH(H$5,Metrics!$A$5:$U$5,0))) -> n/m | I7: =IF($A7="","",INDEX(Metrics!$A$6:$U$305,MATCH($A7,Metrics!$U$6:$U$305,0),MATCH(I$5,Metrics!$A$5:$U$5,0))) | ... P7: =IF($A7="","",INDEX(Metrics!$A$6:$U$305,MATCH($A7,Metrics!$U$6:$U$305,0),MATCH(P$5,Metrics!$A$5:$U$5,0))) -> 119
A8: =IF($A7="","",IF($A7+1>N_Co,"",$A7+1)) -> 3 | B8: =IF($A8="","",INDEX(Metrics!$A$6:$U$305,MATCH($A8,Metrics!$U$6:$U$305,0),MATCH(B$5,Metrics!$A$5:$U$5,0))) -> ALFA | C8: =IF($A8="","",INDEX(Metrics!$A$6:$U$305,MATCH($A8,Metrics!$U$6:$U$305,0),MATCH(C$5,Metrics!$A$5:$U$5,0))) -> Alfa Financial Software | D8: =IF($A8="","",INDEX(Metrics!$A$6:$U$305,MATCH($A8,Metrics!$U$6:$U$305,0),MATCH(D$5,Metrics!$A$5:$U$5,0))) -> Technology | E8: =IF($A8="","",INDEX(Metrics!$A$6:$U$305,MATCH($A8,Metrics!$U$6:$U$305,0),MATCH(E$5,Metrics!$A$5:$U$5,0))) -> #N/A | F8: =IF($A8="","",INDEX(Metrics!$A$6:$U$305,MATCH($A8,Metrics!$U$6:$U$305,0),MATCH(F$5,Metrics!$A$5:$U$5,0))) | G8: =IF($A8="","",INDEX(Metrics!$A$6:$U$305,MATCH($A8,Metrics!$U$6:$U$305,0),MATCH(G$5,Metrics!$A$5:$U$5,0))) | H8: =IF($A8="","",INDEX(Metrics!$A$6:$U$305,MATCH($A8,Metrics!$U$6:$U$305,0),MATCH(H$5,Metrics!$A$5:$U$5,0))) -> n/m | I8: =IF($A8="","",INDEX(Metrics!$A$6:$U$305,MATCH($A8,Metrics!$U$6:$U$305,0),MATCH(I$5,Metrics!$A$5:$U$5,0))) | ... P8: =IF($A8="","",INDEX(Metrics!$A$6:$U$305,MATCH($A8,Metrics!$U$6:$U$305,0),MATCH(P$5,Metrics!$A$5:$U$5,0))) -> 119
A9: =IF($A8="","",IF($A8+1>N_Co,"",$A8+1)) -> 4 | B9: =IF($A9="","",INDEX(Metrics!$A$6:$U$305,MATCH($A9,Metrics!$U$6:$U$305,0),MATCH(B$5,Metrics!$A$5:$U$5,0))) -> AO | C9: =IF($A9="","",INDEX(Metrics!$A$6:$U$305,MATCH($A9,Metrics!$U$6:$U$305,0),MATCH(C$5,Metrics!$A$5:$U$5,0))) -> AO World | D9: =IF($A9="","",INDEX(Metrics!$A$6:$U$305,MATCH($A9,Metrics!$U$6:$U$305,0),MATCH(D$5,Metrics!$A$5:$U$5,0))) -> Consumer Discretionary | E9: =IF($A9="","",INDEX(Metrics!$A$6:$U$305,MATCH($A9,Metrics!$U$6:$U$305,0),MATCH(E$5,Metrics!$A$5:$U$5,0))) -> #N/A | F9: =IF($A9="","",INDEX(Metrics!$A$6:$U$305,MATCH($A9,Metrics!$U$6:$U$305,0),MATCH(F$5,Metrics!$A$5:$U$5,0))) | G9: =IF($A9="","",INDEX(Metrics!$A$6:$U$305,MATCH($A9,Metrics!$U$6:$U$305,0),MATCH(G$5,Metrics!$A$5:$U$5,0))) | H9: =IF($A9="","",INDEX(Metrics!$A$6:$U$305,MATCH($A9,Metrics!$U$6:$U$305,0),MATCH(H$5,Metrics!$A$5:$U$5,0))) -> n/m | I9: =IF($A9="","",INDEX(Metrics!$A$6:$U$305,MATCH($A9,Metrics!$U$6:$U$305,0),MATCH(I$5,Metrics!$A$5:$U$5,0))) | ... P9: =IF($A9="","",INDEX(Metrics!$A$6:$U$305,MATCH($A9,Metrics!$U$6:$U$305,0),MATCH(P$5,Metrics!$A$5:$U$5,0))) -> 119
A10: =IF($A9="","",IF($A9+1>N_Co,"",$A9+1)) -> 5 | B10: =IF($A10="","",INDEX(Metrics!$A$6:$U$305,MATCH($A10,Metrics!$U$6:$U$305,0),MATCH(B$5,Metrics!$A$5:$U$5,0))) -> APN | C10: =IF($A10="","",INDEX(Metrics!$A$6:$U$305,MATCH($A10,Metrics!$U$6:$U$305,0),MATCH(C$5,Metrics!$A$5:$U$5,0))) -> Applied Nutrition | D10: =IF($A10="","",INDEX(Metrics!$A$6:$U$305,MATCH($A10,Metrics!$U$6:$U$305,0),MATCH(D$5,Metrics!$A$5:$U$5,0))) -> Consumer Staples | E10: =IF($A10="","",INDEX(Metrics!$A$6:$U$305,MATCH($A10,Metrics!$U$6:$U$305,0),MATCH(E$5,Metrics!$A$5:$U$5,0))) -> #N/A | F10: =IF($A10="","",INDEX(Metrics!$A$6:$U$305,MATCH($A10,Metrics!$U$6:$U$305,0),MATCH(F$5,Metrics!$A$5:$U$5,0))) | G10: =IF($A10="","",INDEX(Metrics!$A$6:$U$305,MATCH($A10,Metrics!$U$6:$U$305,0),MATCH(G$5,Metrics!$A$5:$U$5,0))) | H10: =IF($A10="","",INDEX(Metrics!$A$6:$U$305,MATCH($A10,Metrics!$U$6:$U$305,0),MATCH(H$5,Metrics!$A$5:$U$5,0))) -> n/m | I10: =IF($A10="","",INDEX(Metrics!$A$6:$U$305,MATCH($A10,Metrics!$U$6:$U$305,0),MATCH(I$5,Metrics!$A$5:$U$5,0))) | ... P10: =IF($A10="","",INDEX(Metrics!$A$6:$U$305,MATCH($A10,Metrics!$U$6:$U$305,0),MATCH(P$5,Metrics!$A$5:$U$5,0))) -> 119
A11: =IF($A10="","",IF($A10+1>N_Co,"",$A10+1)) -> 6 | B11: =IF($A11="","",INDEX(Metrics!$A$6:$U$305,MATCH($A11,Metrics!$U$6:$U$305,0),MATCH(B$5,Metrics!$A$5:$U$5,0))) -> ASC | C11: =IF($A11="","",INDEX(Metrics!$A$6:$U$305,MATCH($A11,Metrics!$U$6:$U$305,0),MATCH(C$5,Metrics!$A$5:$U$5,0))) -> ASOS | D11: =IF($A11="","",INDEX(Metrics!$A$6:$U$305,MATCH($A11,Metrics!$U$6:$U$305,0),MATCH(D$5,Metrics!$A$5:$U$5,0))) -> Consumer Discretionary | E11: =IF($A11="","",INDEX(Metrics!$A$6:$U$305,MATCH($A11,Metrics!$U$6:$U$305,0),MATCH(E$5,Metrics!$A$5:$U$5,0))) -> #N/A | F11: =IF($A11="","",INDEX(Metrics!$A$6:$U$305,MATCH($A11,Metrics!$U$6:$U$305,0),MATCH(F$5,Metrics!$A$5:$U$5,0))) | G11: =IF($A11="","",INDEX(Metrics!$A$6:$U$305,MATCH($A11,Metrics!$U$6:$U$305,0),MATCH(G$5,Metrics!$A$5:$U$5,0))) | H11: =IF($A11="","",INDEX(Metrics!$A$6:$U$305,MATCH($A11,Metrics!$U$6:$U$305,0),MATCH(H$5,Metrics!$A$5:$U$5,0))) -> n/m | I11: =IF($A11="","",INDEX(Metrics!$A$6:$U$305,MATCH($A11,Metrics!$U$6:$U$305,0),MATCH(I$5,Metrics!$A$5:$U$5,0))) | ... P11: =IF($A11="","",INDEX(Metrics!$A$6:$U$305,MATCH($A11,Metrics!$U$6:$U$305,0),MATCH(P$5,Metrics!$A$5:$U$5,0))) -> 119
A12: =IF($A11="","",IF($A11+1>N_Co,"",$A11+1)) -> 7 | B12: =IF($A12="","",INDEX(Metrics!$A$6:$U$305,MATCH($A12,Metrics!$U$6:$U$305,0),MATCH(B$5,Metrics!$A$5:$U$5,0))) -> ATYM | C12: =IF($A12="","",INDEX(Metrics!$A$6:$U$305,MATCH($A12,Metrics!$U$6:$U$305,0),MATCH(C$5,Metrics!$A$5:$U$5,0))) -> Atalaya Mining | D12: =IF($A12="","",INDEX(Metrics!$A$6:$U$305,MATCH($A12,Metrics!$U$6:$U$305,0),MATCH(D$5,Metrics!$A$5:$U$5,0))) -> Basic Materials | E12: =IF($A12="","",INDEX(Metrics!$A$6:$U$305,MATCH($A12,Metrics!$U$6:$U$305,0),MATCH(E$5,Metrics!$A$5:$U$5,0))) -> #N/A | F12: =IF($A12="","",INDEX(Metrics!$A$6:$U$305,MATCH($A12,Metrics!$U$6:$U$305,0),MATCH(F$5,Metrics!$A$5:$U$5,0))) | G12: =IF($A12="","",INDEX(Metrics!$A$6:$U$305,MATCH($A12,Metrics!$U$6:$U$305,0),MATCH(G$5,Metrics!$A$5:$U$5,0))) | H12: =IF($A12="","",INDEX(Metrics!$A$6:$U$305,MATCH($A12,Metrics!$U$6:$U$305,0),MATCH(H$5,Metrics!$A$5:$U$5,0))) -> n/m | I12: =IF($A12="","",INDEX(Metrics!$A$6:$U$305,MATCH($A12,Metrics!$U$6:$U$305,0),MATCH(I$5,Metrics!$A$5:$U$5,0))) | ... P12: =IF($A12="","",INDEX(Metrics!$A$6:$U$305,MATCH($A12,Metrics!$U$6:$U$305,0),MATCH(P$5,Metrics!$A$5:$U$5,0))) -> 119
A13: =IF($A12="","",IF($A12+1>N_Co,"",$A12+1)) -> 8 | B13: =IF($A13="","",INDEX(Metrics!$A$6:$U$305,MATCH($A13,Metrics!$U$6:$U$305,0),MATCH(B$5,Metrics!$A$5:$U$5,0))) -> ATG | C13: =IF($A13="","",INDEX(Metrics!$A$6:$U$305,MATCH($A13,Metrics!$U$6:$U$305,0),MATCH(C$5,Metrics!$A$5:$U$5,0))) -> Auction Technology Group | D13: =IF($A13="","",INDEX(Metrics!$A$6:$U$305,MATCH($A13,Metrics!$U$6:$U$305,0),MATCH(D$5,Metrics!$A$5:$U$5,0))) -> Technology | E13: =IF($A13="","",INDEX(Metrics!$A$6:$U$305,MATCH($A13,Metrics!$U$6:$U$305,0),MATCH(E$5,Metrics!$A$5:$U$5,0))) -> #N/A | F13: =IF($A13="","",INDEX(Metrics!$A$6:$U$305,MATCH($A13,Metrics!$U$6:$U$305,0),MATCH(F$5,Metrics!$A$5:$U$5,0))) | G13: =IF($A13="","",INDEX(Metrics!$A$6:$U$305,MATCH($A13,Metrics!$U$6:$U$305,0),MATCH(G$5,Metrics!$A$5:$U$5,0))) | H13: =IF($A13="","",INDEX(Metrics!$A$6:$U$305,MATCH($A13,Metrics!$U$6:$U$305,0),MATCH(H$5,Metrics!$A$5:$U$5,0))) -> n/m | I13: =IF($A13="","",INDEX(Metrics!$A$6:$U$305,MATCH($A13,Metrics!$U$6:$U$305,0),MATCH(I$5,Metrics!$A$5:$U$5,0))) | ... P13: =IF($A13="","",INDEX(Metrics!$A$6:$U$305,MATCH($A13,Metrics!$U$6:$U$305,0),MATCH(P$5,Metrics!$A$5:$U$5,0))) -> 119
A14: =IF($A13="","",IF($A13+1>N_Co,"",$A13+1)) -> 9 | B14: =IF($A14="","",INDEX(Metrics!$A$6:$U$305,MATCH($A14,Metrics!$U$6:$U$305,0),MATCH(B$5,Metrics!$A$5:$U$5,0))) -> AVON | C14: =IF($A14="","",INDEX(Metrics!$A$6:$U$305,MATCH($A14,Metrics!$U$6:$U$305,0),MATCH(C$5,Metrics!$A$5:$U$5,0))) -> Avon Technologies | D14: =IF($A14="","",INDEX(Metrics!$A$6:$U$305,MATCH($A14,Metrics!$U$6:$U$305,0),MATCH(D$5,Metrics!$A$5:$U$5,0))) -> Industrials | E14: =IF($A14="","",INDEX(Metrics!$A$6:$U$305,MATCH($A14,Metrics!$U$6:$U$305,0),MATCH(E$5,Metrics!$A$5:$U$5,0))) -> #N/A | F14: =IF($A14="","",INDEX(Metrics!$A$6:$U$305,MATCH($A14,Metrics!$U$6:$U$305,0),MATCH(F$5,Metrics!$A$5:$U$5,0))) | G14: =IF($A14="","",INDEX(Metrics!$A$6:$U$305,MATCH($A14,Metrics!$U$6:$U$305,0),MATCH(G$5,Metrics!$A$5:$U$5,0))) | H14: =IF($A14="","",INDEX(Metrics!$A$6:$U$305,MATCH($A14,Metrics!$U$6:$U$305,0),MATCH(H$5,Metrics!$A$5:$U$5,0))) -> n/m | I14: =IF($A14="","",INDEX(Metrics!$A$6:$U$305,MATCH($A14,Metrics!$U$6:$U$305,0),MATCH(I$5,Metrics!$A$5:$U$5,0))) | ... P14: =IF($A14="","",INDEX(Metrics!$A$6:$U$305,MATCH($A14,Metrics!$U$6:$U$305,0),MATCH(P$5,Metrics!$A$5:$U$5,0))) -> 119
A15: =IF($A14="","",IF($A14+1>N_Co,"",$A14+1)) -> 10 | B15: =IF($A15="","",INDEX(Metrics!$A$6:$U$305,MATCH($A15,Metrics!$U$6:$U$305,0),MATCH(B$5,Metrics!$A$5:$U$5,0))) -> BME | C15: =IF($A15="","",INDEX(Metrics!$A$6:$U$305,MATCH($A15,Metrics!$U$6:$U$305,0),MATCH(C$5,Metrics!$A$5:$U$5,0))) -> B&M | D15: =IF($A15="","",INDEX(Metrics!$A$6:$U$305,MATCH($A15,Metrics!$U$6:$U$305,0),MATCH(D$5,Metrics!$A$5:$U$5,0))) -> Consumer Discretionary | E15: =IF($A15="","",INDEX(Metrics!$A$6:$U$305,MATCH($A15,Metrics!$U$6:$U$305,0),MATCH(E$5,Metrics!$A$5:$U$5,0))) -> #N/A | F15: =IF($A15="","",INDEX(Metrics!$A$6:$U$305,MATCH($A15,Metrics!$U$6:$U$305,0),MATCH(F$5,Metrics!$A$5:$U$5,0))) | G15: =IF($A15="","",INDEX(Metrics!$A$6:$U$305,MATCH($A15,Metrics!$U$6:$U$305,0),MATCH(G$5,Metrics!$A$5:$U$5,0))) | H15: =IF($A15="","",INDEX(Metrics!$A$6:$U$305,MATCH($A15,Metrics!$U$6:$U$305,0),MATCH(H$5,Metrics!$A$5:$U$5,0))) -> n/m | I15: =IF($A15="","",INDEX(Metrics!$A$6:$U$305,MATCH($A15,Metrics!$U$6:$U$305,0),MATCH(I$5,Metrics!$A$5:$U$5,0))) | ... P15: =IF($A15="","",INDEX(Metrics!$A$6:$U$305,MATCH($A15,Metrics!$U$6:$U$305,0),MATCH(P$5,Metrics!$A$5:$U$5,0))) -> 119
A16: =IF($A15="","",IF($A15+1>N_Co,"",$A15+1)) -> 11 | B16: =IF($A16="","",INDEX(Metrics!$A$6:$U$305,MATCH($A16,Metrics!$U$6:$U$305,0),MATCH(B$5,Metrics!$A$5:$U$5,0))) -> BCG | C16: =IF($A16="","",INDEX(Metrics!$A$6:$U$305,MATCH($A16,Metrics!$U$6:$U$305,0),MATCH(C$5,Metrics!$A$5:$U$5,0))) -> Baltic Classifieds | D16: =IF($A16="","",INDEX(Metrics!$A$6:$U$305,MATCH($A16,Metrics!$U$6:$U$305,0),MATCH(D$5,Metrics!$A$5:$U$5,0))) -> Consumer Discretionary | E16: =IF($A16="","",INDEX(Metrics!$A$6:$U$305,MATCH($A16,Metrics!$U$6:$U$305,0),MATCH(E$5,Metrics!$A$5:$U$5,0))) -> #N/A | F16: =IF($A16="","",INDEX(Metrics!$A$6:$U$305,MATCH($A16,Metrics!$U$6:$U$305,0),MATCH(F$5,Metrics!$A$5:$U$5,0))) | G16: =IF($A16="","",INDEX(Metrics!$A$6:$U$305,MATCH($A16,Metrics!$U$6:$U$305,0),MATCH(G$5,Metrics!$A$5:$U$5,0))) | H16: =IF($A16="","",INDEX(Metrics!$A$6:$U$305,MATCH($A16,Metrics!$U$6:$U$305,0),MATCH(H$5,Metrics!$A$5:$U$5,0))) -> n/m | I16: =IF($A16="","",INDEX(Metrics!$A$6:$U$305,MATCH($A16,Metrics!$U$6:$U$305,0),MATCH(I$5,Metrics!$A$5:$U$5,0))) | ... P16: =IF($A16="","",INDEX(Metrics!$A$6:$U$305,MATCH($A16,Metrics!$U$6:$U$305,0),MATCH(P$5,Metrics!$A$5:$U$5,0))) -> 119
A17: =IF($A16="","",IF($A16+1>N_Co,"",$A16+1)) -> 12 | B17: =IF($A17="","",INDEX(Metrics!$A$6:$U$305,MATCH($A17,Metrics!$U$6:$U$305,0),MATCH(B$5,Metrics!$A$5:$U$5,0))) -> BAG | C17: =IF($A17="","",INDEX(Metrics!$A$6:$U$305,MATCH($A17,Metrics!$U$6:$U$305,0),MATCH(C$5,Metrics!$A$5:$U$5,0))) -> A.G. Barr | D17: =IF($A17="","",INDEX(Metrics!$A$6:$U$305,MATCH($A17,Metrics!$U$6:$U$305,0),MATCH(D$5,Metrics!$A$5:$U$5,0))) -> Consumer Staples | E17: =IF($A17="","",INDEX(Metrics!$A$6:$U$305,MATCH($A17,Metrics!$U$6:$U$305,0),MATCH(E$5,Metrics!$A$5:$U$5,0))) -> #N/A | F17: =IF($A17="","",INDEX(Metrics!$A$6:$U$305,MATCH($A17,Metrics!$U$6:$U$305,0),MATCH(F$5,Metrics!$A$5:$U$5,0))) | G17: =IF($A17="","",INDEX(Metrics!$A$6:$U$305,MATCH($A17,Metrics!$U$6:$U$305,0),MATCH(G$5,Metrics!$A$5:$U$5,0))) | H17: =IF($A17="","",INDEX(Metrics!$A$6:$U$305,MATCH($A17,Metrics!$U$6:$U$305,0),MATCH(H$5,Metrics!$A$5:$U$5,0))) -> n/m | I17: =IF($A17="","",INDEX(Metrics!$A$6:$U$305,MATCH($A17,Metrics!$U$6:$U$305,0),MATCH(I$5,Metrics!$A$5:$U$5,0))) | ... P17: =IF($A17="","",INDEX(Metrics!$A$6:$U$305,MATCH($A17,Metrics!$U$6:$U$305,0),MATCH(P$5,Metrics!$A$5:$U$5,0))) -> 119
A18: =IF($A17="","",IF($A17+1>N_Co,"",$A17+1)) -> 13 | B18: =IF($A18="","",INDEX(Metrics!$A$6:$U$305,MATCH($A18,Metrics!$U$6:$U$305,0),MATCH(B$5,Metrics!$A$5:$U$5,0))) -> BWY | C18: =IF($A18="","",INDEX(Metrics!$A$6:$U$305,MATCH($A18,Metrics!$U$6:$U$305,0),MATCH(C$5,Metrics!$A$5:$U$5,0))) -> Bellway | D18: =IF($A18="","",INDEX(Metrics!$A$6:$U$305,MATCH($A18,Metrics!$U$6:$U$305,0),MATCH(D$5,Metrics!$A$5:$U$5,0))) -> Consumer Discretionary | E18: =IF($A18="","",INDEX(Metrics!$A$6:$U$305,MATCH($A18,Metrics!$U$6:$U$305,0),MATCH(E$5,Metrics!$A$5:$U$5,0))) -> #N/A | F18: =IF($A18="","",INDEX(Metrics!$A$6:$U$305,MATCH($A18,Metrics!$U$6:$U$305,0),MATCH(F$5,Metrics!$A$5:$U$5,0))) | G18: =IF($A18="","",INDEX(Metrics!$A$6:$U$305,MATCH($A18,Metrics!$U$6:$U$305,0),MATCH(G$5,Metrics!$A$5:$U$5,0))) | H18: =IF($A18="","",INDEX(Metrics!$A$6:$U$305,MATCH($A18,Metrics!$U$6:$U$305,0),MATCH(H$5,Metrics!$A$5:$U$5,0))) -> n/m | I18: =IF($A18="","",INDEX(Metrics!$A$6:$U$305,MATCH($A18,Metrics!$U$6:$U$305,0),MATCH(I$5,Metrics!$A$5:$U$5,0))) | ... P18: =IF($A18="","",INDEX(Metrics!$A$6:$U$305,MATCH($A18,Metrics!$U$6:$U$305,0),MATCH(P$5,Metrics!$A$5:$U$5,0))) -> 119
... A305: =IF($A304="","",IF($A304+1>N_Co,"",$A304+1)) | B305: =IF($A305="","",INDEX(Metrics!$A$6:$U$305,MATCH($A305,Metrics!$U$6:$U$305,0),MATCH(B$5,Metrics!$A$5:$U$5,0))) | C305: =IF($A305="","",INDEX(Metrics!$A$6:$U$305,MATCH($A305,Metrics!$U$6:$U$305,0),MATCH(C$5,Metrics!$A$5:$U$5,0))) | D305: =IF($A305="","",INDEX(Metrics!$A$6:$U$305,MATCH($A305,Metrics!$U$6:$U$305,0),MATCH(D$5,Metrics!$A$5:$U$5,0))) | E305: =IF($A305="","",INDEX(Metrics!$A$6:$U$305,MATCH($A305,Metrics!$U$6:$U$305,0),MATCH(E$5,Metrics!$A$5:$U$5,0))) | F305: =IF($A305="","",INDEX(Metrics!$A$6:$U$305,MATCH($A305,Metrics!$U$6:$U$305,0),MATCH(F$5,Metrics!$A$5:$U$5,0))) | G305: =IF($A305="","",INDEX(Metrics!$A$6:$U$305,MATCH($A305,Metrics!$U$6:$U$305,0),MATCH(G$5,Metrics!$A$5:$U$5,0))) | H305: =IF($A305="","",INDEX(Metrics!$A$6:$U$305,MATCH($A305,Metrics!$U$6:$U$305,0),MATCH(H$5,Metrics!$A$5:$U$5,0))) | I305: =IF($A305="","",INDEX(Metrics!$A$6:$U$305,MATCH($A305,Metrics!$U$6:$U$305,0),MATCH(I$5,Metrics!$A$5:$U$5,0))) | ... P305: =IF($A305="","",INDEX(Metrics!$A$6:$U$305,MATCH($A305,Metrics!$U$6:$U$305,0),MATCH(P$5,Metrics!$A$5:$U$5,0)))

Sheet Checks
A1: Checks
B3: Overall | C3: =IF(COUNTIF(D6:D13,"CHECK")=0,"All checks OK","Fix issues on Checks sheet") -> Fix issues on Checks sheet
B5: Test | C5: Result | D5: Status
B6: Weights add up to 100% | C6: =Inputs!C9 -> 1 | D6: =IF(ROUND(C6,6)=1,"OK","CHECK") -> OK
B7: Companies included | C7: =N_Co -> 119 | D7: =IF(C7>0,"OK","CHECK") -> OK
B8: Included but no fundamentals | C8: =COUNTIFS(Data!$E$6:$E$305,"Include",Data!$F$6:$F$305,"") -> 119 | D8: =IF(C8=0,"OK","CHECK") -> CHECK
B9: Included but no market cap | C9: =COUNTIFS(Data!$E$6:$E$305,"Include",Data!$Z$6:$Z$305,"") -> 0 | D9: =IF(C9=0,"OK","CHECK") -> OK
B10: Currencies missing from FX table | C10: =COUNTIF(Data!$H$6:$H$305,"Missing FX") -> 0 | D10: =IF(C10=0,"OK","CHECK") -> OK
B11: Market caps over £20bn (pence error?) | C11: =COUNTIF(Data!$Z$6:$Z$305,">20000") -> 0 | D11: =IF(C11=0,"OK","CHECK") -> OK
B12: Companies with a final rank | C12: =COUNT(Metrics!$U$6:$U$305) -> 119 | D12: =IF(AND(C12=N_Co,MAX(Metrics!$U$6:$U$305)=N_Co),"OK","CHECK") -> OK
B13: Error cells on Metrics | C13: {=SUMPRODUCT(--ISERROR(Metrics!$A$6:$U$305))} -> 119 | D13: =IF(C13=0,"OK","CHECK") -> CHECK

Sheet Notes
A1: Universe
B2: Index Basis | C2: FTSE 250 constituents
B3: Exclusions | C3: Financials (banks, insurers, REITs, etc.) and Real Estate
B4: Overrides | C4: Amaroq and Meridian Mining excluded: no accounts in Compustat
B5: Companies ranked | C5: 119
A7: Data
B8: Fundamentals | C8: WRDS Compustat Global, Fundamentals Annual. Fiscal years 2020 to 2026
C9: Prices and shares | D9: WRDS Compustat Global, Security Daily, LSE listing, 30 September 2026
C10: Company matching | D10: ISINs matched to Compustat by Company name, done by hand
C11: Currency | D11: All figures in GBP millions, non sterling financials converted at BoE spot rates on 30 Sep 2026
A13: Metrics
B14: EV/EBIT | C14: (Market cap + net debt + minority interest) / EBIT, latest fiscal year
B15: FCF yield | C15: (Operating cash flow - capex) / market cap, latest fiscal year
B16: Cash conversion | C16: 3-year free cash flow / 3 year net income
B17: Net debt / EBITDA | C17: (Long term debt + short term debt - cash) / EBITDA, latest fiscal year
B18: Revenue CAGR | C18: 3 year compound annual revenue growth
B19: Not meaningful (n/m) | C19: Negative EV/EBIT Values marked n/m , negative cash conversion marked n/m, leverage if EBITDA negative marked n/m
A21: Scoring | B21: Method | C21: Each metric ranked across included companies. 1 = Best Ranked. Composite = weighted average of the 5 ranks; lowest composite ranks first. Ties broken by alphabetical order, both investigated.
B22: Weights | C22: EV/EBIT 30%. FCF yield 25%, Cash Conversion 20%, Net debt/EBITDA 15%, Revenue CAGR 10%
B23: Missing data | C23: A missing or n/m metric gets the worst rank for that metric
A25: Limitations
B26: Stale accounts | C26: Uses the latest published fiscal year, which could be up to 18 months old
B27: Single year | C27: EV/EBIT and FCF yield use one year, so an irregular year could affect ranking.
B28: Minority interest | C28: Taken from Compustat's total noncontrolling interest; blank treated as 0
B29: Index List | C29: Constituent list was not an official FTSE Russell File, Source: Wikipedia FTSE 250 Index page
A32: WRDS Data Removed to comply with WRDS usage policy.
A33: Paste needed from Compustat Global Fundamentals Annual export into Raw_fund from E1 and a Security Daily Export into Raw_Mkt from D1 to run screen
